[
    {
        "id": 29544,
        "name": "",
        "username": "Boko",
        "avatar_template": "/letter_avatar_proxy/v4/letter/b/e480ec/{size}.png",
        "created_at": "2024-08-03T16:43:11.535Z",
        "cooked": "<p><div class=\"lightbox-wrapper\"><a class=\"lightbox\" href=\"ошибка-в-goodbyedpiскриншот-прикрепил-8628/eda37815f0142185d34a5c9d3ff5976af6b11f9b.png\" data-download-href=\"https://ntc.party/uploads/default/eda37815f0142185d34a5c9d3ff5976af6b11f9b\" title=\"image\"><img src=\"ошибка-в-goodbyedpiскриншот-прикрепил-8628/eda37815f0142185d34a5c9d3ff5976af6b11f9b.png\" alt=\"image\" data-base62-sha1=\"xUfogwrCc2mDvtBWXAjZmg0cfYT\" width=\"690\" height=\"137\" data-dominant-color=\"141313\"><div class=\"meta\"><svg class=\"fa d-icon d-icon-far-image svg-icon\" aria-hidden=\"true\"><use href=\"#far-image\"></use></svg><span class=\"filename\">image</span><span class=\"informations\">961×192 10.4 KB</span><svg class=\"fa d-icon d-icon-discourse-expand svg-icon\" aria-hidden=\"true\"><use href=\"#discourse-expand\"></use></svg></div></a></div></p>",
        "post_number": 1,
        "post_type": 1,
        "posts_count": 7,
        "updated_at": "2024-08-03T16:43:11.535Z",
        "reply_count": 0,
        "reply_to_post_number": null,
        "quote_count": 0,
        "incoming_link_count": 15,
        "reads": 60,
        "readers_count": 59,
        "score": 87.0,
        "yours": false,
        "topic_id": 8628,
        "topic_slug": "%D0%BE%D1%88%D0%B8%D0%B1%D0%BA%D0%B0-%D0%B2-goodbyedpi%D1%81%D0%BA%D1%80%D0%B8%D0%BD%D1%88%D0%BE%D1%82-%D0%BF%D1%80%D0%B8%D0%BA%D1%80%D0%B5%D0%BF%D0%B8%D0%BB",
        "display_username": "",
        "primary_group_name": null,
        "flair_name": null,
        "flair_url": null,
        "flair_bg_color": null,
        "flair_color": null,
        "flair_group_id": null,
        "badges_granted": [],
        "version": 1,
        "can_edit": false,
        "can_delete": false,
        "can_recover": false,
        "can_see_hidden_post": false,
        "can_wiki": false,
        "read": true,
        "user_title": null,
        "bookmarked": false,
        "actions_summary": [],
        "moderator": false,
        "admin": false,
        "staff": false,
        "user_id": 3990,
        "hidden": false,
        "trust_level": 1,
        "deleted_at": null,
        "user_deleted": false,
        "edit_reason": null,
        "can_view_edit_history": false,
        "wiki": false,
        "post_url": "/t/%D0%BE%D1%88%D0%B8%D0%B1%D0%BA%D0%B0-%D0%B2-goodbyedpi%D1%81%D0%BA%D1%80%D0%B8%D0%BD%D1%88%D0%BE%D1%82-%D0%BF%D1%80%D0%B8%D0%BA%D1%80%D0%B5%D0%BF%D0%B8%D0%BB/8628/1",
        "can_translate": false
    },
    {
        "id": 29546,
        "name": "YoutubeNotWork",
        "username": "jestxfot",
        "avatar_template": "/letter_avatar_proxy/v4/letter/j/d9b06d/{size}.png",
        "created_at": "2024-08-03T16:53:52.905Z",
        "cooked": "<p>У меня такая проблема была на Windows LTSC, вероятно связано с тем что там отсутствуют какие-то службы</p>",
        "post_number": 2,
        "post_type": 1,
        "posts_count": 7,
        "updated_at": "2024-08-03T16:53:52.905Z",
        "reply_count": 1,
        "reply_to_post_number": null,
        "quote_count": 0,
        "incoming_link_count": 0,
        "reads": 59,
        "readers_count": 58,
        "score": 16.8,
        "yours": false,
        "topic_id": 8628,
        "topic_slug": "%D0%BE%D1%88%D0%B8%D0%B1%D0%BA%D0%B0-%D0%B2-goodbyedpi%D1%81%D0%BA%D1%80%D0%B8%D0%BD%D1%88%D0%BE%D1%82-%D0%BF%D1%80%D0%B8%D0%BA%D1%80%D0%B5%D0%BF%D0%B8%D0%BB",
        "display_username": "YoutubeNotWork",
        "primary_group_name": null,
        "flair_name": null,
        "flair_url": null,
        "flair_bg_color": null,
        "flair_color": null,
        "flair_group_id": null,
        "badges_granted": [],
        "version": 1,
        "can_edit": false,
        "can_delete": false,
        "can_recover": false,
        "can_see_hidden_post": false,
        "can_wiki": false,
        "read": true,
        "user_title": "",
        "bookmarked": false,
        "actions_summary": [],
        "moderator": false,
        "admin": false,
        "staff": false,
        "user_id": 1076,
        "hidden": false,
        "trust_level": 2,
        "deleted_at": null,
        "user_deleted": false,
        "edit_reason": null,
        "can_view_edit_history": false,
        "wiki": false,
        "post_url": "/t/%D0%BE%D1%88%D0%B8%D0%B1%D0%BA%D0%B0-%D0%B2-goodbyedpi%D1%81%D0%BA%D1%80%D0%B8%D0%BD%D1%88%D0%BE%D1%82-%D0%BF%D1%80%D0%B8%D0%BA%D1%80%D0%B5%D0%BF%D0%B8%D0%BB/8628/2",
        "can_translate": false
    },
    {
        "id": 29548,
        "name": "",
        "username": "Boko",
        "avatar_template": "/letter_avatar_proxy/v4/letter/b/e480ec/{size}.png",
        "created_at": "2024-08-03T16:56:46.723Z",
        "cooked": "<p>ну да, у меня корпоративная винда, но чёт очень сомневаюсь, что проблема именно в этом, буду ждать, мб кто-то разобрался</p>",
        "post_number": 3,
        "post_type": 1,
        "posts_count": 7,
        "updated_at": "2024-08-03T16:56:46.723Z",
        "reply_count": 1,
        "reply_to_post_number": 2,
        "quote_count": 0,
        "incoming_link_count": 0,
        "reads": 59,
        "readers_count": 58,
        "score": 16.8,
        "yours": false,
        "topic_id": 8628,
        "topic_slug": "%D0%BE%D1%88%D0%B8%D0%B1%D0%BA%D0%B0-%D0%B2-goodbyedpi%D1%81%D0%BA%D1%80%D0%B8%D0%BD%D1%88%D0%BE%D1%82-%D0%BF%D1%80%D0%B8%D0%BA%D1%80%D0%B5%D0%BF%D0%B8%D0%BB",
        "display_username": "",
        "primary_group_name": null,
        "flair_name": null,
        "flair_url": null,
        "flair_bg_color": null,
        "flair_color": null,
        "flair_group_id": null,
        "badges_granted": [],
        "version": 1,
        "can_edit": false,
        "can_delete": false,
        "can_recover": false,
        "can_see_hidden_post": false,
        "can_wiki": false,
        "read": true,
        "user_title": null,
        "reply_to_user": {
            "username": "jestxfot",
            "name": "YoutubeNotWork",
            "avatar_template": "/letter_avatar_proxy/v4/letter/j/d9b06d/{size}.png"
        },
        "bookmarked": false,
        "actions_summary": [],
        "moderator": false,
        "admin": false,
        "staff": false,
        "user_id": 3990,
        "hidden": false,
        "trust_level": 1,
        "deleted_at": null,
        "user_deleted": false,
        "edit_reason": null,
        "can_view_edit_history": false,
        "wiki": false,
        "post_url": "/t/%D0%BE%D1%88%D0%B8%D0%B1%D0%BA%D0%B0-%D0%B2-goodbyedpi%D1%81%D0%BA%D1%80%D0%B8%D0%BD%D1%88%D0%BE%D1%82-%D0%BF%D1%80%D0%B8%D0%BA%D1%80%D0%B5%D0%BF%D0%B8%D0%BB/8628/3",
        "can_translate": false
    },
    {
        "id": 29555,
        "name": "YoutubeNotWork",
        "username": "jestxfot",
        "avatar_template": "/letter_avatar_proxy/v4/letter/j/d9b06d/{size}.png",
        "created_at": "2024-08-03T17:34:31.832Z",
        "cooked": "<p>Пробуй на винде про, вполне может помочь. Я пока не разобрался как пофиксить это на LTSC, буду пробовать дальше</p>",
        "post_number": 4,
        "post_type": 1,
        "posts_count": 7,
        "updated_at": "2024-08-03T17:34:31.832Z",
        "reply_count": 0,
        "reply_to_post_number": 3,
        "quote_count": 0,
        "incoming_link_count": 0,
        "reads": 57,
        "readers_count": 56,
        "score": 11.4,
        "yours": false,
        "topic_id": 8628,
        "topic_slug": "%D0%BE%D1%88%D0%B8%D0%B1%D0%BA%D0%B0-%D0%B2-goodbyedpi%D1%81%D0%BA%D1%80%D0%B8%D0%BD%D1%88%D0%BE%D1%82-%D0%BF%D1%80%D0%B8%D0%BA%D1%80%D0%B5%D0%BF%D0%B8%D0%BB",
        "display_username": "YoutubeNotWork",
        "primary_group_name": null,
        "flair_name": null,
        "flair_url": null,
        "flair_bg_color": null,
        "flair_color": null,
        "flair_group_id": null,
        "badges_granted": [],
        "version": 1,
        "can_edit": false,
        "can_delete": false,
        "can_recover": false,
        "can_see_hidden_post": false,
        "can_wiki": false,
        "read": true,
        "user_title": "",
        "reply_to_user": {
            "username": "Boko",
            "name": "",
            "avatar_template": "/letter_avatar_proxy/v4/letter/b/e480ec/{size}.png"
        },
        "bookmarked": false,
        "actions_summary": [],
        "moderator": false,
        "admin": false,
        "staff": false,
        "user_id": 1076,
        "hidden": false,
        "trust_level": 2,
        "deleted_at": null,
        "user_deleted": false,
        "edit_reason": null,
        "can_view_edit_history": false,
        "wiki": false,
        "post_url": "/t/%D0%BE%D1%88%D0%B8%D0%B1%D0%BA%D0%B0-%D0%B2-goodbyedpi%D1%81%D0%BA%D1%80%D0%B8%D0%BD%D1%88%D0%BE%D1%82-%D0%BF%D1%80%D0%B8%D0%BA%D1%80%D0%B5%D0%BF%D0%B8%D0%BB/8628/4",
        "can_translate": false
    },
    {
        "id": 29557,
        "name": "",
        "username": "Boko",
        "avatar_template": "/letter_avatar_proxy/v4/letter/b/e480ec/{size}.png",
        "created_at": "2024-08-03T17:35:13.878Z",
        "cooked": "<p>Да у меня просто возможности такой нет, в этом траблы</p>",
        "post_number": 5,
        "post_type": 1,
        "posts_count": 7,
        "updated_at": "2024-08-03T17:35:13.878Z",
        "reply_count": 1,
        "reply_to_post_number": null,
        "quote_count": 0,
        "incoming_link_count": 0,
        "reads": 52,
        "readers_count": 51,
        "score": 15.4,
        "yours": false,
        "topic_id": 8628,
        "topic_slug": "%D0%BE%D1%88%D0%B8%D0%B1%D0%BA%D0%B0-%D0%B2-goodbyedpi%D1%81%D0%BA%D1%80%D0%B8%D0%BD%D1%88%D0%BE%D1%82-%D0%BF%D1%80%D0%B8%D0%BA%D1%80%D0%B5%D0%BF%D0%B8%D0%BB",
        "display_username": "",
        "primary_group_name": null,
        "flair_name": null,
        "flair_url": null,
        "flair_bg_color": null,
        "flair_color": null,
        "flair_group_id": null,
        "badges_granted": [],
        "version": 1,
        "can_edit": false,
        "can_delete": false,
        "can_recover": false,
        "can_see_hidden_post": false,
        "can_wiki": false,
        "read": true,
        "user_title": null,
        "bookmarked": false,
        "actions_summary": [],
        "moderator": false,
        "admin": false,
        "staff": false,
        "user_id": 3990,
        "hidden": false,
        "trust_level": 1,
        "deleted_at": null,
        "user_deleted": false,
        "edit_reason": null,
        "can_view_edit_history": false,
        "wiki": false,
        "post_url": "/t/%D0%BE%D1%88%D0%B8%D0%B1%D0%BA%D0%B0-%D0%B2-goodbyedpi%D1%81%D0%BA%D1%80%D0%B8%D0%BD%D1%88%D0%BE%D1%82-%D0%BF%D1%80%D0%B8%D0%BA%D1%80%D0%B5%D0%BF%D0%B8%D0%BB/8628/5",
        "can_translate": false
    },
    {
        "id": 29559,
        "name": "YoutubeNotWork",
        "username": "jestxfot",
        "avatar_template": "/letter_avatar_proxy/v4/letter/j/d9b06d/{size}.png",
        "created_at": "2024-08-03T17:42:01.847Z",
        "cooked": "<p>Извини за оффтоп, но почему? Попробуй временно поставить новую сборку на ПК</p>",
        "post_number": 6,
        "post_type": 1,
        "posts_count": 7,
        "updated_at": "2024-08-03T17:42:01.847Z",
        "reply_count": 1,
        "reply_to_post_number": 5,
        "quote_count": 0,
        "incoming_link_count": 0,
        "reads": 49,
        "readers_count": 48,
        "score": 14.8,
        "yours": false,
        "topic_id": 8628,
        "topic_slug": "%D0%BE%D1%88%D0%B8%D0%B1%D0%BA%D0%B0-%D0%B2-goodbyedpi%D1%81%D0%BA%D1%80%D0%B8%D0%BD%D1%88%D0%BE%D1%82-%D0%BF%D1%80%D0%B8%D0%BA%D1%80%D0%B5%D0%BF%D0%B8%D0%BB",
        "display_username": "YoutubeNotWork",
        "primary_group_name": null,
        "flair_name": null,
        "flair_url": null,
        "flair_bg_color": null,
        "flair_color": null,
        "flair_group_id": null,
        "badges_granted": [],
        "version": 1,
        "can_edit": false,
        "can_delete": false,
        "can_recover": false,
        "can_see_hidden_post": false,
        "can_wiki": false,
        "read": true,
        "user_title": "",
        "reply_to_user": {
            "username": "Boko",
            "name": "",
            "avatar_template": "/letter_avatar_proxy/v4/letter/b/e480ec/{size}.png"
        },
        "bookmarked": false,
        "actions_summary": [],
        "moderator": false,
        "admin": false,
        "staff": false,
        "user_id": 1076,
        "hidden": false,
        "trust_level": 2,
        "deleted_at": null,
        "user_deleted": false,
        "edit_reason": null,
        "can_view_edit_history": false,
        "wiki": false,
        "post_url": "/t/%D0%BE%D1%88%D0%B8%D0%B1%D0%BA%D0%B0-%D0%B2-goodbyedpi%D1%81%D0%BA%D1%80%D0%B8%D0%BD%D1%88%D0%BE%D1%82-%D0%BF%D1%80%D0%B8%D0%BA%D1%80%D0%B5%D0%BF%D0%B8%D0%BB/8628/6",
        "can_translate": false
    },
    {
        "id": 29589,
        "name": "",
        "username": "Boko",
        "avatar_template": "/letter_avatar_proxy/v4/letter/b/e480ec/{size}.png",
        "created_at": "2024-08-03T19:01:06.419Z",
        "cooked": "<p>Мне сейчас не выгодно это делать, флешки тоже свободной нема, плюс нужную инфу я перенести на данный момент не могу, опять же не на что</p>",
        "post_number": 7,
        "post_type": 1,
        "posts_count": 7,
        "updated_at": "2024-08-03T19:01:06.419Z",
        "reply_count": 0,
        "reply_to_post_number": 6,
        "quote_count": 0,
        "incoming_link_count": 0,
        "reads": 45,
        "readers_count": 44,
        "score": 9.0,
        "yours": false,
        "topic_id": 8628,
        "topic_slug": "%D0%BE%D1%88%D0%B8%D0%B1%D0%BA%D0%B0-%D0%B2-goodbyedpi%D1%81%D0%BA%D1%80%D0%B8%D0%BD%D1%88%D0%BE%D1%82-%D0%BF%D1%80%D0%B8%D0%BA%D1%80%D0%B5%D0%BF%D0%B8%D0%BB",
        "display_username": "",
        "primary_group_name": null,
        "flair_name": null,
        "flair_url": null,
        "flair_bg_color": null,
        "flair_color": null,
        "flair_group_id": null,
        "badges_granted": [],
        "version": 1,
        "can_edit": false,
        "can_delete": false,
        "can_recover": false,
        "can_see_hidden_post": false,
        "can_wiki": false,
        "read": true,
        "user_title": null,
        "reply_to_user": {
            "username": "jestxfot",
            "name": "YoutubeNotWork",
            "avatar_template": "/letter_avatar_proxy/v4/letter/j/d9b06d/{size}.png"
        },
        "bookmarked": false,
        "actions_summary": [],
        "moderator": false,
        "admin": false,
        "staff": false,
        "user_id": 3990,
        "hidden": false,
        "trust_level": 1,
        "deleted_at": null,
        "user_deleted": false,
        "edit_reason": null,
        "can_view_edit_history": false,
        "wiki": false,
        "post_url": "/t/%D0%BE%D1%88%D0%B8%D0%B1%D0%BA%D0%B0-%D0%B2-goodbyedpi%D1%81%D0%BA%D1%80%D0%B8%D0%BD%D1%88%D0%BE%D1%82-%D0%BF%D1%80%D0%B8%D0%BA%D1%80%D0%B5%D0%BF%D0%B8%D0%BB/8628/7",
        "can_translate": false
    }
]