[
    {
        "id": 1828,
        "name": "",
        "username": "JIPCOROD",
        "avatar_template": "/user_avatar/ntc.party/jipcorod/{size}/6810_2.png",
        "created_at": "2020-09-04T23:57:31.678Z",
        "cooked": "<p>Здравствуйте, есть 2 довольно популярных, интересующих меня ресурса, блокировка по которым не исполняется в полной мере на территории РФ, это аниме сайты:</p>\n<p>pixiv. net<br>\niwara. tv</p>\n<p>Столкнулся с ограничением в 2 ссылки для новичков, так что все проверки и доказательства перенёс сюда <a href=\"https://github.com/pyplyn/Postero_ATG_Zebra/issues/1\" rel=\"nofollow noopener\">https://github.com/pyplyn/Postero_ATG_Zebra/issues/1</a></p>",
        "post_number": 1,
        "post_type": 1,
        "posts_count": 25,
        "updated_at": "2020-09-05T00:04:39.134Z",
        "reply_count": 0,
        "reply_to_post_number": null,
        "quote_count": 0,
        "incoming_link_count": 1282,
        "reads": 76,
        "readers_count": 75,
        "score": 6425.2,
        "yours": false,
        "topic_id": 668,
        "topic_slug": "%D1%87%D0%B0%D1%81%D1%82%D0%B8%D1%87%D0%BD%D0%BE-%D0%B7%D0%B0%D0%B1%D0%BB%D0%BE%D0%BA%D0%B8%D1%80%D0%BE%D0%B2%D0%B0%D0%BD%D0%BD%D1%8B%D0%B5-%D1%80%D0%B5%D1%81%D1%83%D1%80%D1%81%D1%8B",
        "display_username": "",
        "primary_group_name": null,
        "flair_name": null,
        "flair_url": null,
        "flair_bg_color": null,
        "flair_color": null,
        "flair_group_id": null,
        "badges_granted": [],
        "version": 2,
        "can_edit": false,
        "can_delete": false,
        "can_recover": false,
        "can_see_hidden_post": false,
        "can_wiki": false,
        "link_counts": [
            {
                "url": "https://github.com/pyplyn/Postero_ATG_Zebra/issues/1",
                "internal": false,
                "reflection": false,
                "title": "частично заблокированные ресурсы · Issue #1 · pyplyn/Postero_ATG_Zebra · GitHub",
                "clicks": 53
            },
            {
                "url": "https://ntc.party/t/pixivnet-errsslprotocolerror/903/2",
                "internal": true,
                "reflection": true,
                "title": "Pixiv.net: ERR_SSL_PROTOCOL_ERROR",
                "clicks": 1
            }
        ],
        "read": true,
        "user_title": "",
        "bookmarked": false,
        "actions_summary": [],
        "moderator": false,
        "admin": false,
        "staff": false,
        "user_id": 287,
        "hidden": false,
        "trust_level": 2,
        "deleted_at": null,
        "user_deleted": false,
        "edit_reason": null,
        "can_view_edit_history": false,
        "wiki": false,
        "post_url": "/t/%D1%87%D0%B0%D1%81%D1%82%D0%B8%D1%87%D0%BD%D0%BE-%D0%B7%D0%B0%D0%B1%D0%BB%D0%BE%D0%BA%D0%B8%D1%80%D0%BE%D0%B2%D0%B0%D0%BD%D0%BD%D1%8B%D0%B5-%D1%80%D0%B5%D1%81%D1%83%D1%80%D1%81%D1%8B/668/1",
        "can_translate": false
    },
    {
        "id": 1833,
        "name": null,
        "username": "ValdikSS",
        "avatar_template": "/user_avatar/ntc.party/valdikss/{size}/2_2.png",
        "created_at": "2020-09-05T09:57:05.542Z",
        "cooked": "<blockquote>\n<p>полная версия сообщения.<br>\nИнтересует 2 сайта, который стали медленно работать при использование списка АнтиЗапрета, при том, что они в большинстве точек России не заблокированы</p>\n<p><a href=\"http://pixiv.net\">pixiv.net</a><br>\nДействительно в реестре находится огромное количество страниц, но основной домен не заблокирован<br>\nв России есть пинг почти со всех нод [зеркало]</p>\n<p><a href=\"http://iwara.tv\">iwara.tv</a><br>\n2 страницы вынесены из реестра, 1 осталась. Все “нападения” были в 2017 году<br>\nв России есть пинг почти со всех нод [зеркало]</p>\n<p>Считаю оба сайта можно вынести из списка “АнтиЗапрета”. Это можно сделать локально в фаерфоксе, но нельзя в плагине для хромиума, приходиться полностью отключать обход ограничения, что бы использовать эти сайты (скорость на иваре не позволяет без лагов смотреть ролики даже в 320p)</p>\n<p>Жаль нет 100% способа отличить частично заблокированный сайт, без блокировки основного домена но всё же не работающий (как <a href=\"http://nicovideo.jp\">http://nicovideo.jp</a> ) на isitblockedinrussia по нему вообще ничего не находит и всё же работающие сайты, частично прописанные в реестре, как 2 примера выше</p>\n</blockquote>",
        "post_number": 2,
        "post_type": 1,
        "posts_count": 25,
        "updated_at": "2020-09-05T09:57:05.542Z",
        "reply_count": 0,
        "reply_to_post_number": null,
        "quote_count": 0,
        "incoming_link_count": 42,
        "reads": 76,
        "readers_count": 75,
        "score": 225.2,
        "yours": false,
        "topic_id": 668,
        "topic_slug": "%D1%87%D0%B0%D1%81%D1%82%D0%B8%D1%87%D0%BD%D0%BE-%D0%B7%D0%B0%D0%B1%D0%BB%D0%BE%D0%BA%D0%B8%D1%80%D0%BE%D0%B2%D0%B0%D0%BD%D0%BD%D1%8B%D0%B5-%D1%80%D0%B5%D1%81%D1%83%D1%80%D1%81%D1%8B",
        "display_username": null,
        "primary_group_name": null,
        "flair_name": null,
        "flair_url": null,
        "flair_bg_color": null,
        "flair_color": null,
        "flair_group_id": null,
        "badges_granted": [],
        "version": 1,
        "can_edit": false,
        "can_delete": false,
        "can_recover": false,
        "can_see_hidden_post": false,
        "can_wiki": false,
        "link_counts": [
            {
                "url": "http://pixiv.net",
                "internal": false,
                "reflection": false,
                "clicks": 68
            },
            {
                "url": "http://iwara.tv",
                "internal": false,
                "reflection": false,
                "clicks": 27
            },
            {
                "url": "http://nicovideo.jp",
                "internal": false,
                "reflection": false,
                "clicks": 15
            }
        ],
        "read": true,
        "user_title": "AntiZapret staff",
        "title_is_group": false,
        "bookmarked": false,
        "actions_summary": [],
        "moderator": true,
        "admin": true,
        "staff": true,
        "user_id": 1,
        "hidden": false,
        "trust_level": 2,
        "deleted_at": null,
        "user_deleted": false,
        "edit_reason": null,
        "can_view_edit_history": false,
        "wiki": false,
        "post_url": "/t/%D1%87%D0%B0%D1%81%D1%82%D0%B8%D1%87%D0%BD%D0%BE-%D0%B7%D0%B0%D0%B1%D0%BB%D0%BE%D0%BA%D0%B8%D1%80%D0%BE%D0%B2%D0%B0%D0%BD%D0%BD%D1%8B%D0%B5-%D1%80%D0%B5%D1%81%D1%83%D1%80%D1%81%D1%8B/668/2",
        "can_translate": false
    },
    {
        "id": 1834,
        "name": null,
        "username": "ValdikSS",
        "avatar_template": "/user_avatar/ntc.party/valdikss/{size}/2_2.png",
        "created_at": "2020-09-05T10:00:06.323Z",
        "cooked": "<p>Pixiv и iwara заблокированы по протоколу HTTP, все заблокированные ссылки уже не работают.<br>\nУбрал эти сайты, хоть они и сломаются у провайдеров, блокирующих сайты через DNS, например, у мобильного Теле2. Ну и поделом.</p>\n<blockquote>\n<p>Жаль нет 100% способа отличить частично заблокированный сайт, без блокировки основного домена но всё же не работающий (как <a href=\"http://nicovideo.jp\">http://nicovideo.jp</a> ) на isitblockedinrussia по нему вообще ничего не находит и всё же работающие сайты, частично прописанные в реестре, как 2 примера выше</p>\n</blockquote>\n<p>Не пользуйтесь isitblockedinrussia, он некорректно работает: <a href=\"https://github.com/deNULL/isitblockedinrussia.com/issues/3\" class=\"inline-onebox\">Результаты меняются из раза к разу · Issue #3 · deNULL/isitblockedinrussia.com · GitHub</a></p>\n<p>niconicodouga внесён в реестр по протоколу HTTPS, из-за чего «заблокирован полностью».</p>",
        "post_number": 3,
        "post_type": 1,
        "posts_count": 25,
        "updated_at": "2020-09-05T10:00:06.323Z",
        "reply_count": 1,
        "reply_to_post_number": null,
        "quote_count": 0,
        "incoming_link_count": 37,
        "reads": 66,
        "readers_count": 65,
        "score": 203.2,
        "yours": false,
        "topic_id": 668,
        "topic_slug": "%D1%87%D0%B0%D1%81%D1%82%D0%B8%D1%87%D0%BD%D0%BE-%D0%B7%D0%B0%D0%B1%D0%BB%D0%BE%D0%BA%D0%B8%D1%80%D0%BE%D0%B2%D0%B0%D0%BD%D0%BD%D1%8B%D0%B5-%D1%80%D0%B5%D1%81%D1%83%D1%80%D1%81%D1%8B",
        "display_username": null,
        "primary_group_name": null,
        "flair_name": null,
        "flair_url": null,
        "flair_bg_color": null,
        "flair_color": null,
        "flair_group_id": null,
        "badges_granted": [],
        "version": 1,
        "can_edit": false,
        "can_delete": false,
        "can_recover": false,
        "can_see_hidden_post": false,
        "can_wiki": false,
        "link_counts": [
            {
                "url": "https://github.com/deNULL/isitblockedinrussia.com/issues/3",
                "internal": false,
                "reflection": false,
                "title": "Результаты меняются из раза к разу · Issue #3 · deNULL/isitblockedinrussia.com · GitHub",
                "clicks": 26
            },
            {
                "url": "http://nicovideo.jp",
                "internal": false,
                "reflection": false,
                "clicks": 7
            }
        ],
        "read": true,
        "user_title": "AntiZapret staff",
        "title_is_group": false,
        "bookmarked": false,
        "actions_summary": [],
        "moderator": true,
        "admin": true,
        "staff": true,
        "user_id": 1,
        "hidden": false,
        "trust_level": 2,
        "deleted_at": null,
        "user_deleted": false,
        "edit_reason": null,
        "can_view_edit_history": false,
        "wiki": false,
        "post_url": "/t/%D1%87%D0%B0%D1%81%D1%82%D0%B8%D1%87%D0%BD%D0%BE-%D0%B7%D0%B0%D0%B1%D0%BB%D0%BE%D0%BA%D0%B8%D1%80%D0%BE%D0%B2%D0%B0%D0%BD%D0%BD%D1%8B%D0%B5-%D1%80%D0%B5%D1%81%D1%83%D1%80%D1%81%D1%8B/668/3",
        "can_translate": false
    },
    {
        "id": 1835,
        "name": null,
        "username": "ValdikSS",
        "avatar_template": "/user_avatar/ntc.party/valdikss/{size}/2_2.png",
        "created_at": "2020-09-05T10:01:46.507Z",
        "cooked": "<p>Если вас не устраивает скорость работы, можете поднять антизапрет на своём сервере: <a href=\"https://antizapret.prostovpn.org/selfhosted.html\">https://antizapret.prostovpn.org/selfhosted.html</a></p>",
        "post_number": 4,
        "post_type": 1,
        "posts_count": 25,
        "updated_at": "2020-09-05T10:01:46.507Z",
        "reply_count": 0,
        "reply_to_post_number": null,
        "quote_count": 0,
        "incoming_link_count": 6,
        "reads": 56,
        "readers_count": 55,
        "score": 41.2,
        "yours": false,
        "topic_id": 668,
        "topic_slug": "%D1%87%D0%B0%D1%81%D1%82%D0%B8%D1%87%D0%BD%D0%BE-%D0%B7%D0%B0%D0%B1%D0%BB%D0%BE%D0%BA%D0%B8%D1%80%D0%BE%D0%B2%D0%B0%D0%BD%D0%BD%D1%8B%D0%B5-%D1%80%D0%B5%D1%81%D1%83%D1%80%D1%81%D1%8B",
        "display_username": null,
        "primary_group_name": null,
        "flair_name": null,
        "flair_url": null,
        "flair_bg_color": null,
        "flair_color": null,
        "flair_group_id": null,
        "badges_granted": [],
        "version": 1,
        "can_edit": false,
        "can_delete": false,
        "can_recover": false,
        "can_see_hidden_post": false,
        "can_wiki": false,
        "link_counts": [
            {
                "url": "https://antizapret.prostovpn.org/selfhosted.html",
                "internal": false,
                "reflection": false,
                "title": "АнтиЗапрет на своём сервере",
                "clicks": 81
            }
        ],
        "read": true,
        "user_title": "AntiZapret staff",
        "title_is_group": false,
        "bookmarked": false,
        "actions_summary": [],
        "moderator": true,
        "admin": true,
        "staff": true,
        "user_id": 1,
        "hidden": false,
        "trust_level": 2,
        "deleted_at": null,
        "user_deleted": false,
        "edit_reason": null,
        "can_view_edit_history": false,
        "wiki": false,
        "post_url": "/t/%D1%87%D0%B0%D1%81%D1%82%D0%B8%D1%87%D0%BD%D0%BE-%D0%B7%D0%B0%D0%B1%D0%BB%D0%BE%D0%BA%D0%B8%D1%80%D0%BE%D0%B2%D0%B0%D0%BD%D0%BD%D1%8B%D0%B5-%D1%80%D0%B5%D1%81%D1%83%D1%80%D1%81%D1%8B/668/4",
        "can_translate": false
    },
    {
        "id": 1836,
        "name": "",
        "username": "JIPCOROD",
        "avatar_template": "/user_avatar/ntc.party/jipcorod/{size}/6810_2.png",
        "created_at": "2020-09-05T10:02:20.241Z",
        "cooked": "<p>niconicodouga да - не работает нигде. А пикксив и ивара, сколько тестил - везде нормально, но вот именно на теле 2 не доводилось<br>\nСпасибо за исключение сервисов)</p>",
        "post_number": 5,
        "post_type": 1,
        "posts_count": 25,
        "updated_at": "2020-09-05T10:02:20.241Z",
        "reply_count": 0,
        "reply_to_post_number": null,
        "quote_count": 0,
        "incoming_link_count": 5,
        "reads": 60,
        "readers_count": 59,
        "score": 37.0,
        "yours": false,
        "topic_id": 668,
        "topic_slug": "%D1%87%D0%B0%D1%81%D1%82%D0%B8%D1%87%D0%BD%D0%BE-%D0%B7%D0%B0%D0%B1%D0%BB%D0%BE%D0%BA%D0%B8%D1%80%D0%BE%D0%B2%D0%B0%D0%BD%D0%BD%D1%8B%D0%B5-%D1%80%D0%B5%D1%81%D1%83%D1%80%D1%81%D1%8B",
        "display_username": "",
        "primary_group_name": null,
        "flair_name": null,
        "flair_url": null,
        "flair_bg_color": null,
        "flair_color": null,
        "flair_group_id": null,
        "badges_granted": [],
        "version": 1,
        "can_edit": false,
        "can_delete": false,
        "can_recover": false,
        "can_see_hidden_post": false,
        "can_wiki": false,
        "read": true,
        "user_title": "",
        "bookmarked": false,
        "actions_summary": [],
        "moderator": false,
        "admin": false,
        "staff": false,
        "user_id": 287,
        "hidden": false,
        "trust_level": 2,
        "deleted_at": null,
        "user_deleted": false,
        "edit_reason": null,
        "can_view_edit_history": false,
        "wiki": false,
        "post_url": "/t/%D1%87%D0%B0%D1%81%D1%82%D0%B8%D1%87%D0%BD%D0%BE-%D0%B7%D0%B0%D0%B1%D0%BB%D0%BE%D0%BA%D0%B8%D1%80%D0%BE%D0%B2%D0%B0%D0%BD%D0%BD%D1%8B%D0%B5-%D1%80%D0%B5%D1%81%D1%83%D1%80%D1%81%D1%8B/668/5",
        "can_translate": false
    },
    {
        "id": 1880,
        "name": "Александр",
        "username": "Lyinx",
        "avatar_template": "/user_avatar/ntc.party/lyinx/{size}/382_2.png",
        "created_at": "2020-09-12T17:06:23.872Z",
        "cooked": "<aside class=\"quote no-group\" data-username=\"ValdikSS\" data-post=\"3\" data-topic=\"668\">\n<div class=\"title\">\n<div class=\"quote-controls\"></div>\n<img loading=\"lazy\" alt=\"\" width=\"24\" height=\"24\" src=\"https://ntc.party/user_avatar/ntc.party/valdikss/48/2_2.png\" class=\"avatar\"> ValdikSS:</div>\n<blockquote>\n<p>Убрал эти сайты, хоть они и сломаются у провайдеров, блокирующих сайты через DNS</p>\n</blockquote>\n</aside>\n<p>Ну вот примерно когда вы убрали pixiv (оттуда откуда убрали), он у меня и сломался, хотя до этого работал без вопросов. Вернуть нельзя? XD</p>\n<p>СПб, провайдер – SkyNet / <a href=\"http://sknt.ru\" rel=\"noopener nofollow ugc\">sknt.ru</a>, Firefox 80.0.1, в проксях автонастройка через proxy.pac, DNS over HTTPS была отключена (сейчас ни на что не влияет). Других средств обхода нет.<br>\nПерепробовал goodbyeDPI со всеми возможными настройками -– не пошло.</p>\n<details>\n<summary>\nBlockCheck v0.0.9.8</summary>\n<p>Проверка работоспособности IPv6: IPv6 недоступен.<br>\n[O] Тестируем IPv4 DNS<br>\nЧерез системный DNS:\t [‘185.37.129.10’, ‘185.37.129.10’, ‘185.37.129.10’, ‘185.37.129.10’, ‘185.37.129.10’, ‘185.37.129.10’]<br>\nЧерез Google DNS:\t [‘104.18.182.1’, ‘104.18.183.1’, ‘104.26.10.39’, ‘104.26.11.39’, ‘104.26.4.231’, ‘104.26.5.231’, ‘172.67.70.38’, ‘172.67.70.99’, ‘195.8.215.136’, ‘195.82.146.214’, ‘208.100.28.56’, ‘67.202.114.141’]<br>\nЧерез Google API:\t [‘104.18.182.1’, ‘104.18.183.1’, ‘104.26.10.39’, ‘104.26.11.39’, ‘104.26.4.231’, ‘104.26.5.231’, ‘172.67.70.38’, ‘172.67.70.99’, ‘195.8.215.136’, ‘195.82.146.214’, ‘208.100.28.56’, ‘67.202.114.141’]<br>\nНесуществующий DNS не вернул адресов (это не ошибка)<br>\n[<img src=\"https://ntc.party/images/emoji/twitter/skull_and_crossbones.png?v=12\" title=\":skull_and_crossbones:\" class=\"emoji\" alt=\":skull_and_crossbones:\" loading=\"lazy\" width=\"20\" height=\"20\">] DNS-записи подменяются<br>\n[✓] DNS не перенаправляется</p>\n<p>[O] Тестируем HTTP (по настоящим IP-адресам сайтов)<br>\nОткрываем  <a href=\"http://a.putinhuylo.com/\" rel=\"noopener nofollow ugc\">http://a.putinhuylo.com/</a><br>\n[✓] Сайт открывается<br>\nОткрываем  <a href=\"http://furry.booru.org/\" rel=\"noopener nofollow ugc\">http://furry.booru.org/</a><br>\n[<img src=\"https://ntc.party/images/emoji/twitter/skull_and_crossbones.png?v=12\" title=\":skull_and_crossbones:\" class=\"emoji\" alt=\":skull_and_crossbones:\" loading=\"lazy\" width=\"20\" height=\"20\">] Получен неожиданный ответ, скорее всего, страница-заглушка провайдера. Пробуем через прокси.<br>\n[<img src=\"https://ntc.party/images/emoji/twitter/skull_and_crossbones.png?v=12\" title=\":skull_and_crossbones:\" class=\"emoji\" alt=\":skull_and_crossbones:\" loading=\"lazy\" width=\"20\" height=\"20\">] Сайт не открывается через прокси<br>\nПроверяем доступность через isupme<br>\n[⁇] Неожиданный ответ от isupme, код 403<br>\nОткрываем  <a href=\"http://furry.booru.org/index.php?page=post&amp;s=view&amp;id=111173\" class=\"inline-onebox\" rel=\"noopener nofollow ugc\">The Big ImageBoard (TBIB) - beach bird breasts cleavage copyright request day drink hat highres medium breasts mitsumi misato parrot solo straw hat sun hat tropical drink umbrella | 111173</a><br>\n[<img src=\"https://ntc.party/images/emoji/twitter/skull_and_crossbones.png?v=12\" title=\":skull_and_crossbones:\" class=\"emoji\" alt=\":skull_and_crossbones:\" loading=\"lazy\" width=\"20\" height=\"20\">] Сайт не открывается, пробуем через прокси<br>\n[<img src=\"https://ntc.party/images/emoji/twitter/skull_and_crossbones.png?v=12\" title=\":skull_and_crossbones:\" class=\"emoji\" alt=\":skull_and_crossbones:\" loading=\"lazy\" width=\"20\" height=\"20\">] Сайт не открывается через прокси<br>\nПроверяем доступность через isupme<br>\n[⁇] Неожиданный ответ от isupme, код 403<br>\nОткрываем  <a href=\"http://pboorucom/\" rel=\"noopener nofollow ugc\">http://pboorucom/</a><br>\n[<img src=\"https://ntc.party/images/emoji/twitter/skull_and_crossbones.png?v=12\" title=\":skull_and_crossbones:\" class=\"emoji\" alt=\":skull_and_crossbones:\" loading=\"lazy\" width=\"20\" height=\"20\">] Сайт не открывается, пробуем через прокси<br>\n[<img src=\"https://ntc.party/images/emoji/twitter/skull_and_crossbones.png?v=12\" title=\":skull_and_crossbones:\" class=\"emoji\" alt=\":skull_and_crossbones:\" loading=\"lazy\" width=\"20\" height=\"20\">] Сайт не открывается через прокси<br>\nПроверяем доступность через isupme<br>\n[⁇] Неожиданный ответ от isupme, код 403<br>\nОткрываем  <a href=\"http://pboorucom/index.php?page=post&amp;s=view&amp;id=303026\" rel=\"noopener nofollow ugc\">http://pboorucom/index.php?page=post&amp;s=view&amp;id=303026</a><br>\n[<img src=\"https://ntc.party/images/emoji/twitter/skull_and_crossbones.png?v=12\" title=\":skull_and_crossbones:\" class=\"emoji\" alt=\":skull_and_crossbones:\" loading=\"lazy\" width=\"20\" height=\"20\">] Сайт не открывается, пробуем через прокси<br>\n[<img src=\"https://ntc.party/images/emoji/twitter/skull_and_crossbones.png?v=12\" title=\":skull_and_crossbones:\" class=\"emoji\" alt=\":skull_and_crossbones:\" loading=\"lazy\" width=\"20\" height=\"20\">] Сайт не открывается через прокси<br>\nПроверяем доступность через isupme<br>\n[⁇] Неожиданный ответ от isupme, код 403<br>\nОткрываем  <a href=\"http://rutrackerorg/forum/index.php\" rel=\"noopener nofollow ugc\">http://rutrackerorg/forum/index.php</a><br>\n[✓] Сайт открывается</p>\n<p>[O] Тестируем HTTPS<br>\nОткрываем  <a href=\"https://e621.net/\" rel=\"noopener nofollow ugc\">https://e621.net/</a><br>\n[<img src=\"https://ntc.party/images/emoji/twitter/skull_and_crossbones.png?v=12\" title=\":skull_and_crossbones:\" class=\"emoji\" alt=\":skull_and_crossbones:\" loading=\"lazy\" width=\"20\" height=\"20\">] Сайт не открывается<br>\nОткрываем  <a href=\"https://lolibooru.moe/\" rel=\"noopener nofollow ugc\">https://lolibooru.moe/</a><br>\n[<img src=\"https://ntc.party/images/emoji/twitter/skull_and_crossbones.png?v=12\" title=\":skull_and_crossbones:\" class=\"emoji\" alt=\":skull_and_crossbones:\" loading=\"lazy\" width=\"20\" height=\"20\">] Сайт не открывается<br>\nОткрываем  <a href=\"https://rutrackerorg/forum/index.php\" rel=\"noopener nofollow ugc\">https://rutrackerorg/forum/index.php</a><br>\n[✓] Сайт открывается<br>\nОткрываем  <a href=\"https://www.dailymotion.com/\" rel=\"noopener nofollow ugc\">https://www.dailymotion.com/</a><br>\n[✓] Сайт открывается</p>\n<p>[O] Тестируем обход DPI<br>\nПробуем способ «дополнительный пробел после GET» на pboorucom<br>\n[<img src=\"https://ntc.party/images/emoji/twitter/skull_and_crossbones.png?v=12\" title=\":skull_and_crossbones:\" class=\"emoji\" alt=\":skull_and_crossbones:\" loading=\"lazy\" width=\"20\" height=\"20\">] Сайт не открывается<br>\nПробуем способ «заголовок hOSt вместо Host» на pboorucom<br>\n[<img src=\"https://ntc.party/images/emoji/twitter/skull_and_crossbones.png?v=12\" title=\":skull_and_crossbones:\" class=\"emoji\" alt=\":skull_and_crossbones:\" loading=\"lazy\" width=\"20\" height=\"20\">] Сайт не открывается<br>\nПробуем способ «заголовок hoSt вместо Host» на pboorucom<br>\n[<img src=\"https://ntc.party/images/emoji/twitter/skull_and_crossbones.png?v=12\" title=\":skull_and_crossbones:\" class=\"emoji\" alt=\":skull_and_crossbones:\" loading=\"lazy\" width=\"20\" height=\"20\">] Сайт не открывается<br>\nПробуем способ «значение Host БОЛЬШИМИ БУКВАМИ» на pboorucom<br>\n[<img src=\"https://ntc.party/images/emoji/twitter/skull_and_crossbones.png?v=12\" title=\":skull_and_crossbones:\" class=\"emoji\" alt=\":skull_and_crossbones:\" loading=\"lazy\" width=\"20\" height=\"20\">] Сайт не открывается<br>\nПробуем способ «необычный порядок заголовков» на pboorucom<br>\n[<img src=\"https://ntc.party/images/emoji/twitter/skull_and_crossbones.png?v=12\" title=\":skull_and_crossbones:\" class=\"emoji\" alt=\":skull_and_crossbones:\" loading=\"lazy\" width=\"20\" height=\"20\">] Сайт не открывается<br>\nПробуем способ «отсутствие пробела между двоеточием и значением заголовка Host» на pboorucom<br>\n[<img src=\"https://ntc.party/images/emoji/twitter/skull_and_crossbones.png?v=12\" title=\":skull_and_crossbones:\" class=\"emoji\" alt=\":skull_and_crossbones:\" loading=\"lazy\" width=\"20\" height=\"20\">] Сайт не открывается<br>\nПробуем способ «перенос строки в заголовках в UNIX-стиле» на pboorucom<br>\n[<img src=\"https://ntc.party/images/emoji/twitter/skull_and_crossbones.png?v=12\" title=\":skull_and_crossbones:\" class=\"emoji\" alt=\":skull_and_crossbones:\" loading=\"lazy\" width=\"20\" height=\"20\">] Сайт не открывается<br>\nПробуем способ «перенос строки перед GET» на pboorucom<br>\n[<img src=\"https://ntc.party/images/emoji/twitter/skull_and_crossbones.png?v=12\" title=\":skull_and_crossbones:\" class=\"emoji\" alt=\":skull_and_crossbones:\" loading=\"lazy\" width=\"20\" height=\"20\">] Сайт не открывается<br>\nПробуем способ «табуляция в конце домена» на pboorucom<br>\n[<img src=\"https://ntc.party/images/emoji/twitter/skull_and_crossbones.png?v=12\" title=\":skull_and_crossbones:\" class=\"emoji\" alt=\":skull_and_crossbones:\" loading=\"lazy\" width=\"20\" height=\"20\">] Сайт не открывается<br>\nПробуем способ «точка в конце домена» на pboorucom<br>\n[<img src=\"https://ntc.party/images/emoji/twitter/skull_and_crossbones.png?v=12\" title=\":skull_and_crossbones:\" class=\"emoji\" alt=\":skull_and_crossbones:\" loading=\"lazy\" width=\"20\" height=\"20\">] Сайт не открывается<br>\nПробуем способ «фрагментирование заголовка» на pboorucom<br>\n[<img src=\"https://ntc.party/images/emoji/twitter/skull_and_crossbones.png?v=12\" title=\":skull_and_crossbones:\" class=\"emoji\" alt=\":skull_and_crossbones:\" loading=\"lazy\" width=\"20\" height=\"20\">] Сайт не открывается<br>\nПробуем способ «фрагментирование заголовка, hoSt и отсутствие пробела одновременно» на pboorucom<br>\n[<img src=\"https://ntc.party/images/emoji/twitter/skull_and_crossbones.png?v=12\" title=\":skull_and_crossbones:\" class=\"emoji\" alt=\":skull_and_crossbones:\" loading=\"lazy\" width=\"20\" height=\"20\">] Сайт не открывается<br>\nПробуем способ «дополнительный пробел после GET» на rutrackerorg<br>\n[✓] Сайт открывается<br>\nПробуем способ «заголовок hOSt вместо Host» на rutrackerorg<br>\n[✓] Сайт открывается<br>\nПробуем способ «заголовок hoSt вместо Host» на rutrackerorg<br>\n[✓] Сайт открывается<br>\nПробуем способ «значение Host БОЛЬШИМИ БУКВАМИ» на rutrackerorg<br>\n[✓] Сайт открывается<br>\nПробуем способ «необычный порядок заголовков» на rutrackerorg<br>\n[✓] Сайт открывается<br>\nПробуем способ «отсутствие пробела между двоеточием и значением заголовка Host» на rutrackerorg<br>\n[✓] Сайт открывается<br>\nПробуем способ «перенос строки в заголовках в UNIX-стиле» на rutrackerorg<br>\n[✓] Сайт открывается<br>\nПробуем способ «перенос строки перед GET» на rutrackerorg<br>\n[✓] Сайт открывается<br>\nПробуем способ «табуляция в конце домена» на rutrackerorg<br>\n[<img src=\"https://ntc.party/images/emoji/twitter/skull_and_crossbones.png?v=12\" title=\":skull_and_crossbones:\" class=\"emoji\" alt=\":skull_and_crossbones:\" loading=\"lazy\" width=\"20\" height=\"20\">] Сайт не открывается<br>\nПробуем способ «точка в конце домена» на rutrackerorg<br>\n[<img src=\"https://ntc.party/images/emoji/twitter/skull_and_crossbones.png?v=12\" title=\":skull_and_crossbones:\" class=\"emoji\" alt=\":skull_and_crossbones:\" loading=\"lazy\" width=\"20\" height=\"20\">] Сайт не открывается<br>\nПробуем способ «фрагментирование заголовка» на rutrackerorg<br>\n[✓] Сайт открывается<br>\nПробуем способ «фрагментирование заголовка, hoSt и отсутствие пробела одновременно» на rutrackerorg<br>\n[✓] Сайт открывается</p>\n<p>[!] Результат:<br>\n[<img src=\"https://ntc.party/images/emoji/twitter/warning.png?v=12\" title=\":warning:\" class=\"emoji\" alt=\":warning:\" loading=\"lazy\" width=\"20\" height=\"20\">] Ваш провайдер подменяет DNS-записи, но не перенаправляет сторонние IPv4 DNS-серверы на свой.<br>\nВам поможет смена DNS, например, на Яндекс.DNS 77.88.8.8 или Google DNS 8.8.8.8 и 8.8.4.4.<br>\n[<img src=\"https://ntc.party/images/emoji/twitter/warning.png?v=12\" title=\":warning:\" class=\"emoji\" alt=\":warning:\" loading=\"lazy\" width=\"20\" height=\"20\">] Ваш провайдер полностью блокирует доступ к HTTPS-сайтам из реестра.<br>\n[<img src=\"https://ntc.party/images/emoji/twitter/warning.png?v=12\" title=\":warning:\" class=\"emoji\" alt=\":warning:\" loading=\"lazy\" width=\"20\" height=\"20\">] isupme даёт неожиданные ответы или недоступен. Рекомендуем повторить тест, когда он начнёт работать. Возможно, эта версия программы устарела. Возможно (но маловероятно), что сам isupme уже занесён в чёрный список.<br>\n[<img src=\"https://ntc.party/images/emoji/twitter/warning.png?v=12\" title=\":warning:\" class=\"emoji\" alt=\":warning:\" loading=\"lazy\" width=\"20\" height=\"20\">] Если проигнорировать isupme, то у вашего провайдера “полный” DPI. Он отслеживает ссылки даже внутри прокси, поэтому вам следует использовать любое шифрованное соединение, например, VPN или Tor.</p>\n</details>",
        "post_number": 6,
        "post_type": 1,
        "posts_count": 25,
        "updated_at": "2020-09-12T17:06:23.872Z",
        "reply_count": 1,
        "reply_to_post_number": 3,
        "quote_count": 1,
        "incoming_link_count": 10,
        "reads": 58,
        "readers_count": 57,
        "score": 66.6,
        "yours": false,
        "topic_id": 668,
        "topic_slug": "%D1%87%D0%B0%D1%81%D1%82%D0%B8%D1%87%D0%BD%D0%BE-%D0%B7%D0%B0%D0%B1%D0%BB%D0%BE%D0%BA%D0%B8%D1%80%D0%BE%D0%B2%D0%B0%D0%BD%D0%BD%D1%8B%D0%B5-%D1%80%D0%B5%D1%81%D1%83%D1%80%D1%81%D1%8B",
        "display_username": "Александр",
        "primary_group_name": null,
        "flair_name": null,
        "flair_url": null,
        "flair_bg_color": null,
        "flair_color": null,
        "flair_group_id": null,
        "badges_granted": [],
        "version": 1,
        "can_edit": false,
        "can_delete": false,
        "can_recover": false,
        "can_see_hidden_post": false,
        "can_wiki": false,
        "link_counts": [
            {
                "url": "http://sknt.ru",
                "internal": false,
                "reflection": false,
                "clicks": 2
            },
            {
                "url": "http://pboorucom/",
                "internal": false,
                "reflection": false,
                "clicks": 1
            },
            {
                "url": "http://furry.booru.org/",
                "internal": false,
                "reflection": false,
                "clicks": 1
            },
            {
                "url": "https://lolibooru.moe/",
                "internal": false,
                "reflection": false,
                "title": "Lolibooru",
                "clicks": 0
            },
            {
                "url": "http://a.putinhuylo.com/",
                "internal": false,
                "reflection": false,
                "title": "Antizapret test page",
                "clicks": 0
            },
            {
                "url": "http://furry.booru.org/index.php?page=post&s=view&id=111173",
                "internal": false,
                "reflection": false,
                "clicks": 0
            },
            {
                "url": "http://rutrackerorg/forum/index.php",
                "internal": false,
                "reflection": false,
                "clicks": 0
            },
            {
                "url": "https://e621.net/",
                "internal": false,
                "reflection": false,
                "clicks": 0
            },
            {
                "url": "http://pboorucom/index.php?page=post&s=view&id=303026",
                "internal": false,
                "reflection": false,
                "clicks": 0
            },
            {
                "url": "https://rutrackerorg/forum/index.php",
                "internal": false,
                "reflection": false,
                "clicks": 0
            },
            {
                "url": "https://www.dailymotion.com/",
                "internal": false,
                "reflection": false,
                "clicks": 0
            }
        ],
        "read": true,
        "user_title": null,
        "bookmarked": false,
        "actions_summary": [],
        "moderator": false,
        "admin": false,
        "staff": false,
        "user_id": 296,
        "hidden": false,
        "trust_level": 0,
        "deleted_at": null,
        "user_deleted": false,
        "edit_reason": null,
        "can_view_edit_history": false,
        "wiki": false,
        "post_url": "/t/%D1%87%D0%B0%D1%81%D1%82%D0%B8%D1%87%D0%BD%D0%BE-%D0%B7%D0%B0%D0%B1%D0%BB%D0%BE%D0%BA%D0%B8%D1%80%D0%BE%D0%B2%D0%B0%D0%BD%D0%BD%D1%8B%D0%B5-%D1%80%D0%B5%D1%81%D1%83%D1%80%D1%81%D1%8B/668/6",
        "can_translate": false
    },
    {
        "id": 1881,
        "name": null,
        "username": "ValdikSS",
        "avatar_template": "/user_avatar/ntc.party/valdikss/{size}/2_2.png",
        "created_at": "2020-09-12T17:49:37.639Z",
        "cooked": "<p>Попробуйте сменить DNS с провайдерского на какой-то другой, например, на <code>8.8.8.8</code>.</p>",
        "post_number": 7,
        "post_type": 1,
        "posts_count": 25,
        "updated_at": "2020-09-12T17:49:37.639Z",
        "reply_count": 1,
        "reply_to_post_number": 6,
        "quote_count": 0,
        "incoming_link_count": 4,
        "reads": 52,
        "readers_count": 51,
        "score": 35.4,
        "yours": false,
        "topic_id": 668,
        "topic_slug": "%D1%87%D0%B0%D1%81%D1%82%D0%B8%D1%87%D0%BD%D0%BE-%D0%B7%D0%B0%D0%B1%D0%BB%D0%BE%D0%BA%D0%B8%D1%80%D0%BE%D0%B2%D0%B0%D0%BD%D0%BD%D1%8B%D0%B5-%D1%80%D0%B5%D1%81%D1%83%D1%80%D1%81%D1%8B",
        "display_username": null,
        "primary_group_name": null,
        "flair_name": null,
        "flair_url": null,
        "flair_bg_color": null,
        "flair_color": null,
        "flair_group_id": null,
        "badges_granted": [],
        "version": 1,
        "can_edit": false,
        "can_delete": false,
        "can_recover": false,
        "can_see_hidden_post": false,
        "can_wiki": false,
        "read": true,
        "user_title": "AntiZapret staff",
        "title_is_group": false,
        "reply_to_user": {
            "username": "Lyinx",
            "name": "Александр",
            "avatar_template": "/user_avatar/ntc.party/lyinx/{size}/382_2.png"
        },
        "bookmarked": false,
        "actions_summary": [],
        "moderator": true,
        "admin": true,
        "staff": true,
        "user_id": 1,
        "hidden": false,
        "trust_level": 2,
        "deleted_at": null,
        "user_deleted": false,
        "edit_reason": null,
        "can_view_edit_history": false,
        "wiki": false,
        "post_url": "/t/%D1%87%D0%B0%D1%81%D1%82%D0%B8%D1%87%D0%BD%D0%BE-%D0%B7%D0%B0%D0%B1%D0%BB%D0%BE%D0%BA%D0%B8%D1%80%D0%BE%D0%B2%D0%B0%D0%BD%D0%BD%D1%8B%D0%B5-%D1%80%D0%B5%D1%81%D1%83%D1%80%D1%81%D1%8B/668/7",
        "can_translate": false
    },
    {
        "id": 1882,
        "name": "Александр",
        "username": "Lyinx",
        "avatar_template": "/user_avatar/ntc.party/lyinx/{size}/382_2.png",
        "created_at": "2020-09-12T18:01:18.814Z",
        "cooked": "<p>Это помогло, правда только через DNS over HTTPS с Cloudflare, DoH через NextDNS не робил.</p>",
        "post_number": 8,
        "post_type": 1,
        "posts_count": 25,
        "updated_at": "2020-09-12T18:01:18.814Z",
        "reply_count": 1,
        "reply_to_post_number": 7,
        "quote_count": 0,
        "incoming_link_count": 5,
        "reads": 52,
        "readers_count": 51,
        "score": 40.4,
        "yours": false,
        "topic_id": 668,
        "topic_slug": "%D1%87%D0%B0%D1%81%D1%82%D0%B8%D1%87%D0%BD%D0%BE-%D0%B7%D0%B0%D0%B1%D0%BB%D0%BE%D0%BA%D0%B8%D1%80%D0%BE%D0%B2%D0%B0%D0%BD%D0%BD%D1%8B%D0%B5-%D1%80%D0%B5%D1%81%D1%83%D1%80%D1%81%D1%8B",
        "display_username": "Александр",
        "primary_group_name": null,
        "flair_name": null,
        "flair_url": null,
        "flair_bg_color": null,
        "flair_color": null,
        "flair_group_id": null,
        "badges_granted": [],
        "version": 1,
        "can_edit": false,
        "can_delete": false,
        "can_recover": false,
        "can_see_hidden_post": false,
        "can_wiki": false,
        "read": true,
        "user_title": null,
        "reply_to_user": {
            "username": "ValdikSS",
            "name": null,
            "avatar_template": "/user_avatar/ntc.party/valdikss/{size}/2_2.png"
        },
        "bookmarked": false,
        "actions_summary": [],
        "moderator": false,
        "admin": false,
        "staff": false,
        "user_id": 296,
        "hidden": false,
        "trust_level": 0,
        "deleted_at": null,
        "user_deleted": false,
        "edit_reason": null,
        "can_view_edit_history": false,
        "wiki": false,
        "post_url": "/t/%D1%87%D0%B0%D1%81%D1%82%D0%B8%D1%87%D0%BD%D0%BE-%D0%B7%D0%B0%D0%B1%D0%BB%D0%BE%D0%BA%D0%B8%D1%80%D0%BE%D0%B2%D0%B0%D0%BD%D0%BD%D1%8B%D0%B5-%D1%80%D0%B5%D1%81%D1%83%D1%80%D1%81%D1%8B/668/8",
        "can_translate": false
    },
    {
        "id": 1883,
        "name": null,
        "username": "ValdikSS",
        "avatar_template": "/user_avatar/ntc.party/valdikss/{size}/2_2.png",
        "created_at": "2020-09-12T18:02:19.512Z",
        "cooked": "<p>Лучше сменить непосредственно на роутере или в настройках ОС, а не в браузере. DoH не очень хорошо работает с PAC-листами.</p>",
        "post_number": 9,
        "post_type": 1,
        "posts_count": 25,
        "updated_at": "2020-09-12T18:02:19.512Z",
        "reply_count": 1,
        "reply_to_post_number": 8,
        "quote_count": 0,
        "incoming_link_count": 4,
        "reads": 51,
        "readers_count": 50,
        "score": 35.2,
        "yours": false,
        "topic_id": 668,
        "topic_slug": "%D1%87%D0%B0%D1%81%D1%82%D0%B8%D1%87%D0%BD%D0%BE-%D0%B7%D0%B0%D0%B1%D0%BB%D0%BE%D0%BA%D0%B8%D1%80%D0%BE%D0%B2%D0%B0%D0%BD%D0%BD%D1%8B%D0%B5-%D1%80%D0%B5%D1%81%D1%83%D1%80%D1%81%D1%8B",
        "display_username": null,
        "primary_group_name": null,
        "flair_name": null,
        "flair_url": null,
        "flair_bg_color": null,
        "flair_color": null,
        "flair_group_id": null,
        "badges_granted": [],
        "version": 1,
        "can_edit": false,
        "can_delete": false,
        "can_recover": false,
        "can_see_hidden_post": false,
        "can_wiki": false,
        "read": true,
        "user_title": "AntiZapret staff",
        "title_is_group": false,
        "reply_to_user": {
            "username": "Lyinx",
            "name": "Александр",
            "avatar_template": "/user_avatar/ntc.party/lyinx/{size}/382_2.png"
        },
        "bookmarked": false,
        "actions_summary": [],
        "moderator": true,
        "admin": true,
        "staff": true,
        "user_id": 1,
        "hidden": false,
        "trust_level": 2,
        "deleted_at": null,
        "user_deleted": false,
        "edit_reason": null,
        "can_view_edit_history": false,
        "wiki": false,
        "post_url": "/t/%D1%87%D0%B0%D1%81%D1%82%D0%B8%D1%87%D0%BD%D0%BE-%D0%B7%D0%B0%D0%B1%D0%BB%D0%BE%D0%BA%D0%B8%D1%80%D0%BE%D0%B2%D0%B0%D0%BD%D0%BD%D1%8B%D0%B5-%D1%80%D0%B5%D1%81%D1%83%D1%80%D1%81%D1%8B/668/9",
        "can_translate": false
    },
    {
        "id": 1884,
        "name": "Александр",
        "username": "Lyinx",
        "avatar_template": "/user_avatar/ntc.party/lyinx/{size}/382_2.png",
        "created_at": "2020-09-12T18:03:50.638Z",
        "cooked": "<p>Ну пока сменил в настройках адаптера. Если получится/не получится на микротике моём - сообщу.</p>",
        "post_number": 10,
        "post_type": 1,
        "posts_count": 25,
        "updated_at": "2020-09-12T18:03:50.638Z",
        "reply_count": 1,
        "reply_to_post_number": 9,
        "quote_count": 0,
        "incoming_link_count": 2,
        "reads": 49,
        "readers_count": 48,
        "score": 24.8,
        "yours": false,
        "topic_id": 668,
        "topic_slug": "%D1%87%D0%B0%D1%81%D1%82%D0%B8%D1%87%D0%BD%D0%BE-%D0%B7%D0%B0%D0%B1%D0%BB%D0%BE%D0%BA%D0%B8%D1%80%D0%BE%D0%B2%D0%B0%D0%BD%D0%BD%D1%8B%D0%B5-%D1%80%D0%B5%D1%81%D1%83%D1%80%D1%81%D1%8B",
        "display_username": "Александр",
        "primary_group_name": null,
        "flair_name": null,
        "flair_url": null,
        "flair_bg_color": null,
        "flair_color": null,
        "flair_group_id": null,
        "badges_granted": [],
        "version": 1,
        "can_edit": false,
        "can_delete": false,
        "can_recover": false,
        "can_see_hidden_post": false,
        "can_wiki": false,
        "read": true,
        "user_title": null,
        "reply_to_user": {
            "username": "ValdikSS",
            "name": null,
            "avatar_template": "/user_avatar/ntc.party/valdikss/{size}/2_2.png"
        },
        "bookmarked": false,
        "actions_summary": [],
        "moderator": false,
        "admin": false,
        "staff": false,
        "user_id": 296,
        "hidden": false,
        "trust_level": 0,
        "deleted_at": null,
        "user_deleted": false,
        "edit_reason": null,
        "can_view_edit_history": false,
        "wiki": false,
        "post_url": "/t/%D1%87%D0%B0%D1%81%D1%82%D0%B8%D1%87%D0%BD%D0%BE-%D0%B7%D0%B0%D0%B1%D0%BB%D0%BE%D0%BA%D0%B8%D1%80%D0%BE%D0%B2%D0%B0%D0%BD%D0%BD%D1%8B%D0%B5-%D1%80%D0%B5%D1%81%D1%83%D1%80%D1%81%D1%8B/668/10",
        "can_translate": false
    },
    {
        "id": 1885,
        "name": "Александр",
        "username": "Lyinx",
        "avatar_template": "/user_avatar/ntc.party/lyinx/{size}/382_2.png",
        "created_at": "2020-09-12T18:11:03.503Z",
        "cooked": "<p>Да, сработало и через микротик.<br>\nХотя в обоих вариантах слегка страдает скорость.</p>",
        "post_number": 11,
        "post_type": 1,
        "posts_count": 25,
        "updated_at": "2020-09-12T18:11:03.503Z",
        "reply_count": 0,
        "reply_to_post_number": 10,
        "quote_count": 0,
        "incoming_link_count": 3,
        "reads": 48,
        "readers_count": 47,
        "score": 24.6,
        "yours": false,
        "topic_id": 668,
        "topic_slug": "%D1%87%D0%B0%D1%81%D1%82%D0%B8%D1%87%D0%BD%D0%BE-%D0%B7%D0%B0%D0%B1%D0%BB%D0%BE%D0%BA%D0%B8%D1%80%D0%BE%D0%B2%D0%B0%D0%BD%D0%BD%D1%8B%D0%B5-%D1%80%D0%B5%D1%81%D1%83%D1%80%D1%81%D1%8B",
        "display_username": "Александр",
        "primary_group_name": null,
        "flair_name": null,
        "flair_url": null,
        "flair_bg_color": null,
        "flair_color": null,
        "flair_group_id": null,
        "badges_granted": [],
        "version": 1,
        "can_edit": false,
        "can_delete": false,
        "can_recover": false,
        "can_see_hidden_post": false,
        "can_wiki": false,
        "read": true,
        "user_title": null,
        "reply_to_user": {
            "username": "Lyinx",
            "name": "Александр",
            "avatar_template": "/user_avatar/ntc.party/lyinx/{size}/382_2.png"
        },
        "bookmarked": false,
        "actions_summary": [],
        "moderator": false,
        "admin": false,
        "staff": false,
        "user_id": 296,
        "hidden": false,
        "trust_level": 0,
        "deleted_at": null,
        "user_deleted": false,
        "edit_reason": null,
        "can_view_edit_history": false,
        "wiki": false,
        "post_url": "/t/%D1%87%D0%B0%D1%81%D1%82%D0%B8%D1%87%D0%BD%D0%BE-%D0%B7%D0%B0%D0%B1%D0%BB%D0%BE%D0%BA%D0%B8%D1%80%D0%BE%D0%B2%D0%B0%D0%BD%D0%BD%D1%8B%D0%B5-%D1%80%D0%B5%D1%81%D1%83%D1%80%D1%81%D1%8B/668/11",
        "can_translate": false
    },
    {
        "id": 2339,
        "name": "",
        "username": "JIPCOROD",
        "avatar_template": "/user_avatar/ntc.party/jipcorod/{size}/6810_2.png",
        "created_at": "2021-01-12T11:19:54.003Z",
        "cooked": "<p>Дов**бы#ся((((  <div class=\"lightbox-wrapper\"><a class=\"lightbox\" href=\"частично-заблокированные-ресурсы-668/f850f118bca04e6860cf7503d8d6fea4244c09fe.png\" data-download-href=\"https://ntc.party/uploads/default/f850f118bca04e6860cf7503d8d6fea4244c09fe\" title=\"image\"><img src=\"частично-заблокированные-ресурсы-668/f850f118bca04e6860cf7503d8d6fea4244c09fe.png\" alt=\"image\" data-base62-sha1=\"zqHPr9c5ZE1qjNofuOJVFOhERoa\" width=\"690\" height=\"403\" data-dominant-color=\"F7F8F9\"><div class=\"meta\"><svg class=\"fa d-icon d-icon-far-image svg-icon\" aria-hidden=\"true\"><use href=\"#far-image\"></use></svg><span class=\"filename\">image</span><span class=\"informations\">755×442 25.7 KB</span><svg class=\"fa d-icon d-icon-discourse-expand svg-icon\" aria-hidden=\"true\"><use href=\"#discourse-expand\"></use></svg></div></a></div></p>",
        "post_number": 12,
        "post_type": 1,
        "posts_count": 25,
        "updated_at": "2021-01-12T11:19:54.003Z",
        "reply_count": 0,
        "reply_to_post_number": null,
        "quote_count": 0,
        "incoming_link_count": 23,
        "reads": 43,
        "readers_count": 42,
        "score": 123.6,
        "yours": false,
        "topic_id": 668,
        "topic_slug": "%D1%87%D0%B0%D1%81%D1%82%D0%B8%D1%87%D0%BD%D0%BE-%D0%B7%D0%B0%D0%B1%D0%BB%D0%BE%D0%BA%D0%B8%D1%80%D0%BE%D0%B2%D0%B0%D0%BD%D0%BD%D1%8B%D0%B5-%D1%80%D0%B5%D1%81%D1%83%D1%80%D1%81%D1%8B",
        "display_username": "",
        "primary_group_name": null,
        "flair_name": null,
        "flair_url": null,
        "flair_bg_color": null,
        "flair_color": null,
        "flair_group_id": null,
        "badges_granted": [],
        "version": 1,
        "can_edit": false,
        "can_delete": false,
        "can_recover": false,
        "can_see_hidden_post": false,
        "can_wiki": false,
        "read": true,
        "user_title": "",
        "bookmarked": false,
        "actions_summary": [],
        "moderator": false,
        "admin": false,
        "staff": false,
        "user_id": 287,
        "hidden": false,
        "trust_level": 2,
        "deleted_at": null,
        "user_deleted": false,
        "edit_reason": null,
        "can_view_edit_history": false,
        "wiki": false,
        "post_url": "/t/%D1%87%D0%B0%D1%81%D1%82%D0%B8%D1%87%D0%BD%D0%BE-%D0%B7%D0%B0%D0%B1%D0%BB%D0%BE%D0%BA%D0%B8%D1%80%D0%BE%D0%B2%D0%B0%D0%BD%D0%BD%D1%8B%D0%B5-%D1%80%D0%B5%D1%81%D1%83%D1%80%D1%81%D1%8B/668/12",
        "can_translate": false
    },
    {
        "id": 2921,
        "name": "",
        "username": "xmn",
        "avatar_template": "/letter_avatar_proxy/v4/letter/x/e19b73/{size}.png",
        "created_at": "2021-03-24T01:34:45.899Z",
        "cooked": "<p>Здравствуйте <strong>ValdikSS</strong> возможно пора добавить <a href=\"http://ecchi.iwara.tv\" rel=\"noopener nofollow ugc\">ecchi.iwara.tv</a></p>",
        "post_number": 13,
        "post_type": 1,
        "posts_count": 25,
        "updated_at": "2021-03-24T01:34:45.899Z",
        "reply_count": 0,
        "reply_to_post_number": null,
        "quote_count": 0,
        "incoming_link_count": 9,
        "reads": 39,
        "readers_count": 38,
        "score": 52.8,
        "yours": false,
        "topic_id": 668,
        "topic_slug": "%D1%87%D0%B0%D1%81%D1%82%D0%B8%D1%87%D0%BD%D0%BE-%D0%B7%D0%B0%D0%B1%D0%BB%D0%BE%D0%BA%D0%B8%D1%80%D0%BE%D0%B2%D0%B0%D0%BD%D0%BD%D1%8B%D0%B5-%D1%80%D0%B5%D1%81%D1%83%D1%80%D1%81%D1%8B",
        "display_username": "",
        "primary_group_name": null,
        "flair_name": null,
        "flair_url": null,
        "flair_bg_color": null,
        "flair_color": null,
        "flair_group_id": null,
        "badges_granted": [],
        "version": 1,
        "can_edit": false,
        "can_delete": false,
        "can_recover": false,
        "can_see_hidden_post": false,
        "can_wiki": false,
        "link_counts": [
            {
                "url": "http://ecchi.iwara.tv",
                "internal": false,
                "reflection": false,
                "clicks": 24
            }
        ],
        "read": true,
        "user_title": null,
        "bookmarked": false,
        "actions_summary": [],
        "moderator": false,
        "admin": false,
        "staff": false,
        "user_id": 460,
        "hidden": false,
        "trust_level": 1,
        "deleted_at": null,
        "user_deleted": false,
        "edit_reason": null,
        "can_view_edit_history": false,
        "wiki": false,
        "post_url": "/t/%D1%87%D0%B0%D1%81%D1%82%D0%B8%D1%87%D0%BD%D0%BE-%D0%B7%D0%B0%D0%B1%D0%BB%D0%BE%D0%BA%D0%B8%D1%80%D0%BE%D0%B2%D0%B0%D0%BD%D0%BD%D1%8B%D0%B5-%D1%80%D0%B5%D1%81%D1%83%D1%80%D1%81%D1%8B/668/13",
        "can_translate": false
    },
    {
        "id": 2924,
        "name": "",
        "username": "JIPCOROD",
        "avatar_template": "/user_avatar/ntc.party/jipcorod/{size}/6810_2.png",
        "created_at": "2021-03-25T05:37:44.627Z",
        "cooked": "<p>согласен. Главное без домена с самим контентом <a href=\"http://megurine.iwara.tv\" rel=\"noopener nofollow ugc\">megurine.iwara.tv</a> по тому что он не находиться в реестре! А грузить сами видео через прокси в сентябре, когда я писал эту тему, было просто невозможно медленно</p>",
        "post_number": 14,
        "post_type": 1,
        "posts_count": 25,
        "updated_at": "2021-03-25T05:37:44.627Z",
        "reply_count": 0,
        "reply_to_post_number": null,
        "quote_count": 0,
        "incoming_link_count": 10,
        "reads": 37,
        "readers_count": 36,
        "score": 57.4,
        "yours": false,
        "topic_id": 668,
        "topic_slug": "%D1%87%D0%B0%D1%81%D1%82%D0%B8%D1%87%D0%BD%D0%BE-%D0%B7%D0%B0%D0%B1%D0%BB%D0%BE%D0%BA%D0%B8%D1%80%D0%BE%D0%B2%D0%B0%D0%BD%D0%BD%D1%8B%D0%B5-%D1%80%D0%B5%D1%81%D1%83%D1%80%D1%81%D1%8B",
        "display_username": "",
        "primary_group_name": null,
        "flair_name": null,
        "flair_url": null,
        "flair_bg_color": null,
        "flair_color": null,
        "flair_group_id": null,
        "badges_granted": [],
        "version": 1,
        "can_edit": false,
        "can_delete": false,
        "can_recover": false,
        "can_see_hidden_post": false,
        "can_wiki": false,
        "link_counts": [
            {
                "url": "http://megurine.iwara.tv",
                "internal": false,
                "reflection": false,
                "clicks": 17
            }
        ],
        "read": true,
        "user_title": "",
        "bookmarked": false,
        "actions_summary": [],
        "moderator": false,
        "admin": false,
        "staff": false,
        "user_id": 287,
        "hidden": false,
        "trust_level": 2,
        "deleted_at": null,
        "user_deleted": false,
        "edit_reason": null,
        "can_view_edit_history": false,
        "wiki": false,
        "post_url": "/t/%D1%87%D0%B0%D1%81%D1%82%D0%B8%D1%87%D0%BD%D0%BE-%D0%B7%D0%B0%D0%B1%D0%BB%D0%BE%D0%BA%D0%B8%D1%80%D0%BE%D0%B2%D0%B0%D0%BD%D0%BD%D1%8B%D0%B5-%D1%80%D0%B5%D1%81%D1%83%D1%80%D1%81%D1%8B/668/14",
        "can_translate": false
    },
    {
        "id": 2927,
        "name": null,
        "username": "ValdikSS",
        "avatar_template": "/user_avatar/ntc.party/valdikss/{size}/2_2.png",
        "created_at": "2021-03-27T09:59:09.912Z",
        "cooked": "<p>Готово, <a href=\"http://ecchi.iwara.tv\">ecchi.iwara.tv</a> опять проксируется.</p>",
        "post_number": 15,
        "post_type": 1,
        "posts_count": 25,
        "updated_at": "2021-03-27T09:59:09.912Z",
        "reply_count": 0,
        "reply_to_post_number": null,
        "quote_count": 0,
        "incoming_link_count": 2,
        "reads": 36,
        "readers_count": 35,
        "score": 17.2,
        "yours": false,
        "topic_id": 668,
        "topic_slug": "%D1%87%D0%B0%D1%81%D1%82%D0%B8%D1%87%D0%BD%D0%BE-%D0%B7%D0%B0%D0%B1%D0%BB%D0%BE%D0%BA%D0%B8%D1%80%D0%BE%D0%B2%D0%B0%D0%BD%D0%BD%D1%8B%D0%B5-%D1%80%D0%B5%D1%81%D1%83%D1%80%D1%81%D1%8B",
        "display_username": null,
        "primary_group_name": null,
        "flair_name": null,
        "flair_url": null,
        "flair_bg_color": null,
        "flair_color": null,
        "flair_group_id": null,
        "badges_granted": [],
        "version": 1,
        "can_edit": false,
        "can_delete": false,
        "can_recover": false,
        "can_see_hidden_post": false,
        "can_wiki": false,
        "link_counts": [
            {
                "url": "http://ecchi.iwara.tv",
                "internal": false,
                "reflection": false,
                "clicks": 18
            }
        ],
        "read": true,
        "user_title": "AntiZapret staff",
        "title_is_group": false,
        "bookmarked": false,
        "actions_summary": [],
        "moderator": true,
        "admin": true,
        "staff": true,
        "user_id": 1,
        "hidden": false,
        "trust_level": 2,
        "deleted_at": null,
        "user_deleted": false,
        "edit_reason": null,
        "can_view_edit_history": false,
        "wiki": false,
        "post_url": "/t/%D1%87%D0%B0%D1%81%D1%82%D0%B8%D1%87%D0%BD%D0%BE-%D0%B7%D0%B0%D0%B1%D0%BB%D0%BE%D0%BA%D0%B8%D1%80%D0%BE%D0%B2%D0%B0%D0%BD%D0%BD%D1%8B%D0%B5-%D1%80%D0%B5%D1%81%D1%83%D1%80%D1%81%D1%8B/668/15",
        "can_translate": false
    },
    {
        "id": 3001,
        "name": "",
        "username": "JIPCOROD",
        "avatar_template": "/user_avatar/ntc.party/jipcorod/{size}/6810_2.png",
        "created_at": "2021-04-23T09:44:22.167Z",
        "cooked": "<p>Пожалуйста, добавите в исключения эти псубдоменны <a href=\"http://pximg.net\" rel=\"noopener nofollow ugc\">pximg.net</a> - из-за их проектирования пиксив полумёртвый<br>\n<img src=\"частично-заблокированные-ресурсы-668/d2afd9500e011caf5e80387e50d7273becc24c13.png\" alt=\"image\" data-base62-sha1=\"u3P1rtEvSKARa74rALnb9Kqqmc3\" width=\"349\" height=\"162\"></p>\n<p>Попало из-за налётов на booth <a href=\"http://reestr.rublacklist.net/search/?q=pximg.net\" rel=\"noopener nofollow ugc\">reestr.rublacklist.net/search/?q=pximg.net</a></p>",
        "post_number": 16,
        "post_type": 1,
        "posts_count": 25,
        "updated_at": "2021-04-23T09:49:27.972Z",
        "reply_count": 1,
        "reply_to_post_number": null,
        "quote_count": 0,
        "incoming_link_count": 6,
        "reads": 32,
        "readers_count": 31,
        "score": 41.4,
        "yours": false,
        "topic_id": 668,
        "topic_slug": "%D1%87%D0%B0%D1%81%D1%82%D0%B8%D1%87%D0%BD%D0%BE-%D0%B7%D0%B0%D0%B1%D0%BB%D0%BE%D0%BA%D0%B8%D1%80%D0%BE%D0%B2%D0%B0%D0%BD%D0%BD%D1%8B%D0%B5-%D1%80%D0%B5%D1%81%D1%83%D1%80%D1%81%D1%8B",
        "display_username": "",
        "primary_group_name": null,
        "flair_name": null,
        "flair_url": null,
        "flair_bg_color": null,
        "flair_color": null,
        "flair_group_id": null,
        "badges_granted": [],
        "version": 2,
        "can_edit": false,
        "can_delete": false,
        "can_recover": false,
        "can_see_hidden_post": false,
        "can_wiki": false,
        "link_counts": [
            {
                "url": "http://pximg.net",
                "internal": false,
                "reflection": false,
                "title": "pximg.net",
                "clicks": 6
            },
            {
                "url": "http://reestr.rublacklist.net/search/?q=pximg.net",
                "internal": false,
                "reflection": false,
                "clicks": 3
            }
        ],
        "read": true,
        "user_title": "",
        "bookmarked": false,
        "actions_summary": [],
        "moderator": false,
        "admin": false,
        "staff": false,
        "user_id": 287,
        "hidden": false,
        "trust_level": 2,
        "deleted_at": null,
        "user_deleted": false,
        "edit_reason": null,
        "can_view_edit_history": false,
        "wiki": false,
        "post_url": "/t/%D1%87%D0%B0%D1%81%D1%82%D0%B8%D1%87%D0%BD%D0%BE-%D0%B7%D0%B0%D0%B1%D0%BB%D0%BE%D0%BA%D0%B8%D1%80%D0%BE%D0%B2%D0%B0%D0%BD%D0%BD%D1%8B%D0%B5-%D1%80%D0%B5%D1%81%D1%83%D1%80%D1%81%D1%8B/668/16",
        "can_translate": false
    },
    {
        "id": 3002,
        "name": null,
        "username": "ValdikSS",
        "avatar_template": "/user_avatar/ntc.party/valdikss/{size}/2_2.png",
        "created_at": "2021-04-23T22:18:04.739Z",
        "cooked": "<p>Готово.</p>",
        "post_number": 17,
        "post_type": 1,
        "posts_count": 25,
        "updated_at": "2021-04-23T22:18:04.739Z",
        "reply_count": 0,
        "reply_to_post_number": 16,
        "quote_count": 0,
        "incoming_link_count": 1,
        "reads": 32,
        "readers_count": 31,
        "score": 11.4,
        "yours": false,
        "topic_id": 668,
        "topic_slug": "%D1%87%D0%B0%D1%81%D1%82%D0%B8%D1%87%D0%BD%D0%BE-%D0%B7%D0%B0%D0%B1%D0%BB%D0%BE%D0%BA%D0%B8%D1%80%D0%BE%D0%B2%D0%B0%D0%BD%D0%BD%D1%8B%D0%B5-%D1%80%D0%B5%D1%81%D1%83%D1%80%D1%81%D1%8B",
        "display_username": null,
        "primary_group_name": null,
        "flair_name": null,
        "flair_url": null,
        "flair_bg_color": null,
        "flair_color": null,
        "flair_group_id": null,
        "badges_granted": [],
        "version": 1,
        "can_edit": false,
        "can_delete": false,
        "can_recover": false,
        "can_see_hidden_post": false,
        "can_wiki": false,
        "read": true,
        "user_title": "AntiZapret staff",
        "title_is_group": false,
        "reply_to_user": {
            "username": "JIPCOROD",
            "name": "",
            "avatar_template": "/user_avatar/ntc.party/jipcorod/{size}/6810_2.png"
        },
        "bookmarked": false,
        "actions_summary": [],
        "moderator": true,
        "admin": true,
        "staff": true,
        "user_id": 1,
        "hidden": false,
        "trust_level": 2,
        "deleted_at": null,
        "user_deleted": false,
        "edit_reason": null,
        "can_view_edit_history": false,
        "wiki": false,
        "post_url": "/t/%D1%87%D0%B0%D1%81%D1%82%D0%B8%D1%87%D0%BD%D0%BE-%D0%B7%D0%B0%D0%B1%D0%BB%D0%BE%D0%BA%D0%B8%D1%80%D0%BE%D0%B2%D0%B0%D0%BD%D0%BD%D1%8B%D0%B5-%D1%80%D0%B5%D1%81%D1%83%D1%80%D1%81%D1%8B/668/17",
        "can_translate": false
    },
    {
        "id": 3290,
        "name": "",
        "username": "JIPCOROD",
        "avatar_template": "/user_avatar/ntc.party/jipcorod/{size}/6810_2.png",
        "created_at": "2021-06-25T14:40:21.221Z",
        "cooked": "<p>и снова здравствуйте)<br>\n<a href=\"http://bp.blogspot.com\" rel=\"noopener nofollow ugc\">bp.blogspot.com</a> внесёны все <a href=\"https://reestr.rublacklist.net/search/3?q=bp.blogspot.com\" rel=\"noopener nofollow ugc\">через http</a> и в проксировании не нуждается + это вообще кусок гугла</p>\n<p><img src=\"частично-заблокированные-ресурсы-668/3b1886ef4ba884fc617bcc4fa96a1fc39cc9111c.png\" alt=\"изображение\" data-base62-sha1=\"8qMICUYyd5Pq8W3RBN0T46Xyn1y\" width=\"420\" height=\"123\"></p>",
        "post_number": 18,
        "post_type": 1,
        "posts_count": 25,
        "updated_at": "2021-06-25T14:44:23.395Z",
        "reply_count": 1,
        "reply_to_post_number": null,
        "quote_count": 0,
        "incoming_link_count": 16,
        "reads": 33,
        "readers_count": 32,
        "score": 91.6,
        "yours": false,
        "topic_id": 668,
        "topic_slug": "%D1%87%D0%B0%D1%81%D1%82%D0%B8%D1%87%D0%BD%D0%BE-%D0%B7%D0%B0%D0%B1%D0%BB%D0%BE%D0%BA%D0%B8%D1%80%D0%BE%D0%B2%D0%B0%D0%BD%D0%BD%D1%8B%D0%B5-%D1%80%D0%B5%D1%81%D1%83%D1%80%D1%81%D1%8B",
        "display_username": "",
        "primary_group_name": null,
        "flair_name": null,
        "flair_url": null,
        "flair_bg_color": null,
        "flair_color": null,
        "flair_group_id": null,
        "badges_granted": [],
        "version": 1,
        "can_edit": false,
        "can_delete": false,
        "can_recover": false,
        "can_see_hidden_post": false,
        "can_wiki": false,
        "link_counts": [
            {
                "url": "http://bp.blogspot.com",
                "internal": false,
                "reflection": false,
                "clicks": 2
            },
            {
                "url": "https://reestr.rublacklist.net/search/3?q=bp.blogspot.com",
                "internal": false,
                "reflection": false,
                "clicks": 0
            }
        ],
        "read": true,
        "user_title": "",
        "bookmarked": false,
        "actions_summary": [],
        "moderator": false,
        "admin": false,
        "staff": false,
        "user_id": 287,
        "hidden": false,
        "trust_level": 2,
        "deleted_at": null,
        "user_deleted": false,
        "edit_reason": null,
        "can_view_edit_history": false,
        "wiki": false,
        "post_url": "/t/%D1%87%D0%B0%D1%81%D1%82%D0%B8%D1%87%D0%BD%D0%BE-%D0%B7%D0%B0%D0%B1%D0%BB%D0%BE%D0%BA%D0%B8%D1%80%D0%BE%D0%B2%D0%B0%D0%BD%D0%BD%D1%8B%D0%B5-%D1%80%D0%B5%D1%81%D1%83%D1%80%D1%81%D1%8B/668/18",
        "can_translate": false
    },
    {
        "id": 3292,
        "name": null,
        "username": "ValdikSS",
        "avatar_template": "/user_avatar/ntc.party/valdikss/{size}/2_2.png",
        "created_at": "2021-06-25T18:47:28.116Z",
        "cooked": "<p>Исключение для него сделать проблематично.</p>",
        "post_number": 19,
        "post_type": 1,
        "posts_count": 25,
        "updated_at": "2021-06-25T18:47:28.116Z",
        "reply_count": 0,
        "reply_to_post_number": 18,
        "quote_count": 0,
        "incoming_link_count": 10,
        "reads": 34,
        "readers_count": 33,
        "score": 56.8,
        "yours": false,
        "topic_id": 668,
        "topic_slug": "%D1%87%D0%B0%D1%81%D1%82%D0%B8%D1%87%D0%BD%D0%BE-%D0%B7%D0%B0%D0%B1%D0%BB%D0%BE%D0%BA%D0%B8%D1%80%D0%BE%D0%B2%D0%B0%D0%BD%D0%BD%D1%8B%D0%B5-%D1%80%D0%B5%D1%81%D1%83%D1%80%D1%81%D1%8B",
        "display_username": null,
        "primary_group_name": null,
        "flair_name": null,
        "flair_url": null,
        "flair_bg_color": null,
        "flair_color": null,
        "flair_group_id": null,
        "badges_granted": [],
        "version": 1,
        "can_edit": false,
        "can_delete": false,
        "can_recover": false,
        "can_see_hidden_post": false,
        "can_wiki": false,
        "read": true,
        "user_title": "AntiZapret staff",
        "title_is_group": false,
        "reply_to_user": {
            "username": "JIPCOROD",
            "name": "",
            "avatar_template": "/user_avatar/ntc.party/jipcorod/{size}/6810_2.png"
        },
        "bookmarked": false,
        "actions_summary": [],
        "moderator": true,
        "admin": true,
        "staff": true,
        "user_id": 1,
        "hidden": false,
        "trust_level": 2,
        "deleted_at": null,
        "user_deleted": false,
        "edit_reason": null,
        "can_view_edit_history": false,
        "wiki": false,
        "post_url": "/t/%D1%87%D0%B0%D1%81%D1%82%D0%B8%D1%87%D0%BD%D0%BE-%D0%B7%D0%B0%D0%B1%D0%BB%D0%BE%D0%BA%D0%B8%D1%80%D0%BE%D0%B2%D0%B0%D0%BD%D0%BD%D1%8B%D0%B5-%D1%80%D0%B5%D1%81%D1%83%D1%80%D1%81%D1%8B/668/19",
        "can_translate": false
    },
    {
        "id": 3424,
        "name": null,
        "username": "ValdikSS",
        "avatar_template": "/user_avatar/ntc.party/valdikss/{size}/2_2.png",
        "created_at": "2021-07-15T20:56:30.684Z",
        "cooked": "<p><a href=\"http://Pixiv.net\">Pixiv.net</a> снова добавлен в список (вернее, убран из списка исключений) по причине попадания в реестр по HTTPS-ссылке, что привело к блокировке всего ресурса.<br>\n<a href=\"https://reestr.rublacklist.net/record/3411314/\" class=\"inline-onebox\">Реестр запрещенных сайтов</a></p>",
        "post_number": 20,
        "post_type": 1,
        "posts_count": 25,
        "updated_at": "2021-07-15T20:56:30.684Z",
        "reply_count": 0,
        "reply_to_post_number": null,
        "quote_count": 0,
        "incoming_link_count": 11,
        "reads": 36,
        "readers_count": 35,
        "score": 62.2,
        "yours": false,
        "topic_id": 668,
        "topic_slug": "%D1%87%D0%B0%D1%81%D1%82%D0%B8%D1%87%D0%BD%D0%BE-%D0%B7%D0%B0%D0%B1%D0%BB%D0%BE%D0%BA%D0%B8%D1%80%D0%BE%D0%B2%D0%B0%D0%BD%D0%BD%D1%8B%D0%B5-%D1%80%D0%B5%D1%81%D1%83%D1%80%D1%81%D1%8B",
        "display_username": null,
        "primary_group_name": null,
        "flair_name": null,
        "flair_url": null,
        "flair_bg_color": null,
        "flair_color": null,
        "flair_group_id": null,
        "badges_granted": [],
        "version": 1,
        "can_edit": false,
        "can_delete": false,
        "can_recover": false,
        "can_see_hidden_post": false,
        "can_wiki": false,
        "link_counts": [
            {
                "url": "https://reestr.rublacklist.net/record/3411314/",
                "internal": false,
                "reflection": false,
                "title": "Реестр запрещенных сайтов",
                "clicks": 26
            },
            {
                "url": "http://Pixiv.net",
                "internal": false,
                "reflection": false,
                "clicks": 20
            }
        ],
        "read": true,
        "user_title": "AntiZapret staff",
        "title_is_group": false,
        "bookmarked": false,
        "actions_summary": [],
        "moderator": true,
        "admin": true,
        "staff": true,
        "user_id": 1,
        "hidden": false,
        "trust_level": 2,
        "deleted_at": null,
        "user_deleted": false,
        "edit_reason": null,
        "can_view_edit_history": false,
        "wiki": false,
        "post_url": "/t/%D1%87%D0%B0%D1%81%D1%82%D0%B8%D1%87%D0%BD%D0%BE-%D0%B7%D0%B0%D0%B1%D0%BB%D0%BE%D0%BA%D0%B8%D1%80%D0%BE%D0%B2%D0%B0%D0%BD%D0%BD%D1%8B%D0%B5-%D1%80%D0%B5%D1%81%D1%83%D1%80%D1%81%D1%8B/668/20",
        "can_translate": false
    },
    {
        "id": 3430,
        "name": "",
        "username": "JIPCOROD",
        "avatar_template": "/user_avatar/ntc.party/jipcorod/{size}/6810_2.png",
        "created_at": "2021-07-17T23:54:31.568Z",
        "cooked": "<p>думаю до конца месяца ту <strong>удалённую</strong> картинку уже открутят.</p>\n<p>iawra провела реорганизацию и теперь сидит на Cloudflare с другим ip. Но её могут опять внести, требования они точно выполнять не собираться, а систему разграничений им делать уже очень поздно.<br>\nСпасибо разработчикам расширения за белый список, а РКН (сквозь зубы) за невнимательность по отношению к многочисленным ip сложных систем)</p>",
        "post_number": 21,
        "post_type": 1,
        "posts_count": 25,
        "updated_at": "2021-07-18T00:01:01.807Z",
        "reply_count": 0,
        "reply_to_post_number": null,
        "quote_count": 0,
        "incoming_link_count": 25,
        "reads": 35,
        "readers_count": 34,
        "score": 132.0,
        "yours": false,
        "topic_id": 668,
        "topic_slug": "%D1%87%D0%B0%D1%81%D1%82%D0%B8%D1%87%D0%BD%D0%BE-%D0%B7%D0%B0%D0%B1%D0%BB%D0%BE%D0%BA%D0%B8%D1%80%D0%BE%D0%B2%D0%B0%D0%BD%D0%BD%D1%8B%D0%B5-%D1%80%D0%B5%D1%81%D1%83%D1%80%D1%81%D1%8B",
        "display_username": "",
        "primary_group_name": null,
        "flair_name": null,
        "flair_url": null,
        "flair_bg_color": null,
        "flair_color": null,
        "flair_group_id": null,
        "badges_granted": [],
        "version": 2,
        "can_edit": false,
        "can_delete": false,
        "can_recover": false,
        "can_see_hidden_post": false,
        "can_wiki": false,
        "read": true,
        "user_title": "",
        "bookmarked": false,
        "actions_summary": [],
        "moderator": false,
        "admin": false,
        "staff": false,
        "user_id": 287,
        "hidden": false,
        "trust_level": 2,
        "deleted_at": null,
        "user_deleted": false,
        "edit_reason": null,
        "can_view_edit_history": false,
        "wiki": false,
        "post_url": "/t/%D1%87%D0%B0%D1%81%D1%82%D0%B8%D1%87%D0%BD%D0%BE-%D0%B7%D0%B0%D0%B1%D0%BB%D0%BE%D0%BA%D0%B8%D1%80%D0%BE%D0%B2%D0%B0%D0%BD%D0%BD%D1%8B%D0%B5-%D1%80%D0%B5%D1%81%D1%83%D1%80%D1%81%D1%8B/668/21",
        "can_translate": false
    },
    {
        "id": 6553,
        "name": "",
        "username": "xmn",
        "avatar_template": "/letter_avatar_proxy/v4/letter/x/e19b73/{size}.png",
        "created_at": "2022-03-28T01:23:02.648Z",
        "cooked": "<p><strong>ValdikSS</strong><br>\nЗдравствуйте. Сейчас сложное время, но возможно можно исправить ситуацию с iwara. Если раньше ркн внес по https субдомен <a href=\"http://ecchi.iwara.tv\" rel=\"noopener nofollow ugc\">ecchi.iwara.tv</a> то 23 марта в блок по https попал весь <a href=\"http://iwara.tv\" rel=\"noopener nofollow ugc\">iwara.tv</a> <a href=\"https://reestr.rublacklist.net/search/?q=iwara\" rel=\"noopener nofollow ugc\">https://reestr.rublacklist.net/search/?q=iwara</a></p>\n<p>Теперь соответственно не работают ни изображения, ни видео.</p>",
        "post_number": 22,
        "post_type": 1,
        "posts_count": 25,
        "updated_at": "2022-03-28T01:23:02.648Z",
        "reply_count": 1,
        "reply_to_post_number": null,
        "quote_count": 0,
        "incoming_link_count": 1,
        "reads": 33,
        "readers_count": 32,
        "score": 16.6,
        "yours": false,
        "topic_id": 668,
        "topic_slug": "%D1%87%D0%B0%D1%81%D1%82%D0%B8%D1%87%D0%BD%D0%BE-%D0%B7%D0%B0%D0%B1%D0%BB%D0%BE%D0%BA%D0%B8%D1%80%D0%BE%D0%B2%D0%B0%D0%BD%D0%BD%D1%8B%D0%B5-%D1%80%D0%B5%D1%81%D1%83%D1%80%D1%81%D1%8B",
        "display_username": "",
        "primary_group_name": null,
        "flair_name": null,
        "flair_url": null,
        "flair_bg_color": null,
        "flair_color": null,
        "flair_group_id": null,
        "badges_granted": [],
        "version": 1,
        "can_edit": false,
        "can_delete": false,
        "can_recover": false,
        "can_see_hidden_post": false,
        "can_wiki": false,
        "link_counts": [
            {
                "url": "http://iwara.tv",
                "internal": false,
                "reflection": false,
                "title": "ホーム | Iwara",
                "clicks": 3
            },
            {
                "url": "http://ecchi.iwara.tv",
                "internal": false,
                "reflection": false,
                "title": "ホーム | Iwara",
                "clicks": 3
            },
            {
                "url": "https://reestr.rublacklist.net/search/?q=iwara",
                "internal": false,
                "reflection": false,
                "title": "Реестр запрещенных сайтов",
                "clicks": 2
            }
        ],
        "read": true,
        "user_title": null,
        "bookmarked": false,
        "actions_summary": [],
        "moderator": false,
        "admin": false,
        "staff": false,
        "user_id": 460,
        "hidden": false,
        "trust_level": 1,
        "deleted_at": null,
        "user_deleted": false,
        "edit_reason": null,
        "can_view_edit_history": false,
        "wiki": false,
        "post_url": "/t/%D1%87%D0%B0%D1%81%D1%82%D0%B8%D1%87%D0%BD%D0%BE-%D0%B7%D0%B0%D0%B1%D0%BB%D0%BE%D0%BA%D0%B8%D1%80%D0%BE%D0%B2%D0%B0%D0%BD%D0%BD%D1%8B%D0%B5-%D1%80%D0%B5%D1%81%D1%83%D1%80%D1%81%D1%8B/668/22",
        "can_translate": false
    },
    {
        "id": 6569,
        "name": null,
        "username": "ValdikSS",
        "avatar_template": "/user_avatar/ntc.party/valdikss/{size}/2_2.png",
        "created_at": "2022-03-28T09:44:34.967Z",
        "cooked": "<p>Лист обновиться в течение 6 часов.</p>",
        "post_number": 23,
        "post_type": 1,
        "posts_count": 25,
        "updated_at": "2022-03-28T09:44:34.967Z",
        "reply_count": 0,
        "reply_to_post_number": 22,
        "quote_count": 0,
        "incoming_link_count": 4,
        "reads": 34,
        "readers_count": 33,
        "score": 26.8,
        "yours": false,
        "topic_id": 668,
        "topic_slug": "%D1%87%D0%B0%D1%81%D1%82%D0%B8%D1%87%D0%BD%D0%BE-%D0%B7%D0%B0%D0%B1%D0%BB%D0%BE%D0%BA%D0%B8%D1%80%D0%BE%D0%B2%D0%B0%D0%BD%D0%BD%D1%8B%D0%B5-%D1%80%D0%B5%D1%81%D1%83%D1%80%D1%81%D1%8B",
        "display_username": null,
        "primary_group_name": null,
        "flair_name": null,
        "flair_url": null,
        "flair_bg_color": null,
        "flair_color": null,
        "flair_group_id": null,
        "badges_granted": [],
        "version": 1,
        "can_edit": false,
        "can_delete": false,
        "can_recover": false,
        "can_see_hidden_post": false,
        "can_wiki": false,
        "read": true,
        "user_title": "AntiZapret staff",
        "title_is_group": false,
        "reply_to_user": {
            "username": "xmn",
            "name": "",
            "avatar_template": "/letter_avatar_proxy/v4/letter/x/e19b73/{size}.png"
        },
        "bookmarked": false,
        "actions_summary": [],
        "moderator": true,
        "admin": true,
        "staff": true,
        "user_id": 1,
        "hidden": false,
        "trust_level": 2,
        "deleted_at": null,
        "user_deleted": false,
        "edit_reason": null,
        "can_view_edit_history": false,
        "wiki": false,
        "post_url": "/t/%D1%87%D0%B0%D1%81%D1%82%D0%B8%D1%87%D0%BD%D0%BE-%D0%B7%D0%B0%D0%B1%D0%BB%D0%BE%D0%BA%D0%B8%D1%80%D0%BE%D0%B2%D0%B0%D0%BD%D0%BD%D1%8B%D0%B5-%D1%80%D0%B5%D1%81%D1%83%D1%80%D1%81%D1%8B/668/23",
        "can_translate": false
    },
    {
        "id": 12782,
        "name": "",
        "username": "JIPCOROD",
        "avatar_template": "/user_avatar/ntc.party/jipcorod/{size}/6810_2.png",
        "created_at": "2023-03-27T21:57:23.295Z",
        "cooked": "<p>Здравствуйте, nicovideo.jp не работает в firefox <strong>без</strong> внесения в список исключений субдомена nvapi.nicovideo.jp (он кстати не заблокирован)<br>\nЯ даже не часто туда захожу, просто стало интересно, наплодил уже 2 темы <a href=\"http://forum.mozilla-russia.org/viewtopic.php?pid=804308#p804308\" class=\"inline-onebox\" rel=\"noopener nofollow ugc\">nicovideo фейлиться на любом видео | Форум Mozilla Россия</a> и <a href=\"http://github.com/webcompat/web-bugs/issues/120006\" class=\"inline-onebox\" rel=\"noopener nofollow ugc\">www.nicovideo.jp - video or audio doesn't play · Issue #120006 · webcompat/web-bugs · GitHub</a><br>\nПосоветовали открыть сети и там увидел проблему с подключением к nvapi.nicovideo.jp ну и да, эта проблема и препятствует воспроизведению на 3 компьютерах, позже ещё на 4 машине попробовал на максимально чистейшем фаерфокс через сторонний ВПН отдельной программой и все ровно получил ошибку. В хроме всё окей с самого начала.</p>\n<p>Добавьте пожалуйста субдомен nvapi в исключения</p>",
        "post_number": 24,
        "post_type": 1,
        "posts_count": 25,
        "updated_at": "2023-03-27T21:57:23.295Z",
        "reply_count": 0,
        "reply_to_post_number": null,
        "quote_count": 0,
        "incoming_link_count": 2,
        "reads": 27,
        "readers_count": 26,
        "score": 15.4,
        "yours": false,
        "topic_id": 668,
        "topic_slug": "%D1%87%D0%B0%D1%81%D1%82%D0%B8%D1%87%D0%BD%D0%BE-%D0%B7%D0%B0%D0%B1%D0%BB%D0%BE%D0%BA%D0%B8%D1%80%D0%BE%D0%B2%D0%B0%D0%BD%D0%BD%D1%8B%D0%B5-%D1%80%D0%B5%D1%81%D1%83%D1%80%D1%81%D1%8B",
        "display_username": "",
        "primary_group_name": null,
        "flair_name": null,
        "flair_url": null,
        "flair_bg_color": null,
        "flair_color": null,
        "flair_group_id": null,
        "badges_granted": [],
        "version": 1,
        "can_edit": false,
        "can_delete": false,
        "can_recover": false,
        "can_see_hidden_post": false,
        "can_wiki": false,
        "link_counts": [
            {
                "url": "http://forum.mozilla-russia.org/viewtopic.php?pid=804308#p804308",
                "internal": false,
                "reflection": false,
                "title": "nicovideo фейлиться на любом видео | Форум Mozilla Россия",
                "clicks": 1
            },
            {
                "url": "http://github.com/webcompat/web-bugs/issues/120006",
                "internal": false,
                "reflection": false,
                "title": "www.nicovideo.jp - video or audio doesn't play · Issue #120006 · webcompat/web-bugs · GitHub",
                "clicks": 0
            }
        ],
        "read": true,
        "user_title": "",
        "bookmarked": false,
        "actions_summary": [],
        "moderator": false,
        "admin": false,
        "staff": false,
        "user_id": 287,
        "hidden": false,
        "trust_level": 2,
        "deleted_at": null,
        "user_deleted": false,
        "edit_reason": null,
        "can_view_edit_history": false,
        "wiki": false,
        "post_url": "/t/%D1%87%D0%B0%D1%81%D1%82%D0%B8%D1%87%D0%BD%D0%BE-%D0%B7%D0%B0%D0%B1%D0%BB%D0%BE%D0%BA%D0%B8%D1%80%D0%BE%D0%B2%D0%B0%D0%BD%D0%BD%D1%8B%D0%B5-%D1%80%D0%B5%D1%81%D1%83%D1%80%D1%81%D1%8B/668/24",
        "can_translate": false
    },
    {
        "id": 12783,
        "name": "",
        "username": "JIPCOROD",
        "avatar_template": "/user_avatar/ntc.party/jipcorod/{size}/6810_2.png",
        "created_at": "2023-03-28T05:39:10.849Z",
        "cooked": "<p><a href=\"https://chan.kemono.party\" rel=\"noopener nofollow ugc\">chan.kemono.party</a> не заблокирован, но вот зато ip прокси на нём заблокирован для создания новых постов</p>",
        "post_number": 25,
        "post_type": 1,
        "posts_count": 25,
        "updated_at": "2023-03-28T05:39:47.907Z",
        "reply_count": 0,
        "reply_to_post_number": null,
        "quote_count": 0,
        "incoming_link_count": 1,
        "reads": 25,
        "readers_count": 24,
        "score": 10.0,
        "yours": false,
        "topic_id": 668,
        "topic_slug": "%D1%87%D0%B0%D1%81%D1%82%D0%B8%D1%87%D0%BD%D0%BE-%D0%B7%D0%B0%D0%B1%D0%BB%D0%BE%D0%BA%D0%B8%D1%80%D0%BE%D0%B2%D0%B0%D0%BD%D0%BD%D1%8B%D0%B5-%D1%80%D0%B5%D1%81%D1%83%D1%80%D1%81%D1%8B",
        "display_username": "",
        "primary_group_name": null,
        "flair_name": null,
        "flair_url": null,
        "flair_bg_color": null,
        "flair_color": null,
        "flair_group_id": null,
        "badges_granted": [],
        "version": 1,
        "can_edit": false,
        "can_delete": false,
        "can_recover": false,
        "can_see_hidden_post": false,
        "can_wiki": false,
        "link_counts": [
            {
                "url": "https://chan.kemono.party",
                "internal": false,
                "reflection": false,
                "title": "/kemono/ - kemono.party",
                "clicks": 13
            }
        ],
        "read": true,
        "user_title": "",
        "bookmarked": false,
        "actions_summary": [],
        "moderator": false,
        "admin": false,
        "staff": false,
        "user_id": 287,
        "hidden": false,
        "trust_level": 2,
        "deleted_at": null,
        "user_deleted": false,
        "edit_reason": null,
        "can_view_edit_history": false,
        "wiki": false,
        "post_url": "/t/%D1%87%D0%B0%D1%81%D1%82%D0%B8%D1%87%D0%BD%D0%BE-%D0%B7%D0%B0%D0%B1%D0%BB%D0%BE%D0%BA%D0%B8%D1%80%D0%BE%D0%B2%D0%B0%D0%BD%D0%BD%D1%8B%D0%B5-%D1%80%D0%B5%D1%81%D1%83%D1%80%D1%81%D1%8B/668/25",
        "can_translate": false
    }
]