[
    {
        "id": 17680,
        "name": "Егор Кузеванов",
        "username": "EgorKuzevanov",
        "avatar_template": "/letter_avatar_proxy/v4/letter/e/db5fbb/{size}.png",
        "created_at": "2023-09-15T07:35:44.642Z",
        "cooked": "<p>Неужели никто до сих пор не знает, как обновиться с Windows XP SP3 до Windows 7 SP1 напрямую с сохранением всего? Официальный форум Антизапрета <a href=\"https://ntc.party\">https://ntc.party</a> не работает в совместимом с Windows XP китайском хромоподобном браузере 360 Extreme Explorer v13.0.2310.0 на основе Chromium 86 (репаке от Elchupacabra):<br>\n<a href=\"http://web.archive.org/web/20230519101848if_/http://mirrors.pdp-11.ru/_x86/_XP/360_extreme_explorer_13.0.2310.0.zip\" rel=\"noopener nofollow ugc\">http://web.archive.org/web/20230519101848if_/http://mirrors.pdp-11.ru/_x86/_XP/360_extreme_explorer_13.0.2310.0.zip</a><br>\nи ругается на то, что мой браузер якобы устарел. Не помогла даже смена юзер-агента с помощью этого расширения: <a href=\"https://chrome.google.com/webstore/detail/user-agent-switcher-and-m/bhchdcejhohfmigjafbampogmaanbfkg\" class=\"inline-onebox\" rel=\"noopener nofollow ugc\">User-Agent Switcher and Manager - Chrome Web Store</a></p>",
        "post_number": 1,
        "post_type": 1,
        "posts_count": 21,
        "updated_at": "2023-09-15T07:36:06.424Z",
        "reply_count": 0,
        "reply_to_post_number": null,
        "quote_count": 0,
        "incoming_link_count": 184,
        "reads": 76,
        "readers_count": 75,
        "score": 935.2,
        "yours": false,
        "topic_id": 5685,
        "topic_slug": "ntcparty-%D0%BD%D0%B5-%D1%80%D0%B0%D0%B1%D0%BE%D1%82%D0%B0%D0%B5%D1%82-%D0%B2-%D0%BA%D0%B8%D1%82%D0%B0%D0%B9%D1%81%D0%BA%D0%BE%D0%BC-%D1%85%D1%80%D0%BE%D0%BC%D0%BE%D0%BF%D0%BE%D0%B4%D0%BE%D0%B1%D0%BD%D0%BE%D0%BC-%D0%B1%D1%80%D0%B0%D1%83%D0%B7%D0%B5%D1%80%D0%B5-360-extreme-explorer-v13023100-%D0%BD%D0%B0-%D0%BE%D1%81%D0%BD%D0%BE%D0%B2%D0%B5-chromium-86-%D0%BF%D0%BE%D0%B4-windows-xp-sp3",
        "display_username": "Егор Кузеванов",
        "primary_group_name": null,
        "flair_name": null,
        "flair_url": null,
        "flair_bg_color": null,
        "flair_color": null,
        "flair_group_id": null,
        "badges_granted": [],
        "version": 1,
        "can_edit": false,
        "can_delete": false,
        "can_recover": false,
        "can_see_hidden_post": false,
        "can_wiki": false,
        "link_counts": [
            {
                "url": "https://ntc.party",
                "internal": true,
                "reflection": false,
                "clicks": 5
            },
            {
                "url": "http://web.archive.org/web/20230519101848if_/http://mirrors.pdp-11.ru/_x86/_XP/360_extreme_explorer_13.0.2310.0.zip",
                "internal": false,
                "reflection": false,
                "clicks": 4
            },
            {
                "url": "https://chrome.google.com/webstore/detail/user-agent-switcher-and-m/bhchdcejhohfmigjafbampogmaanbfkg",
                "internal": false,
                "reflection": false,
                "title": "User-Agent Switcher and Manager - Chrome Web Store",
                "clicks": 0
            }
        ],
        "read": true,
        "user_title": null,
        "bookmarked": false,
        "actions_summary": [],
        "moderator": false,
        "admin": false,
        "staff": false,
        "user_id": 1804,
        "hidden": false,
        "trust_level": 2,
        "deleted_at": null,
        "user_deleted": false,
        "edit_reason": null,
        "can_view_edit_history": false,
        "wiki": false,
        "user_suspended": true,
        "post_url": "/t/ntcparty-%D0%BD%D0%B5-%D1%80%D0%B0%D0%B1%D0%BE%D1%82%D0%B0%D0%B5%D1%82-%D0%B2-%D0%BA%D0%B8%D1%82%D0%B0%D0%B9%D1%81%D0%BA%D0%BE%D0%BC-%D1%85%D1%80%D0%BE%D0%BC%D0%BE%D0%BF%D0%BE%D0%B4%D0%BE%D0%B1%D0%BD%D0%BE%D0%BC-%D0%B1%D1%80%D0%B0%D1%83%D0%B7%D0%B5%D1%80%D0%B5-360-extreme-explorer-v13023100-%D0%BD%D0%B0-%D0%BE%D1%81%D0%BD%D0%BE%D0%B2%D0%B5-chromium-86-%D0%BF%D0%BE%D0%B4-windows-xp-sp3/5685/1",
        "can_translate": false
    },
    {
        "id": 17689,
        "name": null,
        "username": "anon94384997",
        "avatar_template": "/letter_avatar_proxy/v4/letter/a/49beb7/{size}.png",
        "created_at": "2023-09-15T11:23:37.440Z",
        "cooked": "<p>Если хотите продолжать пользоваться 360 Extreme Explorer 13 самое реалистичное писать сюда <a href=\"https://meta.discourse.org/c/bug/1\" rel=\"noopener nofollow ugc\">https://meta.discourse.org/c/bug/1</a> (на английском через Google или DeepL переводчик). Просить, чтобы в упрощенной версии была возможность логина (без костыльного переноса кук) и возможность оставлять простые текстовые сообщения. Расскажите о вашей ситуации, что любите XP. А можете просто сказать, что параноик (или на слабом железе, учитывая жирноту движка даже в упрощенной версии) и отключаете JS в Tor браузере.</p>\n<p>На Win7 как я говорил нет смысла обновляться. Браузеры ее тоже забрасывают. Только новая установка Win10+ или линукс. Смена user agent не поможет, проверяют фичи браузера.</p>\n<p>Можете еще попросить разработчиков Pale Moon <a href=\"https://forum.palemoon.org/\" rel=\"noopener nofollow ugc\">https://forum.palemoon.org/</a> наладить работу полноценной версии. На базе Pale Moon делается Serpent и New Moon. Только не упоминайте XP, они ее не любят.</p>",
        "post_number": 2,
        "post_type": 1,
        "posts_count": 21,
        "updated_at": "2023-09-15T11:41:42.177Z",
        "reply_count": 1,
        "reply_to_post_number": null,
        "quote_count": 0,
        "incoming_link_count": 5,
        "reads": 78,
        "readers_count": 77,
        "score": 45.6,
        "yours": false,
        "topic_id": 5685,
        "topic_slug": "ntcparty-%D0%BD%D0%B5-%D1%80%D0%B0%D0%B1%D0%BE%D1%82%D0%B0%D0%B5%D1%82-%D0%B2-%D0%BA%D0%B8%D1%82%D0%B0%D0%B9%D1%81%D0%BA%D0%BE%D0%BC-%D1%85%D1%80%D0%BE%D0%BC%D0%BE%D0%BF%D0%BE%D0%B4%D0%BE%D0%B1%D0%BD%D0%BE%D0%BC-%D0%B1%D1%80%D0%B0%D1%83%D0%B7%D0%B5%D1%80%D0%B5-360-extreme-explorer-v13023100-%D0%BD%D0%B0-%D0%BE%D1%81%D0%BD%D0%BE%D0%B2%D0%B5-chromium-86-%D0%BF%D0%BE%D0%B4-windows-xp-sp3",
        "display_username": null,
        "primary_group_name": null,
        "flair_name": null,
        "flair_url": null,
        "flair_bg_color": null,
        "flair_color": null,
        "flair_group_id": null,
        "badges_granted": [],
        "version": 2,
        "can_edit": false,
        "can_delete": false,
        "can_recover": false,
        "can_see_hidden_post": false,
        "can_wiki": false,
        "link_counts": [
            {
                "url": "https://meta.discourse.org/c/bug/1",
                "internal": false,
                "reflection": false,
                "title": "bug - Discourse Meta",
                "clicks": 5
            },
            {
                "url": "https://forum.palemoon.org/",
                "internal": false,
                "reflection": false,
                "title": "Pale Moon forum - Forum index",
                "clicks": 3
            }
        ],
        "read": true,
        "user_title": null,
        "bookmarked": false,
        "actions_summary": [],
        "moderator": false,
        "admin": false,
        "staff": false,
        "user_id": 1199,
        "hidden": false,
        "trust_level": 2,
        "deleted_at": null,
        "user_deleted": false,
        "edit_reason": null,
        "can_view_edit_history": false,
        "wiki": false,
        "post_url": "/t/ntcparty-%D0%BD%D0%B5-%D1%80%D0%B0%D0%B1%D0%BE%D1%82%D0%B0%D0%B5%D1%82-%D0%B2-%D0%BA%D0%B8%D1%82%D0%B0%D0%B9%D1%81%D0%BA%D0%BE%D0%BC-%D1%85%D1%80%D0%BE%D0%BC%D0%BE%D0%BF%D0%BE%D0%B4%D0%BE%D0%B1%D0%BD%D0%BE%D0%BC-%D0%B1%D1%80%D0%B0%D1%83%D0%B7%D0%B5%D1%80%D0%B5-360-extreme-explorer-v13023100-%D0%BD%D0%B0-%D0%BE%D1%81%D0%BD%D0%BE%D0%B2%D0%B5-chromium-86-%D0%BF%D0%BE%D0%B4-windows-xp-sp3/5685/2",
        "can_translate": false
    },
    {
        "id": 17693,
        "name": "Егор Кузеванов",
        "username": "EgorKuzevanov",
        "avatar_template": "/letter_avatar_proxy/v4/letter/e/db5fbb/{size}.png",
        "created_at": "2023-09-15T13:16:38.289Z",
        "cooked": "<p>По поводу Windows 10: я не собираюсь обновляться до Windows 10 21H2 ради доступа в будущем к форумам на базе Discourse (в том числе к официальному форуму Антизапрета <a href=\"https://ntc.party\">https://ntc.party</a>). Windows 10 21H2 имеет два неприятных недостатка по сравнению с Windows 7 и Windows 8.1:</p>\n<ul>\n<li>во-первых, Windows 10 21H2 тормозит, нагружает процессор до 100% и слишком медленно откликается на мои действия (в том числе на запуск программ, игр и браузеров и на открытие файлов, папок и окон) на моем бюджетном ноутбуке Asus X540SA (2016 года выпуска) со слабым процессором Intel Celeron N3050 на ядре Braswell (1,6 ГГц) и 4 ГБ оперативной памяти;</li>\n<li>а во-вторых, в Windows 10 21H2 присутствует до сих пор не исправленный Майкрософтом баг, когда при каждом запуске компьютера, при каждой перезагрузке компьютера и при каждом перезаходе в систему принудительно сбрасываются настройки программ по умолчанию (браузер Mozilla Firefox на Microsoft Edge, просмотрщик изображений IrfanView на “Фотографии”, видеоплеер VLC Media Player на “Кино и ТВ” и аудиоплеер AIMP на “Музыка Groove”), сопровождая это сообщениями в трее “Стандартное приложение сброшено” и “Стандартный браузер сброшен”. К тому же, никто из энтузиастов с GitHub или с англоязычного компьютерного форума MSFN до сих пор не создал утилиту, которая раз и навсегда исправила бы в Windows 10 21H2 постоянные сбросы настроек программ по умолчанию.</li>\n</ul>",
        "post_number": 3,
        "post_type": 1,
        "posts_count": 21,
        "updated_at": "2023-09-15T13:24:03.702Z",
        "reply_count": 1,
        "reply_to_post_number": 2,
        "quote_count": 0,
        "incoming_link_count": 0,
        "reads": 71,
        "readers_count": 70,
        "score": 19.2,
        "yours": false,
        "topic_id": 5685,
        "topic_slug": "ntcparty-%D0%BD%D0%B5-%D1%80%D0%B0%D0%B1%D0%BE%D1%82%D0%B0%D0%B5%D1%82-%D0%B2-%D0%BA%D0%B8%D1%82%D0%B0%D0%B9%D1%81%D0%BA%D0%BE%D0%BC-%D1%85%D1%80%D0%BE%D0%BC%D0%BE%D0%BF%D0%BE%D0%B4%D0%BE%D0%B1%D0%BD%D0%BE%D0%BC-%D0%B1%D1%80%D0%B0%D1%83%D0%B7%D0%B5%D1%80%D0%B5-360-extreme-explorer-v13023100-%D0%BD%D0%B0-%D0%BE%D1%81%D0%BD%D0%BE%D0%B2%D0%B5-chromium-86-%D0%BF%D0%BE%D0%B4-windows-xp-sp3",
        "display_username": "Егор Кузеванов",
        "primary_group_name": null,
        "flair_name": null,
        "flair_url": null,
        "flair_bg_color": null,
        "flair_color": null,
        "flair_group_id": null,
        "badges_granted": [],
        "version": 2,
        "can_edit": false,
        "can_delete": false,
        "can_recover": false,
        "can_see_hidden_post": false,
        "can_wiki": false,
        "link_counts": [
            {
                "url": "https://ntc.party",
                "internal": true,
                "reflection": false,
                "clicks": 0
            }
        ],
        "read": true,
        "user_title": null,
        "reply_to_user": {
            "username": "anon94384997",
            "name": null,
            "avatar_template": "/letter_avatar_proxy/v4/letter/a/49beb7/{size}.png"
        },
        "bookmarked": false,
        "actions_summary": [],
        "moderator": false,
        "admin": false,
        "staff": false,
        "user_id": 1804,
        "hidden": false,
        "trust_level": 2,
        "deleted_at": null,
        "user_deleted": false,
        "edit_reason": null,
        "can_view_edit_history": false,
        "wiki": false,
        "user_suspended": true,
        "post_url": "/t/ntcparty-%D0%BD%D0%B5-%D1%80%D0%B0%D0%B1%D0%BE%D1%82%D0%B0%D0%B5%D1%82-%D0%B2-%D0%BA%D0%B8%D1%82%D0%B0%D0%B9%D1%81%D0%BA%D0%BE%D0%BC-%D1%85%D1%80%D0%BE%D0%BC%D0%BE%D0%BF%D0%BE%D0%B4%D0%BE%D0%B1%D0%BD%D0%BE%D0%BC-%D0%B1%D1%80%D0%B0%D1%83%D0%B7%D0%B5%D1%80%D0%B5-360-extreme-explorer-v13023100-%D0%BD%D0%B0-%D0%BE%D1%81%D0%BD%D0%BE%D0%B2%D0%B5-chromium-86-%D0%BF%D0%BE%D0%B4-windows-xp-sp3/5685/3",
        "can_translate": false
    },
    {
        "id": 17695,
        "name": null,
        "username": "anon94384997",
        "avatar_template": "/letter_avatar_proxy/v4/letter/a/49beb7/{size}.png",
        "created_at": "2023-09-15T13:33:32.373Z",
        "cooked": "<p>На сайте microsoft говорят, что обновление с XP на 7 не поддерживается.<br>\n<a href=\"https://answers.microsoft.com/ru-ru/windows/forum/all/%D0%BE%D0%B1%D0%BD%D0%BE%D0%B2%D0%BB%D0%B5%D0%BD/949d4727-201e-4af8-a63c-ac295eaa3124\" rel=\"noopener nofollow ugc\">Обновление Windows XP до Windows 7 - Сообщество Microsoft</a><br>\nМожно установить Win7 с сохранением данных (они будут в папке Windows.old), но не программ.<br>\nВидео урок <a href=\"https://www.youtube.com/watch?v=45CZvrelK_Q\" rel=\"noopener nofollow ugc\">https://www.youtube.com/watch?v=45CZvrelK_Q</a><br>\nТекстовая статья <a href=\"https://softcomputers.org/blog/kak-obnovit-windows-xp-do-windows-7/\" rel=\"noopener nofollow ugc\">https://softcomputers.org/blog/kak-obnovit-windows-xp-do-windows-7/</a><br>\nВидите, люди выбирают полную установку (которая сохранит данные, но не программы). Скорее всего если вы выберете опцию “обновление” то будет ошибка.<br>\nВроде есть платные инструменты с такой функциональностью. Но мне кажется обновление с сохранением программ и драйверов создаст глюки. Проще установить начисто.</p>\n<p>Если у вас много portable софта, то его можно просто скопировать из Windows.old. Правда, я не уверен что будет с файлами не из стандартных директорий, например в корне диска. Скорее всего сохранятся.</p>\n<p>Если Win10 тормозит и глючит, лучше купить новое железо. Новые версии виндовс вообще стали довольно гадкими и неконтроллируемыми. Ведь еще надо решить вопрос с лицензией.<br>\nЕсли у вас есть немного знаний и нет больших требований к софту и играм, на старое железо можно установить какой-нибудь линукс.</p>",
        "post_number": 4,
        "post_type": 1,
        "posts_count": 21,
        "updated_at": "2023-09-15T13:38:51.542Z",
        "reply_count": 2,
        "reply_to_post_number": 3,
        "quote_count": 0,
        "incoming_link_count": 0,
        "reads": 66,
        "readers_count": 65,
        "score": 23.2,
        "yours": false,
        "topic_id": 5685,
        "topic_slug": "ntcparty-%D0%BD%D0%B5-%D1%80%D0%B0%D0%B1%D0%BE%D1%82%D0%B0%D0%B5%D1%82-%D0%B2-%D0%BA%D0%B8%D1%82%D0%B0%D0%B9%D1%81%D0%BA%D0%BE%D0%BC-%D1%85%D1%80%D0%BE%D0%BC%D0%BE%D0%BF%D0%BE%D0%B4%D0%BE%D0%B1%D0%BD%D0%BE%D0%BC-%D0%B1%D1%80%D0%B0%D1%83%D0%B7%D0%B5%D1%80%D0%B5-360-extreme-explorer-v13023100-%D0%BD%D0%B0-%D0%BE%D1%81%D0%BD%D0%BE%D0%B2%D0%B5-chromium-86-%D0%BF%D0%BE%D0%B4-windows-xp-sp3",
        "display_username": null,
        "primary_group_name": null,
        "flair_name": null,
        "flair_url": null,
        "flair_bg_color": null,
        "flair_color": null,
        "flair_group_id": null,
        "badges_granted": [],
        "version": 2,
        "can_edit": false,
        "can_delete": false,
        "can_recover": false,
        "can_see_hidden_post": false,
        "can_wiki": false,
        "link_counts": [
            {
                "url": "https://answers.microsoft.com/ru-ru/windows/forum/all/%D0%BE%D0%B1%D0%BD%D0%BE%D0%B2%D0%BB%D0%B5%D0%BD/949d4727-201e-4af8-a63c-ac295eaa3124",
                "internal": false,
                "reflection": false,
                "title": "Redirecting",
                "clicks": 0
            },
            {
                "url": "https://www.youtube.com/watch?v=45CZvrelK_Q",
                "internal": false,
                "reflection": false,
                "clicks": 0
            },
            {
                "url": "https://softcomputers.org/blog/kak-obnovit-windows-xp-do-windows-7/",
                "internal": false,
                "reflection": false,
                "title": "Как обновить Windows XP до Windows 7",
                "clicks": 0
            }
        ],
        "read": true,
        "user_title": null,
        "reply_to_user": {
            "username": "EgorKuzevanov",
            "name": "Егор Кузеванов",
            "avatar_template": "/letter_avatar_proxy/v4/letter/e/db5fbb/{size}.png"
        },
        "bookmarked": false,
        "actions_summary": [],
        "moderator": false,
        "admin": false,
        "staff": false,
        "user_id": 1199,
        "hidden": false,
        "trust_level": 2,
        "deleted_at": null,
        "user_deleted": false,
        "edit_reason": null,
        "can_view_edit_history": false,
        "wiki": false,
        "post_url": "/t/ntcparty-%D0%BD%D0%B5-%D1%80%D0%B0%D0%B1%D0%BE%D1%82%D0%B0%D0%B5%D1%82-%D0%B2-%D0%BA%D0%B8%D1%82%D0%B0%D0%B9%D1%81%D0%BA%D0%BE%D0%BC-%D1%85%D1%80%D0%BE%D0%BC%D0%BE%D0%BF%D0%BE%D0%B4%D0%BE%D0%B1%D0%BD%D0%BE%D0%BC-%D0%B1%D1%80%D0%B0%D1%83%D0%B7%D0%B5%D1%80%D0%B5-360-extreme-explorer-v13023100-%D0%BD%D0%B0-%D0%BE%D1%81%D0%BD%D0%BE%D0%B2%D0%B5-chromium-86-%D0%BF%D0%BE%D0%B4-windows-xp-sp3/5685/4",
        "can_translate": false
    },
    {
        "id": 17696,
        "name": "Егор Кузеванов",
        "username": "EgorKuzevanov",
        "avatar_template": "/letter_avatar_proxy/v4/letter/e/db5fbb/{size}.png",
        "created_at": "2023-09-15T13:43:41.391Z",
        "cooked": "<p>У меня нет денег на более мощный ноутбук с процессором Intel Core i3/i5/i7, способный потянуть актуальные выпуски Windows 10 (21H2, 22H2 и LTSC 2021). На Авито ноутбуки с процессорами Intel шестого (Skylake) и седьмого поколений (Kaby Lake) стоят очень дорого, а моя мама не разрешает мне тратить много денег со своих банковских карт от Сбербанка, Тинькофф Банка и МТС Банка.</p>\n<p>Мне нужен способ, как в 2024-2025 годах продолжить пользоваться официальным форумом Антизапрета <a href=\"https://ntc.party\">https://ntc.party</a> на базе новых версий Discourse, не переходя с Windows 7 и Windows 8.1 на ухудшенные Майкрософтом и тормозящие на бюджетных процессорах Intel Celeron актуальные выпуски Windows 10 (21H2, 22H2 и LTSC 2021).</p>",
        "post_number": 5,
        "post_type": 1,
        "posts_count": 21,
        "updated_at": "2023-09-15T13:54:13.746Z",
        "reply_count": 0,
        "reply_to_post_number": 4,
        "quote_count": 0,
        "incoming_link_count": 0,
        "reads": 62,
        "readers_count": 61,
        "score": 12.4,
        "yours": false,
        "topic_id": 5685,
        "topic_slug": "ntcparty-%D0%BD%D0%B5-%D1%80%D0%B0%D0%B1%D0%BE%D1%82%D0%B0%D0%B5%D1%82-%D0%B2-%D0%BA%D0%B8%D1%82%D0%B0%D0%B9%D1%81%D0%BA%D0%BE%D0%BC-%D1%85%D1%80%D0%BE%D0%BC%D0%BE%D0%BF%D0%BE%D0%B4%D0%BE%D0%B1%D0%BD%D0%BE%D0%BC-%D0%B1%D1%80%D0%B0%D1%83%D0%B7%D0%B5%D1%80%D0%B5-360-extreme-explorer-v13023100-%D0%BD%D0%B0-%D0%BE%D1%81%D0%BD%D0%BE%D0%B2%D0%B5-chromium-86-%D0%BF%D0%BE%D0%B4-windows-xp-sp3",
        "display_username": "Егор Кузеванов",
        "primary_group_name": null,
        "flair_name": null,
        "flair_url": null,
        "flair_bg_color": null,
        "flair_color": null,
        "flair_group_id": null,
        "badges_granted": [],
        "version": 3,
        "can_edit": false,
        "can_delete": false,
        "can_recover": false,
        "can_see_hidden_post": false,
        "can_wiki": false,
        "link_counts": [
            {
                "url": "https://ntc.party",
                "internal": true,
                "reflection": false,
                "clicks": 0
            }
        ],
        "read": true,
        "user_title": null,
        "reply_to_user": {
            "username": "anon94384997",
            "name": null,
            "avatar_template": "/letter_avatar_proxy/v4/letter/a/49beb7/{size}.png"
        },
        "bookmarked": false,
        "actions_summary": [],
        "moderator": false,
        "admin": false,
        "staff": false,
        "user_id": 1804,
        "hidden": false,
        "trust_level": 2,
        "deleted_at": null,
        "user_deleted": false,
        "edit_reason": null,
        "can_view_edit_history": false,
        "wiki": false,
        "user_suspended": true,
        "post_url": "/t/ntcparty-%D0%BD%D0%B5-%D1%80%D0%B0%D0%B1%D0%BE%D1%82%D0%B0%D0%B5%D1%82-%D0%B2-%D0%BA%D0%B8%D1%82%D0%B0%D0%B9%D1%81%D0%BA%D0%BE%D0%BC-%D1%85%D1%80%D0%BE%D0%BC%D0%BE%D0%BF%D0%BE%D0%B4%D0%BE%D0%B1%D0%BD%D0%BE%D0%BC-%D0%B1%D1%80%D0%B0%D1%83%D0%B7%D0%B5%D1%80%D0%B5-360-extreme-explorer-v13023100-%D0%BD%D0%B0-%D0%BE%D1%81%D0%BD%D0%BE%D0%B2%D0%B5-chromium-86-%D0%BF%D0%BE%D0%B4-windows-xp-sp3/5685/5",
        "can_translate": false
    },
    {
        "id": 17698,
        "name": "Егор Кузеванов",
        "username": "EgorKuzevanov",
        "avatar_template": "/letter_avatar_proxy/v4/letter/e/db5fbb/{size}.png",
        "created_at": "2023-09-15T14:01:08.181Z",
        "cooked": "<p>Два моих вечных вопроса:</p>\n<ol>\n<li>Что делать, если официальный форум Антизапрета <a href=\"https://ntc.party\">https://ntc.party</a> не работает в финальных для Windows 7 и Windows 8.1 браузерах Google Chrome 109 и Mozilla Firefox 115 ESR и ругается на устаревший браузер, а Windows 10 21H2 тормозит на моем бюджетном ноутбуке с процессором Intel Celeron?</li>\n<li>Что делать, если мне очень нужен нормальный ноутбук, на котором не будет тормозить Windows 10 21H2, а денег нет?</li>\n</ol>",
        "post_number": 6,
        "post_type": 1,
        "posts_count": 21,
        "updated_at": "2023-09-15T14:18:25.268Z",
        "reply_count": 1,
        "reply_to_post_number": 4,
        "quote_count": 0,
        "incoming_link_count": 0,
        "reads": 55,
        "readers_count": 54,
        "score": 16.0,
        "yours": false,
        "topic_id": 5685,
        "topic_slug": "ntcparty-%D0%BD%D0%B5-%D1%80%D0%B0%D0%B1%D0%BE%D1%82%D0%B0%D0%B5%D1%82-%D0%B2-%D0%BA%D0%B8%D1%82%D0%B0%D0%B9%D1%81%D0%BA%D0%BE%D0%BC-%D1%85%D1%80%D0%BE%D0%BC%D0%BE%D0%BF%D0%BE%D0%B4%D0%BE%D0%B1%D0%BD%D0%BE%D0%BC-%D0%B1%D1%80%D0%B0%D1%83%D0%B7%D0%B5%D1%80%D0%B5-360-extreme-explorer-v13023100-%D0%BD%D0%B0-%D0%BE%D1%81%D0%BD%D0%BE%D0%B2%D0%B5-chromium-86-%D0%BF%D0%BE%D0%B4-windows-xp-sp3",
        "display_username": "Егор Кузеванов",
        "primary_group_name": null,
        "flair_name": null,
        "flair_url": null,
        "flair_bg_color": null,
        "flair_color": null,
        "flair_group_id": null,
        "badges_granted": [],
        "version": 2,
        "can_edit": false,
        "can_delete": false,
        "can_recover": false,
        "can_see_hidden_post": false,
        "can_wiki": false,
        "link_counts": [
            {
                "url": "https://ntc.party",
                "internal": true,
                "reflection": false,
                "clicks": 0
            }
        ],
        "read": true,
        "user_title": null,
        "reply_to_user": {
            "username": "anon94384997",
            "name": null,
            "avatar_template": "/letter_avatar_proxy/v4/letter/a/49beb7/{size}.png"
        },
        "bookmarked": false,
        "actions_summary": [],
        "moderator": false,
        "admin": false,
        "staff": false,
        "user_id": 1804,
        "hidden": false,
        "trust_level": 2,
        "deleted_at": null,
        "user_deleted": false,
        "edit_reason": null,
        "can_view_edit_history": false,
        "wiki": false,
        "user_suspended": true,
        "post_url": "/t/ntcparty-%D0%BD%D0%B5-%D1%80%D0%B0%D0%B1%D0%BE%D1%82%D0%B0%D0%B5%D1%82-%D0%B2-%D0%BA%D0%B8%D1%82%D0%B0%D0%B9%D1%81%D0%BA%D0%BE%D0%BC-%D1%85%D1%80%D0%BE%D0%BC%D0%BE%D0%BF%D0%BE%D0%B4%D0%BE%D0%B1%D0%BD%D0%BE%D0%BC-%D0%B1%D1%80%D0%B0%D1%83%D0%B7%D0%B5%D1%80%D0%B5-360-extreme-explorer-v13023100-%D0%BD%D0%B0-%D0%BE%D1%81%D0%BD%D0%BE%D0%B2%D0%B5-chromium-86-%D0%BF%D0%BE%D0%B4-windows-xp-sp3/5685/6",
        "can_translate": false
    },
    {
        "id": 17700,
        "name": "ilyaigpetrov",
        "username": "ilyaigpetrov",
        "avatar_template": "/letter_avatar_proxy/v4/letter/i/5fc32e/{size}.png",
        "created_at": "2023-09-15T14:42:59.490Z",
        "cooked": "<p>Попробуйте Линукс.<br>\nБывают разные дистрибутивы, я вам советую Linux Mint Xfce Edition: ссылку на последнюю версию ищите на <a href=\"https://www.linuxmint.com/download_all.php\" class=\"inline-onebox\">All Versions - Linux Mint</a>. Сейчас это 21.2 Victoria Xfce.</p>\n<ol>\n<li>Скачать .iso образ.</li>\n<li>Записать его на флешку с помощью <a href=\"https://rufus.ie/ru/\" class=\"inline-onebox\">Rufus - Простое создание загрузочных USB-дисков</a> или <a href=\"https://gitlab.com/bztsrc/usbimager\" class=\"inline-onebox\">bzt / usbimager · GitLab</a>.</li>\n<li>Загрузиться с флешки (приоритет устройств для загрузки настраивается в BIOS).</li>\n<li>Попробовать живую версию без установки на жёсткий диск. Можно сменить светлую тему на тёмную для оценки дизайна и ваших предпочтений. Запустить браузер (FireFox, Chromium) и протестировать скорость и удобство работы.</li>\n<li>Если всё устраивает, то установить на жёсткий диск. Легче всего отдать на растерзание инсталятору весь диск. <strong>ВАЖНО</strong>: все ваши файлы на выбранном диске будут удалены, так что перед установкой перенесите их на другие запоминающие устройства.</li>\n</ol>\n<p><strong>ОБН1</strong>: Вот заметка по оптимизации Линукса под слабые машины: <a href=\"https://notes.valdikss.org.ru/linux-for-old-pc-from-2007/\" class=\"inline-onebox\">Linux для старого компьютера — История оживления компьютера 2007 года</a>.</p>",
        "post_number": 7,
        "post_type": 1,
        "posts_count": 21,
        "updated_at": "2023-09-15T15:14:43.221Z",
        "reply_count": 1,
        "reply_to_post_number": 6,
        "quote_count": 0,
        "incoming_link_count": 1,
        "reads": 59,
        "readers_count": 58,
        "score": 21.8,
        "yours": false,
        "topic_id": 5685,
        "topic_slug": "ntcparty-%D0%BD%D0%B5-%D1%80%D0%B0%D0%B1%D0%BE%D1%82%D0%B0%D0%B5%D1%82-%D0%B2-%D0%BA%D0%B8%D1%82%D0%B0%D0%B9%D1%81%D0%BA%D0%BE%D0%BC-%D1%85%D1%80%D0%BE%D0%BC%D0%BE%D0%BF%D0%BE%D0%B4%D0%BE%D0%B1%D0%BD%D0%BE%D0%BC-%D0%B1%D1%80%D0%B0%D1%83%D0%B7%D0%B5%D1%80%D0%B5-360-extreme-explorer-v13023100-%D0%BD%D0%B0-%D0%BE%D1%81%D0%BD%D0%BE%D0%B2%D0%B5-chromium-86-%D0%BF%D0%BE%D0%B4-windows-xp-sp3",
        "display_username": "ilyaigpetrov",
        "primary_group_name": null,
        "flair_name": null,
        "flair_url": null,
        "flair_bg_color": null,
        "flair_color": null,
        "flair_group_id": null,
        "badges_granted": [],
        "version": 2,
        "can_edit": false,
        "can_delete": false,
        "can_recover": false,
        "can_see_hidden_post": false,
        "can_wiki": false,
        "link_counts": [
            {
                "url": "https://notes.valdikss.org.ru/linux-for-old-pc-from-2007/",
                "internal": false,
                "reflection": false,
                "title": "Linux для старого компьютера — История оживления компьютера 2007 года",
                "clicks": 4
            },
            {
                "url": "https://www.linuxmint.com/download_all.php",
                "internal": false,
                "reflection": false,
                "title": "All Versions - Linux Mint",
                "clicks": 1
            },
            {
                "url": "https://gitlab.com/bztsrc/usbimager",
                "internal": false,
                "reflection": false,
                "title": "bzt / usbimager · GitLab",
                "clicks": 0
            },
            {
                "url": "https://rufus.ie/ru/",
                "internal": false,
                "reflection": false,
                "title": "Rufus - Простое создание загрузочных USB-дисков",
                "clicks": 0
            },
            {
                "url": "https://ntc.party/t/%D1%81%D0%BE%D0%B2%D0%B5%D1%82%D1%83%D0%B5%D1%82%D0%B5-%D0%BB%D0%B8%D0%BD%D1%83%D0%BA%D1%81-%D1%80%D0%B0%D1%81%D1%81%D0%BA%D0%B0%D0%B6%D0%B8%D1%82%D0%B5-%D0%B8-%D0%BE-%D1%82%D0%BE%D0%BA%D1%81%D0%B8%D1%87%D0%BD%D0%BE%D0%BC-%D0%BB%D0%BE%D1%80%D0%B5-linuxorgru/5696",
                "internal": true,
                "reflection": true,
                "title": "Советуете линукс -- расскажите и о токсичном ЛОРе (linux.org.ru)",
                "clicks": 2
            },
            {
                "url": "https://ntc.party/t/%D1%80%D0%B0%D1%81%D1%88%D0%B8%D1%80%D0%B5%D0%BD%D0%B8%D0%B5-%D0%BE%D0%B1%D1%85%D0%BE%D0%B4-%D0%B1%D0%BB%D0%BE%D0%BA%D0%B8%D1%80%D0%BE%D0%B2%D0%BE%D0%BA-%D1%80%D1%83%D0%BD%D0%B5%D1%82%D0%B0-%D0%B1%D0%B5%D1%81%D0%BA%D0%BE%D0%BD%D0%B5%D1%87%D0%BD%D0%BE-%D0%BE%D1%82%D0%BA%D1%80%D1%8B%D0%B2%D0%B0%D0%B5%D1%82-%D0%BE%D1%84%D0%B8%D1%86%D0%B8%D0%B0%D0%BB%D1%8C%D0%BD%D0%BE%D0%B5-%D0%B7%D0%B5%D1%80%D0%BA%D0%B0%D0%BB%D0%BE-%D1%80%D1%83%D1%82%D1%80%D0%B5%D0%BA%D0%B5%D1%80%D0%B0-httpsrutrackernet/5892/12",
                "internal": true,
                "reflection": true,
                "title": "Расширение \"Обход блокировок Рунета\" бесконечно открывает официальное зеркало Рутрекера https://rutracker.net",
                "clicks": 0
            }
        ],
        "read": true,
        "user_title": "Russian Censorship Bypass Extension staff",
        "title_is_group": false,
        "reply_to_user": {
            "username": "EgorKuzevanov",
            "name": "Егор Кузеванов",
            "avatar_template": "/letter_avatar_proxy/v4/letter/e/db5fbb/{size}.png"
        },
        "bookmarked": false,
        "actions_summary": [],
        "moderator": true,
        "admin": false,
        "staff": true,
        "user_id": 6,
        "hidden": false,
        "trust_level": 2,
        "deleted_at": null,
        "user_deleted": false,
        "edit_reason": null,
        "can_view_edit_history": false,
        "wiki": false,
        "post_url": "/t/ntcparty-%D0%BD%D0%B5-%D1%80%D0%B0%D0%B1%D0%BE%D1%82%D0%B0%D0%B5%D1%82-%D0%B2-%D0%BA%D0%B8%D1%82%D0%B0%D0%B9%D1%81%D0%BA%D0%BE%D0%BC-%D1%85%D1%80%D0%BE%D0%BC%D0%BE%D0%BF%D0%BE%D0%B4%D0%BE%D0%B1%D0%BD%D0%BE%D0%BC-%D0%B1%D1%80%D0%B0%D1%83%D0%B7%D0%B5%D1%80%D0%B5-360-extreme-explorer-v13023100-%D0%BD%D0%B0-%D0%BE%D1%81%D0%BD%D0%BE%D0%B2%D0%B5-chromium-86-%D0%BF%D0%BE%D0%B4-windows-xp-sp3/5685/7",
        "can_translate": false
    },
    {
        "id": 17701,
        "name": "Егор Кузеванов",
        "username": "EgorKuzevanov",
        "avatar_template": "/letter_avatar_proxy/v4/letter/e/db5fbb/{size}.png",
        "created_at": "2023-09-15T14:57:18.759Z",
        "cooked": "<p>К сожалению, на Linux (включая дистрибутивы Debian, Ubuntu и Linux Mint), в отличие от Windows, не существует универсальной утилиты командной строки <a href=\"https://wincmd.ru/plugring/tcimg.html\" rel=\"noopener nofollow ugc\">TCIMG</a> (написанной на скриптовом языке AutoIt). А под Wine утилита TCIMG сильно глючит (ввиду того, что в большинстве команд и параметров TCIMG, написанных на AutoIt, в значительной степени задействованы недокументированные функции Win32 API, отсутствующие в линуксовом Wine).</p>",
        "post_number": 8,
        "post_type": 1,
        "posts_count": 21,
        "updated_at": "2023-09-15T15:02:23.232Z",
        "reply_count": 2,
        "reply_to_post_number": 7,
        "quote_count": 0,
        "incoming_link_count": 0,
        "reads": 52,
        "readers_count": 51,
        "score": 20.4,
        "yours": false,
        "topic_id": 5685,
        "topic_slug": "ntcparty-%D0%BD%D0%B5-%D1%80%D0%B0%D0%B1%D0%BE%D1%82%D0%B0%D0%B5%D1%82-%D0%B2-%D0%BA%D0%B8%D1%82%D0%B0%D0%B9%D1%81%D0%BA%D0%BE%D0%BC-%D1%85%D1%80%D0%BE%D0%BC%D0%BE%D0%BF%D0%BE%D0%B4%D0%BE%D0%B1%D0%BD%D0%BE%D0%BC-%D0%B1%D1%80%D0%B0%D1%83%D0%B7%D0%B5%D1%80%D0%B5-360-extreme-explorer-v13023100-%D0%BD%D0%B0-%D0%BE%D1%81%D0%BD%D0%BE%D0%B2%D0%B5-chromium-86-%D0%BF%D0%BE%D0%B4-windows-xp-sp3",
        "display_username": "Егор Кузеванов",
        "primary_group_name": null,
        "flair_name": null,
        "flair_url": null,
        "flair_bg_color": null,
        "flair_color": null,
        "flair_group_id": null,
        "badges_granted": [],
        "version": 2,
        "can_edit": false,
        "can_delete": false,
        "can_recover": false,
        "can_see_hidden_post": false,
        "can_wiki": false,
        "link_counts": [
            {
                "url": "https://wincmd.ru/plugring/tcimg.html",
                "internal": false,
                "reflection": false,
                "clicks": 16
            }
        ],
        "read": true,
        "user_title": null,
        "reply_to_user": {
            "username": "ilyaigpetrov",
            "name": "ilyaigpetrov",
            "avatar_template": "/letter_avatar_proxy/v4/letter/i/5fc32e/{size}.png"
        },
        "bookmarked": false,
        "actions_summary": [],
        "moderator": false,
        "admin": false,
        "staff": false,
        "user_id": 1804,
        "hidden": false,
        "trust_level": 2,
        "deleted_at": null,
        "user_deleted": false,
        "edit_reason": null,
        "can_view_edit_history": false,
        "wiki": false,
        "user_suspended": true,
        "post_url": "/t/ntcparty-%D0%BD%D0%B5-%D1%80%D0%B0%D0%B1%D0%BE%D1%82%D0%B0%D0%B5%D1%82-%D0%B2-%D0%BA%D0%B8%D1%82%D0%B0%D0%B9%D1%81%D0%BA%D0%BE%D0%BC-%D1%85%D1%80%D0%BE%D0%BC%D0%BE%D0%BF%D0%BE%D0%B4%D0%BE%D0%B1%D0%BD%D0%BE%D0%BC-%D0%B1%D1%80%D0%B0%D1%83%D0%B7%D0%B5%D1%80%D0%B5-360-extreme-explorer-v13023100-%D0%BD%D0%B0-%D0%BE%D1%81%D0%BD%D0%BE%D0%B2%D0%B5-chromium-86-%D0%BF%D0%BE%D0%B4-windows-xp-sp3/5685/8",
        "can_translate": false
    },
    {
        "id": 17703,
        "name": null,
        "username": "anon94384997",
        "avatar_template": "/letter_avatar_proxy/v4/letter/a/49beb7/{size}.png",
        "created_at": "2023-09-15T15:30:46.419Z",
        "cooked": "<p>Этот TCIMG (для Total Commander) я пробовал как-то исследовать. Но он такой сложный и кажется тормозной, что я не стал связываться.<br>\nДля кастомных операций с входом/обработкой/выходом я использую Universal GUI<br>\n<a href=\"https://github.com/artenax/ui\" rel=\"noopener nofollow ugc\">https://github.com/artenax/ui</a><br>\nПравда, надо компилировать, но можно одной командой. Для пакетных операций не очень годится, если только сами утилиты не поддерживают работу с несколькими файлами.</p>\n<p>Для кастомного пакетного конвертирования медиафайлов есть qwinff, например<br>\n<a href=\"https://qwinff.github.io\" rel=\"noopener nofollow ugc\">https://qwinff.github.io</a><br>\nОн есть в репозитории.</p>\n<p>Но пока можно на Win7-8.1 посидеть, какое-то время. Может, китайцы будут обновлять браузеры для них.</p>",
        "post_number": 9,
        "post_type": 1,
        "posts_count": 21,
        "updated_at": "2023-09-15T15:36:06.249Z",
        "reply_count": 1,
        "reply_to_post_number": 8,
        "quote_count": 0,
        "incoming_link_count": 0,
        "reads": 56,
        "readers_count": 55,
        "score": 16.2,
        "yours": false,
        "topic_id": 5685,
        "topic_slug": "ntcparty-%D0%BD%D0%B5-%D1%80%D0%B0%D0%B1%D0%BE%D1%82%D0%B0%D0%B5%D1%82-%D0%B2-%D0%BA%D0%B8%D1%82%D0%B0%D0%B9%D1%81%D0%BA%D0%BE%D0%BC-%D1%85%D1%80%D0%BE%D0%BC%D0%BE%D0%BF%D0%BE%D0%B4%D0%BE%D0%B1%D0%BD%D0%BE%D0%BC-%D0%B1%D1%80%D0%B0%D1%83%D0%B7%D0%B5%D1%80%D0%B5-360-extreme-explorer-v13023100-%D0%BD%D0%B0-%D0%BE%D1%81%D0%BD%D0%BE%D0%B2%D0%B5-chromium-86-%D0%BF%D0%BE%D0%B4-windows-xp-sp3",
        "display_username": null,
        "primary_group_name": null,
        "flair_name": null,
        "flair_url": null,
        "flair_bg_color": null,
        "flair_color": null,
        "flair_group_id": null,
        "badges_granted": [],
        "version": 2,
        "can_edit": false,
        "can_delete": false,
        "can_recover": false,
        "can_see_hidden_post": false,
        "can_wiki": false,
        "link_counts": [
            {
                "url": "https://github.com/artenax/ui",
                "internal": false,
                "reflection": false,
                "title": "GitHub - artenax/ui: Universal GUI",
                "clicks": 3
            },
            {
                "url": "https://qwinff.github.io",
                "internal": false,
                "reflection": false,
                "title": "Home | QWinFF",
                "clicks": 3
            }
        ],
        "read": true,
        "user_title": null,
        "reply_to_user": {
            "username": "EgorKuzevanov",
            "name": "Егор Кузеванов",
            "avatar_template": "/letter_avatar_proxy/v4/letter/e/db5fbb/{size}.png"
        },
        "bookmarked": false,
        "actions_summary": [],
        "moderator": false,
        "admin": false,
        "staff": false,
        "user_id": 1199,
        "hidden": false,
        "trust_level": 2,
        "deleted_at": null,
        "user_deleted": false,
        "edit_reason": null,
        "can_view_edit_history": false,
        "wiki": false,
        "post_url": "/t/ntcparty-%D0%BD%D0%B5-%D1%80%D0%B0%D0%B1%D0%BE%D1%82%D0%B0%D0%B5%D1%82-%D0%B2-%D0%BA%D0%B8%D1%82%D0%B0%D0%B9%D1%81%D0%BA%D0%BE%D0%BC-%D1%85%D1%80%D0%BE%D0%BC%D0%BE%D0%BF%D0%BE%D0%B4%D0%BE%D0%B1%D0%BD%D0%BE%D0%BC-%D0%B1%D1%80%D0%B0%D1%83%D0%B7%D0%B5%D1%80%D0%B5-360-extreme-explorer-v13023100-%D0%BD%D0%B0-%D0%BE%D1%81%D0%BD%D0%BE%D0%B2%D0%B5-chromium-86-%D0%BF%D0%BE%D0%B4-windows-xp-sp3/5685/9",
        "can_translate": false
    },
    {
        "id": 17704,
        "name": "Егор Кузеванов",
        "username": "EgorKuzevanov",
        "avatar_template": "/letter_avatar_proxy/v4/letter/e/db5fbb/{size}.png",
        "created_at": "2023-09-15T16:08:14.175Z",
        "cooked": "<p>На мой взгляд, утилита <a href=\"https://wincmd.ru/plugring/tcimg.html\" rel=\"noopener nofollow ugc\">TCIMG</a> для Windows от Андрея Александровича Аверина (на компьютерном форуме <a href=\"http://forum.ru-board.com\" rel=\"noopener nofollow ugc\">Ru-Board</a> известен под ником <strong>Andrey_A_A</strong>) значительно превосходит по функционалу утилиту командной строки <a href=\"https://www.nirsoft.net/utils/nircmd.html\" rel=\"noopener nofollow ugc\">NirCmd</a> от NirSoft (разработка последней, кстати, приостановлена с 2019 года). А благодаря тому, что утилита TCIMG является скомпилированным AutoIt-скриптом и регулярно обновляется путем добавления новых команд и параметров, с помощью TCIMG можно выполнять очень много задач автоматизации, хакерства, вирусописательства и очень много экспериментов с Windows (по подобию компьютерных YouTube-каналов <a href=\"https://www.youtube.com/@dan55800\" rel=\"noopener nofollow ugc\">“ЕРМАКОВ”</a>, <a href=\"https://www.youtube.com/@DanielM\" rel=\"noopener nofollow ugc\">“Daniel Myslivets”</a> и <a href=\"https://www.youtube.com/@NTDEV\" rel=\"noopener nofollow ugc\">“NTDEV”</a>) в случаях, когда бессильны входящие в состав всех версий Windows скриптовые языки BAT, VBScript, JScript и Windows PowerShell. Ради всего этого мне хотелось бы, чтобы кто-нибудь из пользователей Руборда написал книгу “Утилита TCIMG глазами хакера” в стиле известного автора книг о компьютерах и хакерстве Михаила Фленова.</p>",
        "post_number": 10,
        "post_type": 1,
        "posts_count": 21,
        "updated_at": "2023-09-15T16:37:55.501Z",
        "reply_count": 1,
        "reply_to_post_number": 9,
        "quote_count": 0,
        "incoming_link_count": 0,
        "reads": 51,
        "readers_count": 50,
        "score": 15.2,
        "yours": false,
        "topic_id": 5685,
        "topic_slug": "ntcparty-%D0%BD%D0%B5-%D1%80%D0%B0%D0%B1%D0%BE%D1%82%D0%B0%D0%B5%D1%82-%D0%B2-%D0%BA%D0%B8%D1%82%D0%B0%D0%B9%D1%81%D0%BA%D0%BE%D0%BC-%D1%85%D1%80%D0%BE%D0%BC%D0%BE%D0%BF%D0%BE%D0%B4%D0%BE%D0%B1%D0%BD%D0%BE%D0%BC-%D0%B1%D1%80%D0%B0%D1%83%D0%B7%D0%B5%D1%80%D0%B5-360-extreme-explorer-v13023100-%D0%BD%D0%B0-%D0%BE%D1%81%D0%BD%D0%BE%D0%B2%D0%B5-chromium-86-%D0%BF%D0%BE%D0%B4-windows-xp-sp3",
        "display_username": "Егор Кузеванов",
        "primary_group_name": null,
        "flair_name": null,
        "flair_url": null,
        "flair_bg_color": null,
        "flair_color": null,
        "flair_group_id": null,
        "badges_granted": [],
        "version": 4,
        "can_edit": false,
        "can_delete": false,
        "can_recover": false,
        "can_see_hidden_post": false,
        "can_wiki": false,
        "link_counts": [
            {
                "url": "https://wincmd.ru/plugring/tcimg.html",
                "internal": false,
                "reflection": false,
                "title": "TCIMG 33.2 - Все о Total Commander",
                "clicks": 5
            },
            {
                "url": "https://www.youtube.com/@DanielM",
                "internal": false,
                "reflection": false,
                "clicks": 1
            },
            {
                "url": "https://www.youtube.com/@dan55800",
                "internal": false,
                "reflection": false,
                "clicks": 1
            },
            {
                "url": "https://www.nirsoft.net/utils/nircmd.html",
                "internal": false,
                "reflection": false,
                "title": "NirCmd - Windows command line tool",
                "clicks": 1
            },
            {
                "url": "http://forum.ru-board.com",
                "internal": false,
                "reflection": false,
                "title": "Компьютерный форум Ru.Board",
                "clicks": 0
            },
            {
                "url": "https://www.youtube.com/@NTDEV",
                "internal": false,
                "reflection": false,
                "clicks": 0
            }
        ],
        "read": true,
        "user_title": null,
        "reply_to_user": {
            "username": "anon94384997",
            "name": null,
            "avatar_template": "/letter_avatar_proxy/v4/letter/a/49beb7/{size}.png"
        },
        "bookmarked": false,
        "actions_summary": [],
        "moderator": false,
        "admin": false,
        "staff": false,
        "user_id": 1804,
        "hidden": false,
        "trust_level": 2,
        "deleted_at": null,
        "user_deleted": false,
        "edit_reason": null,
        "can_view_edit_history": false,
        "wiki": false,
        "user_suspended": true,
        "post_url": "/t/ntcparty-%D0%BD%D0%B5-%D1%80%D0%B0%D0%B1%D0%BE%D1%82%D0%B0%D0%B5%D1%82-%D0%B2-%D0%BA%D0%B8%D1%82%D0%B0%D0%B9%D1%81%D0%BA%D0%BE%D0%BC-%D1%85%D1%80%D0%BE%D0%BC%D0%BE%D0%BF%D0%BE%D0%B4%D0%BE%D0%B1%D0%BD%D0%BE%D0%BC-%D0%B1%D1%80%D0%B0%D1%83%D0%B7%D0%B5%D1%80%D0%B5-360-extreme-explorer-v13023100-%D0%BD%D0%B0-%D0%BE%D1%81%D0%BD%D0%BE%D0%B2%D0%B5-chromium-86-%D0%BF%D0%BE%D0%B4-windows-xp-sp3/5685/10",
        "can_translate": false
    },
    {
        "id": 17707,
        "name": null,
        "username": "anon94384997",
        "avatar_template": "/letter_avatar_proxy/v4/letter/a/49beb7/{size}.png",
        "created_at": "2023-09-15T21:15:01.716Z",
        "cooked": "<p>А какие функции вы обычно выполняете в TCIMG?</p>\n<p>Я в UI обычно делаю:<br>\nскачивание с помощью yt-dlp<br>\nпреобразование txt в wav с помощью rhvoice<br>\nзаливка/скачивание по ssh<br>\nконвертирование fb2-txt<br>\nсоздание arc архива<br>\nдекодирование base64<br>\nанализ громкости аудиофайлов</p>",
        "post_number": 11,
        "post_type": 1,
        "posts_count": 21,
        "updated_at": "2023-09-15T21:21:17.973Z",
        "reply_count": 0,
        "reply_to_post_number": 10,
        "quote_count": 0,
        "incoming_link_count": 0,
        "reads": 48,
        "readers_count": 47,
        "score": 9.6,
        "yours": false,
        "topic_id": 5685,
        "topic_slug": "ntcparty-%D0%BD%D0%B5-%D1%80%D0%B0%D0%B1%D0%BE%D1%82%D0%B0%D0%B5%D1%82-%D0%B2-%D0%BA%D0%B8%D1%82%D0%B0%D0%B9%D1%81%D0%BA%D0%BE%D0%BC-%D1%85%D1%80%D0%BE%D0%BC%D0%BE%D0%BF%D0%BE%D0%B4%D0%BE%D0%B1%D0%BD%D0%BE%D0%BC-%D0%B1%D1%80%D0%B0%D1%83%D0%B7%D0%B5%D1%80%D0%B5-360-extreme-explorer-v13023100-%D0%BD%D0%B0-%D0%BE%D1%81%D0%BD%D0%BE%D0%B2%D0%B5-chromium-86-%D0%BF%D0%BE%D0%B4-windows-xp-sp3",
        "display_username": null,
        "primary_group_name": null,
        "flair_name": null,
        "flair_url": null,
        "flair_bg_color": null,
        "flair_color": null,
        "flair_group_id": null,
        "badges_granted": [],
        "version": 2,
        "can_edit": false,
        "can_delete": false,
        "can_recover": false,
        "can_see_hidden_post": false,
        "can_wiki": false,
        "read": true,
        "user_title": null,
        "reply_to_user": {
            "username": "EgorKuzevanov",
            "name": "Егор Кузеванов",
            "avatar_template": "/letter_avatar_proxy/v4/letter/e/db5fbb/{size}.png"
        },
        "bookmarked": false,
        "actions_summary": [],
        "moderator": false,
        "admin": false,
        "staff": false,
        "user_id": 1199,
        "hidden": false,
        "trust_level": 2,
        "deleted_at": null,
        "user_deleted": false,
        "edit_reason": null,
        "can_view_edit_history": false,
        "wiki": false,
        "post_url": "/t/ntcparty-%D0%BD%D0%B5-%D1%80%D0%B0%D0%B1%D0%BE%D1%82%D0%B0%D0%B5%D1%82-%D0%B2-%D0%BA%D0%B8%D1%82%D0%B0%D0%B9%D1%81%D0%BA%D0%BE%D0%BC-%D1%85%D1%80%D0%BE%D0%BC%D0%BE%D0%BF%D0%BE%D0%B4%D0%BE%D0%B1%D0%BD%D0%BE%D0%BC-%D0%B1%D1%80%D0%B0%D1%83%D0%B7%D0%B5%D1%80%D0%B5-360-extreme-explorer-v13023100-%D0%BD%D0%B0-%D0%BE%D1%81%D0%BD%D0%BE%D0%B2%D0%B5-chromium-86-%D0%BF%D0%BE%D0%B4-windows-xp-sp3/5685/11",
        "can_translate": false
    },
    {
        "id": 17746,
        "name": "ilyaigpetrov",
        "username": "ilyaigpetrov",
        "avatar_template": "/letter_avatar_proxy/v4/letter/i/5fc32e/{size}.png",
        "created_at": "2023-09-16T18:42:27.956Z",
        "cooked": "<aside class=\"quote no-group\" data-username=\"0ka\" data-post=\"3\" data-topic=\"5697\">\n<div class=\"title\">\n<div class=\"quote-controls\"></div>\n<img loading=\"lazy\" alt=\"\" width=\"24\" height=\"24\" src=\"https://ntc.party/letter_avatar_proxy/v4/letter/0/d78d45/48.png\" class=\"avatar\"><a href=\"https://ntc.party/t/%D1%81%D0%BE%D0%B2%D0%B5%D1%82%D1%8B-%D0%BF%D0%BE-%D0%BE%D0%BF%D1%82%D0%B8%D0%BC%D0%B8%D0%B7%D0%B0%D1%86%D0%B8%D0%B8-windows-10-%D0%B8-windows-11/5697/3\">Советы по оптимизации Windows 10 и Windows 11</a></div>\n<blockquote>\n<p>Как весь этот дикий оффтоп еще здесь находится не пойму, в других темах за подсказку не по теме сразу пост удаляется.</p>\n</blockquote>\n</aside>\n<ol>\n<li><a href=\"https://ru.wikipedia.org/wiki/%D0%9F%D1%80%D0%BE%D0%B1%D0%BB%D0%B5%D0%BC%D0%B0_XY_%28%D0%9E%D1%88%D0%B8%D0%B1%D0%BA%D0%B0_%D0%BC%D0%BE%D0%BB%D0%BE%D1%82%D0%BA%D0%B0%29\" class=\"inline-onebox\">Проблема XY (Ошибка молотка) — Википедия</a> и <a href=\"https://ru.meta.stackoverflow.com/a/710/275087\" class=\"inline-onebox\">Что такое «Ошибка молотка» или «Ошибка XY»? - Stack Overflow на русском Meta</a>.</li>\n<li>Мне интересно читать сообщения в этом топике, даже если они напрямую не касаются заявленной темы. Если вам кажутся какие-то сообщения лишними в данном обсуждении, то поставьте соответсвующий флажок (который модераторы могут проигнорировать).</li>\n</ol>",
        "post_number": 12,
        "post_type": 1,
        "posts_count": 21,
        "updated_at": "2023-09-17T17:47:24.701Z",
        "reply_count": 1,
        "reply_to_post_number": null,
        "quote_count": 1,
        "incoming_link_count": 2,
        "reads": 51,
        "readers_count": 50,
        "score": 25.2,
        "yours": false,
        "topic_id": 5685,
        "topic_slug": "ntcparty-%D0%BD%D0%B5-%D1%80%D0%B0%D0%B1%D0%BE%D1%82%D0%B0%D0%B5%D1%82-%D0%B2-%D0%BA%D0%B8%D1%82%D0%B0%D0%B9%D1%81%D0%BA%D0%BE%D0%BC-%D1%85%D1%80%D0%BE%D0%BC%D0%BE%D0%BF%D0%BE%D0%B4%D0%BE%D0%B1%D0%BD%D0%BE%D0%BC-%D0%B1%D1%80%D0%B0%D1%83%D0%B7%D0%B5%D1%80%D0%B5-360-extreme-explorer-v13023100-%D0%BD%D0%B0-%D0%BE%D1%81%D0%BD%D0%BE%D0%B2%D0%B5-chromium-86-%D0%BF%D0%BE%D0%B4-windows-xp-sp3",
        "display_username": "ilyaigpetrov",
        "primary_group_name": null,
        "flair_name": null,
        "flair_url": null,
        "flair_bg_color": null,
        "flair_color": null,
        "flair_group_id": null,
        "badges_granted": [],
        "version": 2,
        "can_edit": false,
        "can_delete": false,
        "can_recover": false,
        "can_see_hidden_post": false,
        "can_wiki": false,
        "link_counts": [
            {
                "url": "https://ru.wikipedia.org/wiki/%D0%9F%D1%80%D0%BE%D0%B1%D0%BB%D0%B5%D0%BC%D0%B0_XY_%28%D0%9E%D1%88%D0%B8%D0%B1%D0%BA%D0%B0_%D0%BC%D0%BE%D0%BB%D0%BE%D1%82%D0%BA%D0%B0%29",
                "internal": false,
                "reflection": false,
                "title": "Проблема XY (Ошибка молотка) — Википедия",
                "clicks": 5
            },
            {
                "url": "https://ru.meta.stackoverflow.com/a/710/275087",
                "internal": false,
                "reflection": false,
                "title": "Что такое «Ошибка молотка» или «Ошибка XY»? - Stack Overflow на русском Meta",
                "clicks": 2
            },
            {
                "url": "https://ntc.party/t/%D1%81%D0%BE%D0%B2%D0%B5%D1%82%D1%8B-%D0%BF%D0%BE-%D0%BE%D0%BF%D1%82%D0%B8%D0%BC%D0%B8%D0%B7%D0%B0%D1%86%D0%B8%D0%B8-windows-10-%D0%B8-windows-11/5697/3",
                "internal": true,
                "reflection": false,
                "title": "Советы по оптимизации Windows 10 и Windows 11",
                "clicks": 0
            },
            {
                "url": "https://ntc.party/t/%D1%81%D0%BE%D0%B2%D0%B5%D1%82%D1%8B-%D0%BF%D0%BE-%D0%BE%D0%BF%D1%82%D0%B8%D0%BC%D0%B8%D0%B7%D0%B0%D1%86%D0%B8%D0%B8-windows-10-%D0%B8-windows-11/5697/7",
                "internal": true,
                "reflection": true,
                "title": "Советы по оптимизации Windows 10 и Windows 11",
                "clicks": 6
            }
        ],
        "read": true,
        "user_title": "Russian Censorship Bypass Extension staff",
        "title_is_group": false,
        "bookmarked": false,
        "actions_summary": [],
        "moderator": true,
        "admin": false,
        "staff": true,
        "user_id": 6,
        "hidden": false,
        "trust_level": 2,
        "deleted_at": null,
        "user_deleted": false,
        "edit_reason": null,
        "can_view_edit_history": false,
        "wiki": false,
        "post_url": "/t/ntcparty-%D0%BD%D0%B5-%D1%80%D0%B0%D0%B1%D0%BE%D1%82%D0%B0%D0%B5%D1%82-%D0%B2-%D0%BA%D0%B8%D1%82%D0%B0%D0%B9%D1%81%D0%BA%D0%BE%D0%BC-%D1%85%D1%80%D0%BE%D0%BC%D0%BE%D0%BF%D0%BE%D0%B4%D0%BE%D0%B1%D0%BD%D0%BE%D0%BC-%D0%B1%D1%80%D0%B0%D1%83%D0%B7%D0%B5%D1%80%D0%B5-360-extreme-explorer-v13023100-%D0%BD%D0%B0-%D0%BE%D1%81%D0%BD%D0%BE%D0%B2%D0%B5-chromium-86-%D0%BF%D0%BE%D0%B4-windows-xp-sp3/5685/12",
        "can_translate": false
    },
    {
        "id": 17755,
        "name": "ilyaigpetrov",
        "username": "ilyaigpetrov",
        "avatar_template": "/letter_avatar_proxy/v4/letter/i/5fc32e/{size}.png",
        "created_at": "2023-09-17T17:37:35.956Z",
        "cooked": "<p>8 posts were split to a new topic: <a href=\"/t/%D1%81%D0%BE%D0%B2%D0%B5%D1%82%D1%8B-%D0%BF%D0%BE-%D0%BE%D0%BF%D1%82%D0%B8%D0%BC%D0%B8%D0%B7%D0%B0%D1%86%D0%B8%D0%B8-windows-10/5697\">Советы по оптимизации Windows 10 и Windows 11</a></p>",
        "post_number": 14,
        "post_type": 3,
        "posts_count": 21,
        "updated_at": "2023-09-17T17:47:24.691Z",
        "reply_count": 0,
        "reply_to_post_number": null,
        "quote_count": 0,
        "incoming_link_count": 0,
        "reads": 48,
        "readers_count": 47,
        "score": 9.6,
        "yours": false,
        "topic_id": 5685,
        "topic_slug": "ntcparty-%D0%BD%D0%B5-%D1%80%D0%B0%D0%B1%D0%BE%D1%82%D0%B0%D0%B5%D1%82-%D0%B2-%D0%BA%D0%B8%D1%82%D0%B0%D0%B9%D1%81%D0%BA%D0%BE%D0%BC-%D1%85%D1%80%D0%BE%D0%BC%D0%BE%D0%BF%D0%BE%D0%B4%D0%BE%D0%B1%D0%BD%D0%BE%D0%BC-%D0%B1%D1%80%D0%B0%D1%83%D0%B7%D0%B5%D1%80%D0%B5-360-extreme-explorer-v13023100-%D0%BD%D0%B0-%D0%BE%D1%81%D0%BD%D0%BE%D0%B2%D0%B5-chromium-86-%D0%BF%D0%BE%D0%B4-windows-xp-sp3",
        "display_username": "ilyaigpetrov",
        "primary_group_name": null,
        "flair_name": null,
        "flair_url": null,
        "flair_bg_color": null,
        "flair_color": null,
        "flair_group_id": null,
        "badges_granted": [],
        "version": 1,
        "can_edit": false,
        "can_delete": false,
        "can_recover": false,
        "can_see_hidden_post": false,
        "can_wiki": false,
        "link_counts": [
            {
                "url": "https://ntc.party/t/%D1%81%D0%BE%D0%B2%D0%B5%D1%82%D1%8B-%D0%BF%D0%BE-%D0%BE%D0%BF%D1%82%D0%B8%D0%BC%D0%B8%D0%B7%D0%B0%D1%86%D0%B8%D0%B8-windows-10-%D0%B8-windows-11/5697",
                "internal": true,
                "reflection": false,
                "title": "Советы по оптимизации Windows 10 и Windows 11",
                "clicks": 0
            }
        ],
        "read": true,
        "user_title": "Russian Censorship Bypass Extension staff",
        "title_is_group": false,
        "bookmarked": false,
        "actions_summary": [],
        "moderator": true,
        "admin": false,
        "staff": true,
        "user_id": 6,
        "hidden": false,
        "trust_level": 2,
        "deleted_at": null,
        "user_deleted": false,
        "edit_reason": null,
        "can_view_edit_history": false,
        "wiki": false,
        "action_code": "split_topic",
        "post_url": "/t/ntcparty-%D0%BD%D0%B5-%D1%80%D0%B0%D0%B1%D0%BE%D1%82%D0%B0%D0%B5%D1%82-%D0%B2-%D0%BA%D0%B8%D1%82%D0%B0%D0%B9%D1%81%D0%BA%D0%BE%D0%BC-%D1%85%D1%80%D0%BE%D0%BC%D0%BE%D0%BF%D0%BE%D0%B4%D0%BE%D0%B1%D0%BD%D0%BE%D0%BC-%D0%B1%D1%80%D0%B0%D1%83%D0%B7%D0%B5%D1%80%D0%B5-360-extreme-explorer-v13023100-%D0%BD%D0%B0-%D0%BE%D1%81%D0%BD%D0%BE%D0%B2%D0%B5-chromium-86-%D0%BF%D0%BE%D0%B4-windows-xp-sp3/5685/14",
        "can_translate": false
    },
    {
        "id": 17713,
        "name": null,
        "username": "anon94384997",
        "avatar_template": "/letter_avatar_proxy/v4/letter/a/49beb7/{size}.png",
        "created_at": "2023-09-15T23:31:10.266Z",
        "cooked": "<p>А как отправлять в ntc сообщения через почту? Только если ответить на письмо с уведомлением?</p>",
        "post_number": 15,
        "post_type": 1,
        "posts_count": 21,
        "updated_at": "2023-09-17T17:47:24.688Z",
        "reply_count": 0,
        "reply_to_post_number": null,
        "quote_count": 0,
        "incoming_link_count": 0,
        "reads": 53,
        "readers_count": 52,
        "score": 10.6,
        "yours": false,
        "topic_id": 5685,
        "topic_slug": "ntcparty-%D0%BD%D0%B5-%D1%80%D0%B0%D0%B1%D0%BE%D1%82%D0%B0%D0%B5%D1%82-%D0%B2-%D0%BA%D0%B8%D1%82%D0%B0%D0%B9%D1%81%D0%BA%D0%BE%D0%BC-%D1%85%D1%80%D0%BE%D0%BC%D0%BE%D0%BF%D0%BE%D0%B4%D0%BE%D0%B1%D0%BD%D0%BE%D0%BC-%D0%B1%D1%80%D0%B0%D1%83%D0%B7%D0%B5%D1%80%D0%B5-360-extreme-explorer-v13023100-%D0%BD%D0%B0-%D0%BE%D1%81%D0%BD%D0%BE%D0%B2%D0%B5-chromium-86-%D0%BF%D0%BE%D0%B4-windows-xp-sp3",
        "display_username": null,
        "primary_group_name": null,
        "flair_name": null,
        "flair_url": null,
        "flair_bg_color": null,
        "flair_color": null,
        "flair_group_id": null,
        "badges_granted": [],
        "version": 1,
        "can_edit": false,
        "can_delete": false,
        "can_recover": false,
        "can_see_hidden_post": false,
        "can_wiki": false,
        "read": true,
        "user_title": null,
        "bookmarked": false,
        "actions_summary": [],
        "moderator": false,
        "admin": false,
        "staff": false,
        "user_id": 1199,
        "hidden": false,
        "trust_level": 2,
        "deleted_at": null,
        "user_deleted": false,
        "edit_reason": null,
        "can_view_edit_history": false,
        "wiki": false,
        "post_url": "/t/ntcparty-%D0%BD%D0%B5-%D1%80%D0%B0%D0%B1%D0%BE%D1%82%D0%B0%D0%B5%D1%82-%D0%B2-%D0%BA%D0%B8%D1%82%D0%B0%D0%B9%D1%81%D0%BA%D0%BE%D0%BC-%D1%85%D1%80%D0%BE%D0%BC%D0%BE%D0%BF%D0%BE%D0%B4%D0%BE%D0%B1%D0%BD%D0%BE%D0%BC-%D0%B1%D1%80%D0%B0%D1%83%D0%B7%D0%B5%D1%80%D0%B5-360-extreme-explorer-v13023100-%D0%BD%D0%B0-%D0%BE%D1%81%D0%BD%D0%BE%D0%B2%D0%B5-chromium-86-%D0%BF%D0%BE%D0%B4-windows-xp-sp3/5685/15",
        "can_translate": false
    },
    {
        "id": 17754,
        "name": "ilyaigpetrov",
        "username": "ilyaigpetrov",
        "avatar_template": "/letter_avatar_proxy/v4/letter/i/5fc32e/{size}.png",
        "created_at": "2023-09-17T17:25:42.093Z",
        "cooked": "<p>4 posts were split to a new topic: <a href=\"/t/%D1%81%D0%BE%D0%B2%D0%B5%D1%82%D1%83%D0%B5%D1%82%D0%B5-%D0%BB%D0%B8%D0%BD%D1%83%D0%BA%D1%81-%D1%80%D0%B0%D1%81%D1%81%D0%BA%D0%B0%D0%B6%D0%B8%D1%82%D0%B5-%D0%B8-%D0%BE-%D1%82%D0%BE%D0%BA%D1%81%D0%B8%D1%87%D0%BD%D0%BE%D0%BC-%D0%BB%D0%BE%D1%80%D0%B5-linuxorgru/5696\">Советуете линукс – расскажите и о токсичном ЛОРе (linux.org.ru)</a></p>",
        "post_number": 16,
        "post_type": 3,
        "posts_count": 21,
        "updated_at": "2023-09-17T17:47:24.686Z",
        "reply_count": 0,
        "reply_to_post_number": null,
        "quote_count": 0,
        "incoming_link_count": 0,
        "reads": 51,
        "readers_count": 50,
        "score": 10.2,
        "yours": false,
        "topic_id": 5685,
        "topic_slug": "ntcparty-%D0%BD%D0%B5-%D1%80%D0%B0%D0%B1%D0%BE%D1%82%D0%B0%D0%B5%D1%82-%D0%B2-%D0%BA%D0%B8%D1%82%D0%B0%D0%B9%D1%81%D0%BA%D0%BE%D0%BC-%D1%85%D1%80%D0%BE%D0%BC%D0%BE%D0%BF%D0%BE%D0%B4%D0%BE%D0%B1%D0%BD%D0%BE%D0%BC-%D0%B1%D1%80%D0%B0%D1%83%D0%B7%D0%B5%D1%80%D0%B5-360-extreme-explorer-v13023100-%D0%BD%D0%B0-%D0%BE%D1%81%D0%BD%D0%BE%D0%B2%D0%B5-chromium-86-%D0%BF%D0%BE%D0%B4-windows-xp-sp3",
        "display_username": "ilyaigpetrov",
        "primary_group_name": null,
        "flair_name": null,
        "flair_url": null,
        "flair_bg_color": null,
        "flair_color": null,
        "flair_group_id": null,
        "badges_granted": [],
        "version": 1,
        "can_edit": false,
        "can_delete": false,
        "can_recover": false,
        "can_see_hidden_post": false,
        "can_wiki": false,
        "link_counts": [
            {
                "url": "https://ntc.party/t/%D1%81%D0%BE%D0%B2%D0%B5%D1%82%D1%83%D0%B5%D1%82%D0%B5-%D0%BB%D0%B8%D0%BD%D1%83%D0%BA%D1%81-%D1%80%D0%B0%D1%81%D1%81%D0%BA%D0%B0%D0%B6%D0%B8%D1%82%D0%B5-%D0%B8-%D0%BE-%D1%82%D0%BE%D0%BA%D1%81%D0%B8%D1%87%D0%BD%D0%BE%D0%BC-%D0%BB%D0%BE%D1%80%D0%B5-linuxorgru/5696",
                "internal": true,
                "reflection": false,
                "title": "Советуете линукс -- расскажите и о токсичном ЛОРе (linux.org.ru)",
                "clicks": 0
            }
        ],
        "read": true,
        "user_title": "Russian Censorship Bypass Extension staff",
        "title_is_group": false,
        "bookmarked": false,
        "actions_summary": [],
        "moderator": true,
        "admin": false,
        "staff": true,
        "user_id": 6,
        "hidden": false,
        "trust_level": 2,
        "deleted_at": null,
        "user_deleted": false,
        "edit_reason": null,
        "can_view_edit_history": false,
        "wiki": false,
        "action_code": "split_topic",
        "post_url": "/t/ntcparty-%D0%BD%D0%B5-%D1%80%D0%B0%D0%B1%D0%BE%D1%82%D0%B0%D0%B5%D1%82-%D0%B2-%D0%BA%D0%B8%D1%82%D0%B0%D0%B9%D1%81%D0%BA%D0%BE%D0%BC-%D1%85%D1%80%D0%BE%D0%BC%D0%BE%D0%BF%D0%BE%D0%B4%D0%BE%D0%B1%D0%BD%D0%BE%D0%BC-%D0%B1%D1%80%D0%B0%D1%83%D0%B7%D0%B5%D1%80%D0%B5-360-extreme-explorer-v13023100-%D0%BD%D0%B0-%D0%BE%D1%81%D0%BD%D0%BE%D0%B2%D0%B5-chromium-86-%D0%BF%D0%BE%D0%B4-windows-xp-sp3/5685/16",
        "can_translate": false
    },
    {
        "id": 17735,
        "name": null,
        "username": "anon94384997",
        "avatar_template": "/letter_avatar_proxy/v4/letter/a/49beb7/{size}.png",
        "created_at": "2023-09-16T15:35:57.300Z",
        "cooked": "<aside class=\"onebox discoursetopic\" data-onebox-src=\"https://meta.discourse.org/t/extending-the-capabilities-of-the-simplified-mode/279235\">\n  <header class=\"source\">\n      <img src=\"ntcparty-не-работает-в-китайском-хромоподобном-браузере-360-extreme-explorer-v13023100-на-основе-chromium-86-под-windows-xp-sp3/999ecd27ce1081679a496e1c20889bba79bdc5e8.png\" class=\"site-icon\" data-dominant-color=\"6B6A4D\" width=\"32\" height=\"32\">\n\n      <a href=\"https://meta.discourse.org/t/extending-the-capabilities-of-the-simplified-mode/279235\" target=\"_blank\" rel=\"noopener nofollow ugc\" title=\"03:16PM - 16 September 2023\">Discourse Meta – 16 Sep 23</a>\n  </header>\n\n  <article class=\"onebox-body\">\n    <img src=\"ntcparty-не-работает-в-китайском-хромоподобном-браузере-360-extreme-explorer-v13023100-на-основе-chromium-86-под-windows-xp-sp3/ecc92a52ee7353e03d5c0d1ea6521ce4541d9c25_2_500x500.png\" class=\"thumbnail onebox-avatar\" data-dominant-color=\"6B6A4D\" width=\"500\" height=\"500\">\n\n<div class=\"title-wrapper\">\n  <h3><a href=\"https://meta.discourse.org/t/extending-the-capabilities-of-the-simplified-mode/279235\" target=\"_blank\" rel=\"noopener nofollow ugc\">Extending the capabilities of the simplified mode</a></h3>\n  <div class=\"topic-category\">\n      <span class=\"badge-wrapper bullet\">\n        <span class=\"badge-category-bg\" style=\"background-color: #0E76BD;\"></span>\n        <span class=\"badge-category clear-badge\">\n          <span class=\"category-name\">feature</span>\n        </span>\n      </span>\n  </div>\n</div>\n\n  <p>Hello.  Some users are forced to use the simplified mode on discourse engine forums for various reasons:   The browser is outdated and there is no way to update it. For example, XP fans (they exist) or old Android users. Weak hardware on which it...</p>\n\n  <p>\n    <span class=\"label1\">Reading time: 1 mins 🕑</span>\n      <span class=\"label2\">Likes: 8 ❤</span>\n  </p>\n\n  </article>\n\n  <div class=\"onebox-metadata\">\n    \n    \n  </div>\n\n  <div style=\"clear: both\"></div>\n</aside>\n",
        "post_number": 17,
        "post_type": 1,
        "posts_count": 21,
        "updated_at": "2023-09-17T17:47:24.683Z",
        "reply_count": 1,
        "reply_to_post_number": null,
        "quote_count": 0,
        "incoming_link_count": 0,
        "reads": 56,
        "readers_count": 55,
        "score": 16.2,
        "yours": false,
        "topic_id": 5685,
        "topic_slug": "ntcparty-%D0%BD%D0%B5-%D1%80%D0%B0%D0%B1%D0%BE%D1%82%D0%B0%D0%B5%D1%82-%D0%B2-%D0%BA%D0%B8%D1%82%D0%B0%D0%B9%D1%81%D0%BA%D0%BE%D0%BC-%D1%85%D1%80%D0%BE%D0%BC%D0%BE%D0%BF%D0%BE%D0%B4%D0%BE%D0%B1%D0%BD%D0%BE%D0%BC-%D0%B1%D1%80%D0%B0%D1%83%D0%B7%D0%B5%D1%80%D0%B5-360-extreme-explorer-v13023100-%D0%BD%D0%B0-%D0%BE%D1%81%D0%BD%D0%BE%D0%B2%D0%B5-chromium-86-%D0%BF%D0%BE%D0%B4-windows-xp-sp3",
        "display_username": null,
        "primary_group_name": null,
        "flair_name": null,
        "flair_url": null,
        "flair_bg_color": null,
        "flair_color": null,
        "flair_group_id": null,
        "badges_granted": [],
        "version": 1,
        "can_edit": false,
        "can_delete": false,
        "can_recover": false,
        "can_see_hidden_post": false,
        "can_wiki": false,
        "link_counts": [
            {
                "url": "https://meta.discourse.org/t/extending-the-capabilities-of-the-simplified-mode/279235",
                "internal": false,
                "reflection": false,
                "title": "Extending the capabilities of the simplified mode - feature - Discourse Meta",
                "clicks": 6
            }
        ],
        "read": true,
        "user_title": null,
        "bookmarked": false,
        "actions_summary": [],
        "moderator": false,
        "admin": false,
        "staff": false,
        "user_id": 1199,
        "hidden": false,
        "trust_level": 2,
        "deleted_at": null,
        "user_deleted": false,
        "edit_reason": null,
        "can_view_edit_history": false,
        "wiki": false,
        "post_url": "/t/ntcparty-%D0%BD%D0%B5-%D1%80%D0%B0%D0%B1%D0%BE%D1%82%D0%B0%D0%B5%D1%82-%D0%B2-%D0%BA%D0%B8%D1%82%D0%B0%D0%B9%D1%81%D0%BA%D0%BE%D0%BC-%D1%85%D1%80%D0%BE%D0%BC%D0%BE%D0%BF%D0%BE%D0%B4%D0%BE%D0%B1%D0%BD%D0%BE%D0%BC-%D0%B1%D1%80%D0%B0%D1%83%D0%B7%D0%B5%D1%80%D0%B5-360-extreme-explorer-v13023100-%D0%BD%D0%B0-%D0%BE%D1%81%D0%BD%D0%BE%D0%B2%D0%B5-chromium-86-%D0%BF%D0%BE%D0%B4-windows-xp-sp3/5685/17",
        "can_translate": false
    },
    {
        "id": 18297,
        "name": null,
        "username": "anon94384997",
        "avatar_template": "/letter_avatar_proxy/v4/letter/a/49beb7/{size}.png",
        "created_at": "2023-09-30T15:57:05.976Z",
        "cooked": "<p>Разработчики ответили, что они используют JS движок и поэтому полноценной работы в упрощенной версии не будет.</p>\n<p>ntc.party работает в майском Serpent. Сейчас пишу с него. Правда в самосборном на Linux64. А под XP собирает roytam.<br>\nЯ только добавил в uBlock legacy:<br>\nntc.party*/assets/browser-detect-*</p>\n<p>Если что, обращайтесь туда.<br>\n<a href=\"https://forum.palemoon.org/viewtopic.php?f=70&amp;t=29327&amp;start=120\" class=\"onebox\" target=\"_blank\" rel=\"noopener nofollow ugc\">https://forum.palemoon.org/viewtopic.php?f=70&amp;t=29327&amp;start=120</a></p>",
        "post_number": 25,
        "post_type": 1,
        "posts_count": 21,
        "updated_at": "2023-09-30T19:30:08.961Z",
        "reply_count": 0,
        "reply_to_post_number": 17,
        "quote_count": 0,
        "incoming_link_count": 1,
        "reads": 56,
        "readers_count": 55,
        "score": 16.2,
        "yours": false,
        "topic_id": 5685,
        "topic_slug": "ntcparty-%D0%BD%D0%B5-%D1%80%D0%B0%D0%B1%D0%BE%D1%82%D0%B0%D0%B5%D1%82-%D0%B2-%D0%BA%D0%B8%D1%82%D0%B0%D0%B9%D1%81%D0%BA%D0%BE%D0%BC-%D1%85%D1%80%D0%BE%D0%BC%D0%BE%D0%BF%D0%BE%D0%B4%D0%BE%D0%B1%D0%BD%D0%BE%D0%BC-%D0%B1%D1%80%D0%B0%D1%83%D0%B7%D0%B5%D1%80%D0%B5-360-extreme-explorer-v13023100-%D0%BD%D0%B0-%D0%BE%D1%81%D0%BD%D0%BE%D0%B2%D0%B5-chromium-86-%D0%BF%D0%BE%D0%B4-windows-xp-sp3",
        "display_username": null,
        "primary_group_name": null,
        "flair_name": null,
        "flair_url": null,
        "flair_bg_color": null,
        "flair_color": null,
        "flair_group_id": null,
        "badges_granted": [],
        "version": 3,
        "can_edit": false,
        "can_delete": false,
        "can_recover": false,
        "can_see_hidden_post": false,
        "can_wiki": false,
        "link_counts": [
            {
                "url": "https://forum.palemoon.org/viewtopic.php?f=70&t=29327&start=120",
                "internal": false,
                "reflection": false,
                "title": "Discourse forums no longer allowing me to log in - Page 7 - Pale Moon forum",
                "clicks": 1
            }
        ],
        "read": true,
        "user_title": null,
        "reply_to_user": {
            "username": "anon94384997",
            "name": null,
            "avatar_template": "/letter_avatar_proxy/v4/letter/a/49beb7/{size}.png"
        },
        "bookmarked": false,
        "actions_summary": [],
        "moderator": false,
        "admin": false,
        "staff": false,
        "user_id": 1199,
        "hidden": false,
        "trust_level": 2,
        "deleted_at": null,
        "user_deleted": false,
        "edit_reason": null,
        "can_view_edit_history": false,
        "wiki": false,
        "post_url": "/t/ntcparty-%D0%BD%D0%B5-%D1%80%D0%B0%D0%B1%D0%BE%D1%82%D0%B0%D0%B5%D1%82-%D0%B2-%D0%BA%D0%B8%D1%82%D0%B0%D0%B9%D1%81%D0%BA%D0%BE%D0%BC-%D1%85%D1%80%D0%BE%D0%BC%D0%BE%D0%BF%D0%BE%D0%B4%D0%BE%D0%B1%D0%BD%D0%BE%D0%BC-%D0%B1%D1%80%D0%B0%D1%83%D0%B7%D0%B5%D1%80%D0%B5-360-extreme-explorer-v13023100-%D0%BD%D0%B0-%D0%BE%D1%81%D0%BD%D0%BE%D0%B2%D0%B5-chromium-86-%D0%BF%D0%BE%D0%B4-windows-xp-sp3/5685/25",
        "can_translate": false
    },
    {
        "id": 20471,
        "name": "",
        "username": "heejew",
        "avatar_template": "/user_avatar/ntc.party/heejew/{size}/4007_2.png",
        "created_at": "2023-12-01T17:36:46.401Z",
        "cooked": "<p>На линуксе вам TCIMG не нужен вообще, забудьте про него и идите на линукс спокойно.</p>\n<p>На линуксе у вас будет куда больше свободы, только чуть bash понять, или python вместо него. Вам этого хватит на все задачи.  И куча других тулзовин, если надо, найдете.<br>\nПри смене ОС смена любимого ПО в целом зачастую неизбежна. Держаться лишь за какую-то тулзовину - гиблое занятие, поверьте. А в данном случае бессмысленно втройне - это не незаменимое ПО, как, например, специализированный софт для дизайнеров или фотографов.</p>\n<p>По факту у вас варианта три:</p>\n<ul>\n<li>Обновлять железо и сидеть на более-менее актуальной ОС. Но как вы отметили, у вас нет средств.</li>\n<li>Идти на линукс и изучать новые инструменты. Самый оптимальный вариант.</li>\n<li>Продолжать жрать кактус и пытаться усидеть на старой ОСи. Но тут будьте готовы, что какие-то ресурсы не будут работать у вас. И никто не будет учитывать застрявших юзеров в 2007ом. И вам придется городить какие-то костыли и искать решения зачастую самостоятельно, т.к. таких пользователей становится экстремально мало. Такова данность.  Не тратьте время впустую, пересядьте на линукс, возможно, это поможет вам и в профессиональной среде и поможет найти работу, в следствие которой вы сможете обновить железо. Из вас получился бы неплохой специалист в ИТ с вашей “душностью”, но, без обид, вы тратите энергию не туда.</li>\n</ul>\n<p>P.S. На мой взгляд, утилита TCIMG морально устарела лет 15 назад, несмотря на обновления. Неужели она на XP и правда такая полезная и ей нельзя найти замену? Оо</p>",
        "post_number": 28,
        "post_type": 1,
        "posts_count": 21,
        "updated_at": "2023-12-01T17:40:23.189Z",
        "reply_count": 0,
        "reply_to_post_number": 8,
        "quote_count": 0,
        "incoming_link_count": 20,
        "reads": 44,
        "readers_count": 43,
        "score": 108.8,
        "yours": false,
        "topic_id": 5685,
        "topic_slug": "ntcparty-%D0%BD%D0%B5-%D1%80%D0%B0%D0%B1%D0%BE%D1%82%D0%B0%D0%B5%D1%82-%D0%B2-%D0%BA%D0%B8%D1%82%D0%B0%D0%B9%D1%81%D0%BA%D0%BE%D0%BC-%D1%85%D1%80%D0%BE%D0%BC%D0%BE%D0%BF%D0%BE%D0%B4%D0%BE%D0%B1%D0%BD%D0%BE%D0%BC-%D0%B1%D1%80%D0%B0%D1%83%D0%B7%D0%B5%D1%80%D0%B5-360-extreme-explorer-v13023100-%D0%BD%D0%B0-%D0%BE%D1%81%D0%BD%D0%BE%D0%B2%D0%B5-chromium-86-%D0%BF%D0%BE%D0%B4-windows-xp-sp3",
        "display_username": "",
        "primary_group_name": null,
        "flair_name": null,
        "flair_url": null,
        "flair_bg_color": null,
        "flair_color": null,
        "flair_group_id": null,
        "badges_granted": [],
        "version": 2,
        "can_edit": false,
        "can_delete": false,
        "can_recover": false,
        "can_see_hidden_post": false,
        "can_wiki": false,
        "read": true,
        "user_title": null,
        "reply_to_user": {
            "username": "EgorKuzevanov",
            "name": "Егор Кузеванов",
            "avatar_template": "/letter_avatar_proxy/v4/letter/e/db5fbb/{size}.png"
        },
        "bookmarked": false,
        "actions_summary": [],
        "moderator": false,
        "admin": false,
        "staff": false,
        "user_id": 2871,
        "hidden": false,
        "trust_level": 1,
        "deleted_at": null,
        "user_deleted": false,
        "edit_reason": null,
        "can_view_edit_history": false,
        "wiki": false,
        "post_url": "/t/ntcparty-%D0%BD%D0%B5-%D1%80%D0%B0%D0%B1%D0%BE%D1%82%D0%B0%D0%B5%D1%82-%D0%B2-%D0%BA%D0%B8%D1%82%D0%B0%D0%B9%D1%81%D0%BA%D0%BE%D0%BC-%D1%85%D1%80%D0%BE%D0%BC%D0%BE%D0%BF%D0%BE%D0%B4%D0%BE%D0%B1%D0%BD%D0%BE%D0%BC-%D0%B1%D1%80%D0%B0%D1%83%D0%B7%D0%B5%D1%80%D0%B5-360-extreme-explorer-v13023100-%D0%BD%D0%B0-%D0%BE%D1%81%D0%BD%D0%BE%D0%B2%D0%B5-chromium-86-%D0%BF%D0%BE%D0%B4-windows-xp-sp3/5685/28",
        "can_translate": false
    },
    {
        "id": 21712,
        "name": "",
        "username": "Syrufit",
        "avatar_template": "/user_avatar/ntc.party/syrufit/{size}/4211_2.png",
        "created_at": "2024-01-14T11:09:19.741Z",
        "cooked": "<p>Как выше написали, вам действительно стоит в вашей ситуации перейти на Linux дистрибутивы, благо их множество, и можно все настроить под себя и свое железо, сейчас много туториалов и мануалов в интернете на английском, на русском, да хоть на японском если вам угодно. Конечно в первый раз может быть не удобно, но это как переехать в другую квартиру где вам нужно самому все обставить, что-то во время переезда придется выкинуть, а что-то вы оставите от старой. В общем, не боитесь пробовать новое для вас.</p>",
        "post_number": 30,
        "post_type": 1,
        "posts_count": 21,
        "updated_at": "2024-01-14T11:09:52.713Z",
        "reply_count": 0,
        "reply_to_post_number": null,
        "quote_count": 0,
        "incoming_link_count": 0,
        "reads": 38,
        "readers_count": 37,
        "score": 7.6,
        "yours": false,
        "topic_id": 5685,
        "topic_slug": "ntcparty-%D0%BD%D0%B5-%D1%80%D0%B0%D0%B1%D0%BE%D1%82%D0%B0%D0%B5%D1%82-%D0%B2-%D0%BA%D0%B8%D1%82%D0%B0%D0%B9%D1%81%D0%BA%D0%BE%D0%BC-%D1%85%D1%80%D0%BE%D0%BC%D0%BE%D0%BF%D0%BE%D0%B4%D0%BE%D0%B1%D0%BD%D0%BE%D0%BC-%D0%B1%D1%80%D0%B0%D1%83%D0%B7%D0%B5%D1%80%D0%B5-360-extreme-explorer-v13023100-%D0%BD%D0%B0-%D0%BE%D1%81%D0%BD%D0%BE%D0%B2%D0%B5-chromium-86-%D0%BF%D0%BE%D0%B4-windows-xp-sp3",
        "display_username": "",
        "primary_group_name": null,
        "flair_name": null,
        "flair_url": null,
        "flair_bg_color": null,
        "flair_color": null,
        "flair_group_id": null,
        "badges_granted": [],
        "version": 1,
        "can_edit": false,
        "can_delete": false,
        "can_recover": false,
        "can_see_hidden_post": false,
        "can_wiki": false,
        "read": true,
        "user_title": "",
        "bookmarked": false,
        "actions_summary": [],
        "moderator": false,
        "admin": false,
        "staff": false,
        "user_id": 3117,
        "hidden": false,
        "trust_level": 1,
        "deleted_at": null,
        "user_deleted": false,
        "edit_reason": null,
        "can_view_edit_history": false,
        "wiki": false,
        "post_url": "/t/ntcparty-%D0%BD%D0%B5-%D1%80%D0%B0%D0%B1%D0%BE%D1%82%D0%B0%D0%B5%D1%82-%D0%B2-%D0%BA%D0%B8%D1%82%D0%B0%D0%B9%D1%81%D0%BA%D0%BE%D0%BC-%D1%85%D1%80%D0%BE%D0%BC%D0%BE%D0%BF%D0%BE%D0%B4%D0%BE%D0%B1%D0%BD%D0%BE%D0%BC-%D0%B1%D1%80%D0%B0%D1%83%D0%B7%D0%B5%D1%80%D0%B5-360-extreme-explorer-v13023100-%D0%BD%D0%B0-%D0%BE%D1%81%D0%BD%D0%BE%D0%B2%D0%B5-chromium-86-%D0%BF%D0%BE%D0%B4-windows-xp-sp3/5685/30",
        "can_translate": false
    },
    {
        "id": 21715,
        "name": "Alexander Gavrilov",
        "username": "dartraiden",
        "avatar_template": "/user_avatar/ntc.party/dartraiden/{size}/15299_2.png",
        "created_at": "2024-01-14T14:11:33.466Z",
        "cooked": "<p>Топикстартер обессрочен в связи с угрозами написать донос в полицию на одного из пользователей.<br>\n(он проделал это с клона, а про основную учётку я только сейчас вспомнил)</p>",
        "post_number": 31,
        "post_type": 1,
        "posts_count": 21,
        "updated_at": "2024-01-14T14:16:38.548Z",
        "reply_count": 0,
        "reply_to_post_number": null,
        "quote_count": 0,
        "incoming_link_count": 0,
        "reads": 36,
        "readers_count": 35,
        "score": 7.2,
        "yours": false,
        "topic_id": 5685,
        "topic_slug": "ntcparty-%D0%BD%D0%B5-%D1%80%D0%B0%D0%B1%D0%BE%D1%82%D0%B0%D0%B5%D1%82-%D0%B2-%D0%BA%D0%B8%D1%82%D0%B0%D0%B9%D1%81%D0%BA%D0%BE%D0%BC-%D1%85%D1%80%D0%BE%D0%BC%D0%BE%D0%BF%D0%BE%D0%B4%D0%BE%D0%B1%D0%BD%D0%BE%D0%BC-%D0%B1%D1%80%D0%B0%D1%83%D0%B7%D0%B5%D1%80%D0%B5-360-extreme-explorer-v13023100-%D0%BD%D0%B0-%D0%BE%D1%81%D0%BD%D0%BE%D0%B2%D0%B5-chromium-86-%D0%BF%D0%BE%D0%B4-windows-xp-sp3",
        "display_username": "Alexander Gavrilov",
        "primary_group_name": null,
        "flair_name": null,
        "flair_url": null,
        "flair_bg_color": null,
        "flair_color": null,
        "flair_group_id": null,
        "badges_granted": [],
        "version": 2,
        "can_edit": false,
        "can_delete": false,
        "can_recover": false,
        "can_see_hidden_post": false,
        "can_wiki": false,
        "read": true,
        "user_title": "",
        "bookmarked": false,
        "actions_summary": [],
        "moderator": true,
        "admin": false,
        "staff": true,
        "user_id": 1450,
        "hidden": false,
        "trust_level": 3,
        "deleted_at": null,
        "user_deleted": false,
        "edit_reason": null,
        "can_view_edit_history": false,
        "wiki": false,
        "post_url": "/t/ntcparty-%D0%BD%D0%B5-%D1%80%D0%B0%D0%B1%D0%BE%D1%82%D0%B0%D0%B5%D1%82-%D0%B2-%D0%BA%D0%B8%D1%82%D0%B0%D0%B9%D1%81%D0%BA%D0%BE%D0%BC-%D1%85%D1%80%D0%BE%D0%BC%D0%BE%D0%BF%D0%BE%D0%B4%D0%BE%D0%B1%D0%BD%D0%BE%D0%BC-%D0%B1%D1%80%D0%B0%D1%83%D0%B7%D0%B5%D1%80%D0%B5-360-extreme-explorer-v13023100-%D0%BD%D0%B0-%D0%BE%D1%81%D0%BD%D0%BE%D0%B2%D0%B5-chromium-86-%D0%BF%D0%BE%D0%B4-windows-xp-sp3/5685/31",
        "can_translate": false
    },
    {
        "id": 21716,
        "name": "Alexander Gavrilov",
        "username": "dartraiden",
        "avatar_template": "/user_avatar/ntc.party/dartraiden/{size}/15299_2.png",
        "created_at": "2024-01-14T14:11:43.906Z",
        "cooked": "",
        "post_number": 32,
        "post_type": 3,
        "posts_count": 21,
        "updated_at": "2024-01-14T14:11:43.906Z",
        "reply_count": 0,
        "reply_to_post_number": null,
        "quote_count": 0,
        "incoming_link_count": 0,
        "reads": 36,
        "readers_count": 35,
        "score": 7.2,
        "yours": false,
        "topic_id": 5685,
        "topic_slug": "ntcparty-%D0%BD%D0%B5-%D1%80%D0%B0%D0%B1%D0%BE%D1%82%D0%B0%D0%B5%D1%82-%D0%B2-%D0%BA%D0%B8%D1%82%D0%B0%D0%B9%D1%81%D0%BA%D0%BE%D0%BC-%D1%85%D1%80%D0%BE%D0%BC%D0%BE%D0%BF%D0%BE%D0%B4%D0%BE%D0%B1%D0%BD%D0%BE%D0%BC-%D0%B1%D1%80%D0%B0%D1%83%D0%B7%D0%B5%D1%80%D0%B5-360-extreme-explorer-v13023100-%D0%BD%D0%B0-%D0%BE%D1%81%D0%BD%D0%BE%D0%B2%D0%B5-chromium-86-%D0%BF%D0%BE%D0%B4-windows-xp-sp3",
        "display_username": "Alexander Gavrilov",
        "primary_group_name": null,
        "flair_name": null,
        "flair_url": null,
        "flair_bg_color": null,
        "flair_color": null,
        "flair_group_id": null,
        "badges_granted": [],
        "version": 1,
        "can_edit": false,
        "can_delete": false,
        "can_recover": false,
        "can_see_hidden_post": false,
        "can_wiki": false,
        "read": true,
        "user_title": "",
        "bookmarked": false,
        "actions_summary": [],
        "moderator": true,
        "admin": false,
        "staff": true,
        "user_id": 1450,
        "hidden": false,
        "trust_level": 3,
        "deleted_at": null,
        "user_deleted": false,
        "edit_reason": null,
        "can_view_edit_history": false,
        "wiki": false,
        "action_code": "closed.enabled",
        "post_url": "/t/ntcparty-%D0%BD%D0%B5-%D1%80%D0%B0%D0%B1%D0%BE%D1%82%D0%B0%D0%B5%D1%82-%D0%B2-%D0%BA%D0%B8%D1%82%D0%B0%D0%B9%D1%81%D0%BA%D0%BE%D0%BC-%D1%85%D1%80%D0%BE%D0%BC%D0%BE%D0%BF%D0%BE%D0%B4%D0%BE%D0%B1%D0%BD%D0%BE%D0%BC-%D0%B1%D1%80%D0%B0%D1%83%D0%B7%D0%B5%D1%80%D0%B5-360-extreme-explorer-v13023100-%D0%BD%D0%B0-%D0%BE%D1%81%D0%BD%D0%BE%D0%B2%D0%B5-chromium-86-%D0%BF%D0%BE%D0%B4-windows-xp-sp3/5685/32",
        "can_translate": false
    }
]